Workbook

Sheet Cover
B2: Harley-Davidson, Inc. (NYSE: HOG) - Short
B3: Squarepoint EDGE Stock Pitch - Financial model | Leen Bou Alia | October 2026
B5: Key outputs
B6: Current price | C6: =Valuation!C19 -> 26.95
B7: Price target (probability-weighted) | C7: =Valuation!C20 -> 21.11034
B8: Expected return to a short | C8: =Valuation!C21 -> 0.21668496
B9: Bear / Base / Bull value per share | C9: =TEXT(Valuation!C15,"$0.00")&" / "&TEXT(Valuation!D15,"$0.00")&" / "&TEXT(Valuation!E15,"$0.00") -> $12.43 / $18.78 / $43.12
B10: FY2026E EPS (Base) vs. consensus $0.68 | C10: =Base!S43 -> 0.55290489
B11: FY2027E EPS (Base) | C11: =Base!T43 -> 0.798078
B12: Signal | C12: =Valuation!C29 -> SHORT supported
B14: Colour legend (per competition prompt)
B15: Reported company data
B16: Formulas & calculations
B17: Participant assumptions
B18: Consensus / market estimates
B20: Structure
B21: Inputs - market data, guidance, common and scenario assumptions (edit red cells only)
B22: Historicals - 8 quarters (Q3'24-Q2'26) transcribed from SEC filings, with sources
B23: Base / Bear / Bull - integrated IS, BS, CF; unit drivers; ROIC; DCF & multiples SOTP (one sheet per scenario)
B24: Quarterly forecast Q3'26-Q4'27 (6 quarters) + annual FY2028E-FY2029E
B25: Assumptions - log of every input (live links) plus structural/methodology assumptions
B26: Valuation - probability-weighted scenarios, price target, comps, EPS & valuation sensitivities
... B29: fitted on Q1'25-Q2'26 (see Inputs). This captures Q4 under-absorption losses and operating leverage.

Sheet Historicals
A1: Harley-Davidson, Inc. - Reported historical data (as reported; $ thousands unless noted)
A2: Blue = reported company data, transcribed from SEC filings (8-K earnings releases and 10-Q). Quarterly cash flows derived as YTD differences. D&A and SBC from 10-Q cash flow statements as compiled by StockAnalysis.
A4: Line item | B4: Unit | C4: Q3'24 | D4: Q4'24 | E4: Q1'25 | F4: Q2'25 | G4: Q3'25 | H4: Q4'25 | I4: Q1'26 | J4: Q2'26
A5: Income statement (segment presentation)
A6: HDMC - Motorcycles revenue | B6: $000 | C6: 615628 | D6: 231470 | E6: 863863 | F6: 778051 | G6: 821864 | H6: 193882 | I6: 836294 | J6: 848057
A7: HDMC - Parts & accessories revenue | B7: $000 | C7: 174301 | D7: 117605 | E7: 143433 | F7: 186874 | G7: 167252 | H7: 116513 | I7: 142243 | J7: 176950
A8: HDMC - Apparel revenue | B8: $000 | C8: 55688 | D8: 54078 | E8: 57322 | F8: 55240 | G8: 56052 | H8: 47169 | I8: 57313 | J8: 56068
A9: HDMC - Licensing revenue | B9: $000 | C9: 3897 | D9: 4436 | E9: 3058 | F9: 5944 | G9: 5547 | H9: 7124 | I9: 6048 | J9: 6298
A10: HDMC - Other revenue | B10: $000 | C10: 26891 | D10: 12900 | E10: 13829 | F10: 17540 | G10: 23244 | H10: 14507 | I10: 13573 | J10: 16907
A11: HDMC gross profit | B11: $000 | C11: 263813 | D11: -3170 | E11: 315244 | F11: 298705 | G11: 283110 | H11: -30467 | I11: 266989 | J11: 304126
A12: HDMC operating expense | B12: $000 | C12: 208676 | D12: 210472 | E12: 198972 | F12: 237389 | G12: 228991 | H12: 229970 | I12: 248064 | J12: 231788
A13: LiveWire revenue | B13: $000 | C13: 4808 | D13: 10400 | E13: 2743 | F13: 6011 | G13: 5563 | H13: 11354 | I13: 5116 | J13: 9114
A14: LiveWire gross profit | B14: $000 | C14: -1180 | D14: -5608 | E14: -1781 | F14: 162 | G14: -2271 | H14: -545 | I14: -535 | J14: -48
A15: LiveWire operating expense | B15: $000 | C15: 24905 | D15: 20538 | E15: 18028 | F15: 18815 | G15: 15910 | H15: 17829 | I15: 17136 | J15: 17879
A16: HDFS revenue | B16: $000 | C16: 269482 | D16: 256720 | E16: 244961 | F16: 257438 | G16: 261188 | H16: 105609 | I16: 111944 | J16: 117043
A17: HDFS operating income | B17: $000 | C17: 76744 | D17: 46440 | E17: 64036 | F17: 69773 | G17: 438820 | H17: -82247 | I17: 22240 | J17: 21599
... A25: Dividends per share | B25: $ | C25: 0.1725 | D25: 0.1725 | E25: 0.18 | F25: 0.18 | G25: 0.18 | H25: 0.18 | I25: 0.1875 | J25: 0.1875
A26: Units
A27: HDMC worldwide shipments | B27: units | C27: 27520 | D27: 14010 | E27: 38601 | F27: 35837 | G27: 36524 | H27: 13515 | I27: 37295 | J27: 39209
A28: Grand American Touring (incl. Trike) | B28: units | C28: 15493 | D28: 5563 | E28: 23678 | F28: 18080 | G28: 22035 | H28: 5459 | I28: 21520 | J28: 19641
A29: Cruiser | B29: units | C29: 9610 | D29: 6524 | E29: 11860 | F29: 13110 | G29: 10551 | H29: 5651 | I29: 10659 | J29: 13550
A30: Sport & Lightweight | B30: units | C30: 1770 | D30: 1508 | E30: 2108 | F30: 3188 | G30: 2628 | H30: 1714 | I30: 3731 | J30: 4617
A31: Adventure Touring | B31: units | C31: 647 | D31: 415 | E31: 955 | F31: 1459 | G31: 1310 | H31: 691 | I31: 1385 | J31: 1401
A32: Retail sales - North America | B32: units | C32: 24573 | D32: 15127 | E32: 20892 | F32: 28931 | G32: 23462 | H32: 15847 | I32: 23803 | J32: 29751
A33: Retail sales - EMEA | B33: units | C33: 6054 | D33: 4749 | E33: 5175 | F33: 7621 | G33: 5033 | H33: 3625 | I33: 5034 | J33: 6959
A34: Retail sales - Asia Pacific | B34: units | C34: 4832 | D34: 5025 | E34: 4362 | F34: 4967 | G34: 4667 | H34: 4979 | I34: 3967 | J34: 4990
A35: Retail sales - Latin America | B35: units | C35: 707 | D35: 759 | E35: 581 | F35: 735 | G35: 822 | H35: 836 | I35: 703 | J35: 767
A36: Global dealer inventory, YoY change | B36: % | G36: -0.13 | H36: -0.17 | I36: -0.22 | J36: -0.17
A37: Balance sheet (period end)
A38: Cash and cash equivalents | B38: $000 | C38: 2243910 | D38: 1589608 | E38: 1931175 | F38: 1587664 | G38: 1775038 | H38: 3091744 | I38: 1805068 | J38: 1895789
A39: Restricted cash (current) | B39: $000 | C39: 147910 | D39: 135661 | E39: 150132 | F39: 149782 | G39: 51530 | H39: 0 | I39: 0 | J39: 0
A40: Accounts receivable, net | B40: $000 | C40: 307701 | D40: 234315 | E40: 313334 | F40: 325756 | G40: 305010 | H40: 225760 | I40: 285786 | J40: 301788
A41: Finance receivables held for sale | B41: $000 | C41: 0 | D41: 0 | E41: 0 | F41: 0 | G41: 4080885 | H41: 264238 | I41: 426792 | J41: 545761
A42: Finance receivables HFI - current | B42: $000 | C42: 2300551 | D42: 2031496 | E42: 2286672 | F42: 2127866 | G42: 1221348 | H42: 981926 | I42: 1187550 | J42: 1094533
A43: Inventories, net | B43: $000 | C43: 681864 | D43: 745793 | E43: 712312 | F43: 630287 | G43: 512186 | H43: 730898 | I43: 622189 | J43: 500935
A44: Other current assets | B44: $000 | C44: 208000 | D44: 259764 | E44: 253687 | F44: 327260 | G44: 297444 | H44: 292383 | I44: 415301 | J44: 250420
A45: Finance receivables HFI - long-term | B45: $000 | C45: 5499836 | D45: 5256798 | E45: 5112935 | F45: 5198356 | G45: 662201 | H45: 719060 | I45: 827061 | J45: 1004886
A46: Other long-term assets (incl. PP&E, pension, goodwill) | B46: $000 | C46: 1636887 | D46: 1628144 | E46: 1622134 | F46: 1703474 | G46: 1660742 | H46: 1738806 | I46: 1675914 | J46: 1651753
A47: Total assets | B47: $000 | C47: 13026659 | D47: 11881579 | E47: 12382381 | F47: 12050445 | G47: 10566384 | H47: 8044815 | I47: 7245661 | J47: 7245865
A48: Accounts payable & accrued liabilities | B48: $000 | C48: 931971 | D48: 892678 | E48: 1105802 | F48: 1040616 | G48: 971411 | H48: 1061194 | I48: 1232554 | J48: 1033420
A49: Short-term deposits | B49: $000 | C49: 178638 | D49: 173099 | E49: 178376 | F49: 243101 | G49: 292667 | H49: 280095 | I49: 248642 | J49: 266421
... A54: Total equity (incl. NCI) | B54: $000 | C54: 3425112 | D54: 3158500 | E54: 3173690 | F54: 3307933 | G54: 3561379 | H54: 3156850 | I54: 3080135 | J54: 3116019
A55: Cash flow (quarterly)
A56: Net cash from operating activities | B56: $000 | C56: 353013 | D56: 133178 | E56: 141534 | F56: 367958 | G56: -92589 | H56: 152019 | I56: -228021 | J56: 168336
A57: Depreciation & amortization | B57: $000 | C57: 39190 | D57: 41110 | E57: 41700 | F57: 40430 | G57: 44210 | H57: 46030 | I57: 44140 | J57: 42560
A58: Stock-based compensation | B58: $000 | C58: 10830 | D58: 9190 | E58: 6820 | F58: 10590 | G58: 8430 | H58: 5910 | I58: 8540 | J58: 9490
A59: Capital expenditures | B59: $000 | C59: -52589 | D59: -56139 | E59: -29973 | F59: -35587 | G59: -36530 | H59: -51589 | I59: -31792 | J59: -12902
A60: Net cash from investing activities | B60: $000 | C60: -89148 | D60: 102847 | E60: 61395 | F60: -151249 | G60: 295331 | H60: 3573298 | I60: -92004 | J60: -174734
A61: Dividends paid | B61: $000 | C61: -22095 | D61: -21770 | E61: -22921 | F61: -21835 | G61: -21532 | H61: -20100 | I61: -21540 | J61: -19671
A62: Repurchase of common stock | B62: $000 | C62: -150135 | D62: -100019 | E62: -93095 | F62: -45 | G62: -100069 | H62: -160061 | I62: -70018 | J62: -30370
A63: Net cash from financing activities | B63: $000 | C63: 131462 | D63: -885775 | E63: 150185 | F63: -566704 | G63: -131156 | H63: -2462625 | I63: -959337 | J63: 100433
A64: FX effect on cash | B64: $000 | C64: 11019 | D64: -16343 | E64: 3299 | F64: 9076 | G64: -1366 | H64: 2484 | I64: -7314 | J64: -3314
A66: Sources by quarter
A67: Q3'24 | B67: 8-K Ex.99.1, Q3'25 release (prior-yr column), sec.gov/Archives/edgar/data/793952/000110465925105891
A68: Q4'24 | B68: 8-K Ex.99.1, Q4'25 release (prior-yr column), sec.gov/Archives/edgar/data/793952/000079395226000004
A69: Q1'25 | B69: 8-K Ex.99.1, Q1'26 release (prior-yr column), sec.gov/Archives/edgar/data/793952/000079395226000029
A70: Q2'25 | B70: 8-K Ex.99.1, Q2'26 release (prior-yr column) / Q2'26 10-Q
A71: Q3'25 | B71: 8-K Ex.99.1, Q3'25 release, sec.gov/Archives/edgar/data/793952/000110465925105891
A72: Q4'25 | B72: 8-K Ex.99.1, Q4'25 release, sec.gov/Archives/edgar/data/793952/000079395226000004
A73: Q1'26 | B73: 8-K Ex.99.1, Q1'26 release, sec.gov/Archives/edgar/data/793952/000079395226000029
A74: Q2'26 | B74: 8-K Ex.99.1 + 10-Q Q2'26, sec.gov/Archives/edgar/data/793952/000079395226000055 / 000079395226000061
A75: Dealer inventory YoY: Q3'25 release ('down 13%'), Q4'25 ('down 17%'), Q1'26 ('down 22%'), Q2'26 ('down 17%').
A76: Q4'25 buybacks exclude $40.0M of repurchases not yet settled (shown separately in FY25 financing cash flow).
A78: Helper: HDMC total revenue ($000) | C78: =C6+C7+C8+C9+C10 -> 876405 | D78: =D6+D7+D8+D9+D10 -> 420489 | E78: =E6+E7+E8+E9+E10 -> 1081505 | F78: =F6+F7+F8+F9+F10 -> 1043649 | G78: =G6+G7+G8+G9+G10 -> 1073959 | H78: =H6+H7+H8+H9+H10 -> 379195 | I78: =I6+I7+I8+I9+I10 -> 1055471 | J78: =J6+J7+J8+J9+J10 -> 1104280

Sheet Inputs
B1: Inputs & assumptions
B2: Red = analyst assumption (edit these) | Purple = consensus / market data | Black = formula
B4: Market & consensus data
B5: HOG share price | C5: $ | E5: 26.95 | G5: Updated 7-Oct-2026 (was $26.19 close 5-Oct per StockAnalysis). Update again on submission day.
B6: Shares outstanding | C6: m | E6: 104.07 | G6: StockAnalysis, latest reported.
B7: Consensus FY2026 EPS | C7: $ | E7: 0.68 | G7: TIKR / Citi upgrade coverage, Oct-2026.
B8: Consensus FY2026 revenue growth | C8: % | E8: 0.06 | G8: TIKR, Oct-2026 (motorcycles & related).
B9: Consensus FY2027 revenue growth | C9: % | E9: 0.04 | G9: TIKR, Oct-2026.
B10: Consensus average price target | C10: $ | E10: 28.18 | G10: StockAnalysis, Oct-2026 (Hold).
B11: Citi price target (upgrade to Buy, 5-Oct-2026) | C11: $ | E11: 33 | G11: Citi Research via GuruFocus/TIKR.
B12: Short interest, % of shares outstanding | C12: % | E12: 0.1779 | G12: StockAnalysis; 11.2 days to cover.
B13: Enterprise value (market) | C13: $m | E13: 3720 | G13: StockAnalysis, 5-Oct-2026.
B14: EV / EBITDA (trailing, market) | C14: x | E14: 8.66 | G14: StockAnalysis, 5-Oct-2026.
B15: Price / book (market) | C15: x | E15: 0.82 | G15: StockAnalysis, 5-Oct-2026 (static; comps table recomputes P/B at current price).
B16: HOG net debt & other claims used in market EV | C16: $m | E16: 990 | G16: EV $3.72bn - mkt cap $2.73bn, StockAnalysis 5-Oct-2026. Held constant when price changes.
... B19: HOG annual dividend per share | C19: $ | E19: 0.75 | G19: 4 x $0.1875 quarterly (Q2'26 8-K).
B21: Company guidance (FY2026, Q2'26 release)
B22: HDMC wholesale shipments - low | C22: units | E22: 133500 | G22: Q2'26 8-K Ex.99.1
B23: HDMC wholesale shipments - high | C23: units | E23: 138500 | G23: Same range guided for retail.
B24: HDMC operating income - low | C24: $m | E24: 10
B25: HDMC operating income - high | C25: $m | E25: 50
B26: Long-term deposits at Jun-26 (in Other LT liabilities) | C26: $m | E26: 250.043 | G26: Q2'26 10-Q balance sheet.
B28: Common assumptions (all scenarios)
B29: Effective tax rate | C29: % | E29: 0.23 | G29: ~FY25 normalised rate.
B30: Other income, net (per quarter) | C30: $m | E30: 12 | G30: H1'26 run-rate ~$12.3m/qtr (pension income).
B31: Investment income (per quarter) | C31: $m | E31: 9 | G31: Lower cash balances after buybacks/debt paydown.
B32: Corporate interest expense (per quarter) | C32: $m | E32: 3.6 | G32: H1'26 run-rate.
B33: D&A (per quarter) | C33: $m | E33: 43 | G33: H1'26 avg $43.4m.
B34: Stock-based compensation (per quarter) | C34: $m | E34: 9 | G34: H1'26 avg $9.0m.
B35: NCI share of LiveWire operating loss | C35: % | E35: 0.05 | G35: H1'26: $1.5m NCI loss / $35.6m LW loss.
B36: FY2026 capex | C36: $m | E36: 190 | G36: Guidance $175-200m; H1'26 actual $44.7m.
B37: Capex per year, FY2027+ | C37: $m | E37: 185
B38: Q3 share of H2'26 shipments | C38: % | E38: 0.6 | G38: Q3'25 was 73% of H2'25 shipments, but Q4'25 was depressed by destocking.
B39: FY2027 shipment seasonality - Q1 | C39: % | E39: 0.28 | G39: Q4 kept low (northern off-season).
B40: FY2027 shipment seasonality - Q2 | C40: % | E40: 0.29
B41: FY2027 shipment seasonality - Q3 | C41: % | E41: 0.26
B42: FY2027 shipment seasonality - Q4 | C42: % | E42: =1-E39-E40-E41 -> 0.17 | G42: Plug so shares sum to 100%.
B43: HDMC fixed manufacturing cost inflation, per year | C43: % | E43: 0.02
B44: Finance receivables growth, per year | C44: % | E44: 0 | G44: Capital-light HDFS: originations sold to KKR/PIMCO vehicle.
B45: Dividend per share growth, per year | C45: % | E45: 0.04 | G45: Recent increases ~4%/yr.
B46: Non-Financial Services entities: cash & equivalents, Jun-26 | C46: $m | E46: 1283.3 | G46: Q2'26 10-Q, Note 17 Supplemental Consolidating Data (HDMC + LiveWire legal entities). Financial Services entities hold the other $612.5m.
B47: Non-Financial Services entities: debt, Jun-26 | C47: $m | E47: 297.342 | G47: Q2'26 10-Q, Note 17: long-term debt only ($300m 4.625% senior notes due 2045); no short-term debt.
B48: HDMC net cash ex-HDFS (valuation) | C48: $m | E48: =E46-E47 -> 985.958 | G48: Cash less debt of the Non-Financial Services entities (Note 17). HDFS cash is captured in HDFS equity value.
B49: Value of LiveWire stake | C49: $m | E49: 50 | G49: LiveWire is loss-making; nominal option value.
B50: Diluted shares for valuation | C50: m | E50: 105 | G50: 104.1m outstanding + ~1m dilution.
B51: DCF: years to mid-FY2027 cash flow | C51: yrs | E51: 0.75 | G51: Valuation date Oct-2026; mid-year convention.
B52: DCF: terminal value timing after last (mid-year) cash flow | C52: yrs | E52: 0.5 | G52: TV discounted from end-FY2029.
B53: DCF: floor industrial EV at zero? (1 = yes) | C53: flag | E53: 1 | G53: Equity holders are not assumed to fund perpetual negative industrial FCF; 0 lets EV go negative.
B54: Expected short return needed for 'SHORT supported' signal | C54: % | E54: 0.15 | G54: Hurdle for a crowded short (18% SI, ~3% dividend carry).
B56: Fitted HDMC cost structure (regression of gross profit on revenue, Q1'25-Q2'26)
B57: Contribution margin (slope) | C57: % | E57: =SLOPE(Historicals!E11:J11,Historicals!E78:J78) -> 0.46742844 | G57: SLOPE of HDMC gross profit vs. HDMC revenue.
B58: Fixed manufacturing cost per quarter (-intercept) | C58: $m | E58: =-INTERCEPT(Historicals!E11:J11,Historicals!E78:J78)/1000 -> 207.40416 | G58: Q4 losses are fixed-cost under-absorption: GP = CM x revenue - fixed cost.
B59: R-squared of fit | E59: =RSQ(Historicals!E11:J11,Historicals!E78:J78) -> 0.98718031
B60: Base motorcycle revenue per unit (H1'26 avg) | C60: $000 | E60: =(Historicals!I6+Historicals!J6)/(Historicals!I27+Historicals!J27)*1000/1000 -> 22.016509 | G60: H1'26 motorcycles revenue / H1'26 shipments.
B61: HDFS funding ratio: (debt + deposits) / finance receivables, Jun-26 | C61: x | E61: =(Historicals!J49+Historicals!J50+Historicals!J51+Historicals!J52+Inputs!$E$26*1000)/(Historicals!J41+Historicals!J42+Historicals!J45) -> 1.0429982
B63: Scenario assumptions
D64: Bear | E64: Base | F64: Bull
B65: Scenario probability | C65: % | D65: 0.4 | E65: 0.4 | F65: 0.2 | G65: Analyst view; must sum to 100%.
B66: Retail growth, H2'26 vs H2'25 | C66: % | D66: -0.03 | E66: 0.04 | F66: 0.08 | G66: H1'26 retail +3.7%. Citi checks: Sept 'up double digits'. Guidance implies FY +0.7% to +4.5%.
B67: Retail growth, FY2027 | C67: % | D67: -0.05 | E67: 0.01 | F67: 0.04 | G67: Touring -13% / cruiser -6% industry-wide in 2025 (MIC). Consumer sentiment -11% YoY.
B68: Retail growth, FY2028 | C68: % | D68: -0.03 | E68: 0 | F68: 0.03
B69: Retail growth, FY2029 | C69: % | D69: -0.02 | E69: 0 | F69: 0.02
B70: FY2026 HDMC shipments | C70: units | D70: 130000 | E70: 136000 | F70: 139000 | G70: Guidance 133.5k-138.5k. H1'26 actual 76,504.
B71: Shipments vs. retail, FY2027 (restock + / destock -) | C71: % | D71: -0.04 | E71: 0.01 | F71: 0.02 | G71: Dealer inventory -17% YoY at Q2'26 (lean). Bear: dealers stay lean as demand fades.
B72: Shipments vs. retail, FY2028 | C72: % | D72: -0.01 | E72: 0 | F72: 0.01
B73: Shipments vs. retail, FY2029 | C73: % | D73: 0 | E73: 0 | F73: 0
B74: Revenue/unit vs. H1'26 avg, H2'26 (price & mix) | C74: % | D74: -0.02 | E74: 0 | F74: 0.01 | G74: Sport & Lightweight shipments +45% YoY in Q2'26: mix moving down-market.
B75: Revenue/unit growth, FY2027 | C75: % | D75: -0.04 | E75: -0.01 | F75: 0 | G75: New lower-priced models launching 2027.
B76: Revenue/unit growth, FY2028 | C76: % | D76: -0.02 | E76: 0 | F76: 0.02
B77: Revenue/unit growth, FY2029 | C77: % | D77: -0.01 | E77: 0.01 | F77: 0.02
B78: Parts & accessories / apparel / other growth, per year | C78: % | D78: -0.05 | E78: -0.01 | F78: 0.03 | G78: P&A -5% YoY in Q2'26 (ageing installed base).
B79: Contribution margin vs. fitted, H2'26 | C79: % | D79: -0.015 | E79: -0.005 | F79: 0.005 | G79: Q2'26 gross margin -108bp YoY; tariffs; memory/commodity costs.
B80: Contribution margin vs. fitted, FY2027+ | C80: % | D80: -0.02 | E80: -0.005 | F80: 0.01 | G80: Lower-priced models dilute unit margin (bear) vs. cost savings (bull).
B81: HDMC operating expense growth, per year | C81: % | D81: 0.02 | E81: 0.01 | F81: 0 | G81: Bull assumes Citi's cost-savings case.
B82: LiveWire operating income, FY2026 | C82: $m | D82: -80 | E82: -75 | F82: -70 | G82: Guidance $(70)-(80)m.
B83: LiveWire operating income, FY2027 | C83: $m | D83: -80 | E83: -65 | F83: -55
B84: LiveWire operating income, FY2028 | C84: $m | D84: -75 | E84: -55 | F84: -40
B85: LiveWire operating income, FY2029 | C85: $m | D85: -70 | E85: -45 | F85: -30
B86: LiveWire revenue growth, per year | C86: % | D86: 0 | E86: 0.2 | F86: 0.4
B87: HDFS operating income, FY2026 | C87: $m | D87: 55 | E87: 60 | F87: 65 | G87: Guidance $55-65m (capital-light model).
B88: HDFS operating income, FY2027 | C88: $m | D88: 50 | E88: 65 | F88: 75
B89: HDFS operating income, FY2028 | C89: $m | D89: 50 | E89: 70 | F89: 85
B90: HDFS operating income, FY2029 | C90: $m | D90: 50 | E90: 72 | F90: 90
B91: HDFS revenue growth, per year | C91: % | D91: -0.02 | E91: 0.03 | F91: 0.06
B92: Share buybacks per quarter | C92: $m | D92: 25 | E92: 40 | F92: 60 | G92: H1'26: $100m.
B93: EV / EBITDA multiple on FY2027E industrial EBITDA | C93: x | D93: 5.5 | E93: 7 | F93: 8 | G93: Peers: PII 9.8x, BRP 8.1x (trailing). Bear = auto-OEM multiple.
B94: P/E on FY2027E HDFS after-tax income | C94: x | D94: 7 | E94: 9 | F94: 11 | G94: Consumer finance peers ~8-11x.
B95: WACC | C95: % | D95: 0.11 | E95: 0.1 | F95: 0.095 | G95: Beta 1.3, ERP 5%, rf 4.2%.
B96: Terminal growth | C96: % | D96: 0 | E96: 0.015 | F96: 0.02
B97: Weight on DCF (vs. multiples) in price target | C97: % | D97: 0.5 | E97: 0.5 | F97: 0.5
B98: Check: probabilities sum to 100% | E98: =SUM(D65:F65) -> 1

Sheet Assumptions
B1: Assumptions log - every input used by the model, with rationale and source
B2: Values link live to the Inputs tab (edit them there). Colour of the value follows the prompt: red = analyst assumption, purple = market/consensus, blue = reported, black = derived.
A4: # | B4: Assumption | C4: Unit | D4: Type | E4: Value / Base | F4: Bear | G4: Base | H4: Bull | I4: Rationale & source
A5: 1 | B5: HOG share price | C5: $ | D5: Market / consensus | E5: =Inputs!E5 -> 26.95 | I5: Updated 7-Oct-2026 (was $26.19 close 5-Oct per StockAnalysis). Update again on submission day.
A6: 2 | B6: Shares outstanding | C6: m | D6: Market / consensus | E6: =Inputs!E6 -> 104.07 | I6: StockAnalysis, latest reported.
A7: 3 | B7: Consensus FY2026 EPS | C7: $ | D7: Market / consensus | E7: =Inputs!E7 -> 0.68 | I7: TIKR / Citi upgrade coverage, Oct-2026.
A8: 4 | B8: Consensus FY2026 revenue growth | C8: % | D8: Market / consensus | E8: =Inputs!E8 -> 0.06 | I8: TIKR, Oct-2026 (motorcycles & related).
A9: 5 | B9: Consensus FY2027 revenue growth | C9: % | D9: Market / consensus | E9: =Inputs!E9 -> 0.04 | I9: TIKR, Oct-2026.
A10: 6 | B10: Consensus average price target | C10: $ | D10: Market / consensus | E10: =Inputs!E10 -> 28.18 | I10: StockAnalysis, Oct-2026 (Hold).
A11: 7 | B11: Citi price target (upgrade to Buy, 5-Oct-2026) | C11: $ | D11: Market / consensus | E11: =Inputs!E11 -> 33 | I11: Citi Research via GuruFocus/TIKR.
A12: 8 | B12: Short interest, % of shares outstanding | C12: % | D12: Market / consensus | E12: =Inputs!E12 -> 0.1779 | I12: StockAnalysis; 11.2 days to cover.
A13: 9 | B13: Enterprise value (market) | C13: $m | D13: Market / consensus | E13: =Inputs!E13 -> 3720 | I13: StockAnalysis, 5-Oct-2026.
A14: 10 | B14: EV / EBITDA (trailing, market) | C14: x | D14: Market / consensus | E14: =Inputs!E14 -> 8.66 | I14: StockAnalysis, 5-Oct-2026.
A15: 11 | B15: Price / book (market) | C15: x | D15: Market / consensus | E15: =Inputs!E15 -> 0.82 | I15: StockAnalysis, 5-Oct-2026 (static; comps table recomputes P/B at current price).
A16: 12 | B16: HOG net debt & other claims used in market EV | C16: $m | D16: Market / consensus | E16: =Inputs!E16 -> 990 | I16: EV $3.72bn - mkt cap $2.73bn, StockAnalysis 5-Oct-2026. Held constant when price changes.
... A19: 15 | B19: HOG annual dividend per share | C19: $ | D19: Reported / guidance | E19: =Inputs!E19 -> 0.75 | I19: 4 x $0.1875 quarterly (Q2'26 8-K).
A20: 16 | B20: HDMC wholesale shipments - low | C20: units | D20: Reported / guidance | E20: =Inputs!E22 -> 133500 | I20: Q2'26 8-K Ex.99.1
A21: 17 | B21: HDMC wholesale shipments - high | C21: units | D21: Reported / guidance | E21: =Inputs!E23 -> 138500 | I21: Same range guided for retail.
A22: 18 | B22: HDMC operating income - low | C22: $m | D22: Reported / guidance | E22: =Inputs!E24 -> 10
A23: 19 | B23: HDMC operating income - high | C23: $m | D23: Reported / guidance | E23: =Inputs!E25 -> 50
A24: 20 | B24: Long-term deposits at Jun-26 (in Other LT liabilities) | C24: $m | D24: Reported / guidance | E24: =Inputs!E26 -> 250.043 | I24: Q2'26 10-Q balance sheet.
A25: 21 | B25: Effective tax rate | C25: % | D25: Analyst assumption | E25: =Inputs!E29 -> 0.23 | I25: ~FY25 normalised rate.
A26: 22 | B26: Other income, net (per quarter) | C26: $m | D26: Analyst assumption | E26: =Inputs!E30 -> 12 | I26: H1'26 run-rate ~$12.3m/qtr (pension income).
A27: 23 | B27: Investment income (per quarter) | C27: $m | D27: Analyst assumption | E27: =Inputs!E31 -> 9 | I27: Lower cash balances after buybacks/debt paydown.
A28: 24 | B28: Corporate interest expense (per quarter) | C28: $m | D28: Analyst assumption | E28: =Inputs!E32 -> 3.6 | I28: H1'26 run-rate.
A29: 25 | B29: D&A (per quarter) | C29: $m | D29: Analyst assumption | E29: =Inputs!E33 -> 43 | I29: H1'26 avg $43.4m.
A30: 26 | B30: Stock-based compensation (per quarter) | C30: $m | D30: Analyst assumption | E30: =Inputs!E34 -> 9 | I30: H1'26 avg $9.0m.
A31: 27 | B31: NCI share of LiveWire operating loss | C31: % | D31: Analyst assumption | E31: =Inputs!E35 -> 0.05 | I31: H1'26: $1.5m NCI loss / $35.6m LW loss.
A32: 28 | B32: FY2026 capex | C32: $m | D32: Analyst assumption | E32: =Inputs!E36 -> 190 | I32: Guidance $175-200m; H1'26 actual $44.7m.
A33: 29 | B33: Capex per year, FY2027+ | C33: $m | D33: Analyst assumption | E33: =Inputs!E37 -> 185
A34: 30 | B34: Q3 share of H2'26 shipments | C34: % | D34: Analyst assumption | E34: =Inputs!E38 -> 0.6 | I34: Q3'25 was 73% of H2'25 shipments, but Q4'25 was depressed by destocking.
A35: 31 | B35: FY2027 shipment seasonality - Q1 | C35: % | D35: Analyst assumption | E35: =Inputs!E39 -> 0.28 | I35: Q4 kept low (northern off-season).
A36: 32 | B36: FY2027 shipment seasonality - Q2 | C36: % | D36: Analyst assumption | E36: =Inputs!E40 -> 0.29
A37: 33 | B37: FY2027 shipment seasonality - Q3 | C37: % | D37: Analyst assumption | E37: =Inputs!E41 -> 0.26
A38: 34 | B38: FY2027 shipment seasonality - Q4 | C38: % | D38: Derived (formula) | E38: =Inputs!E42 -> 0.17 | I38: Plug so shares sum to 100%.
A39: 35 | B39: HDMC fixed manufacturing cost inflation, per year | C39: % | D39: Analyst assumption | E39: =Inputs!E43 -> 0.02
A40: 36 | B40: Finance receivables growth, per year | C40: % | D40: Analyst assumption | E40: =Inputs!E44 -> 0 | I40: Capital-light HDFS: originations sold to KKR/PIMCO vehicle.
A41: 37 | B41: Dividend per share growth, per year | C41: % | D41: Analyst assumption | E41: =Inputs!E45 -> 0.04 | I41: Recent increases ~4%/yr.
A42: 38 | B42: Non-Financial Services entities: cash & equivalents, Jun-26 | C42: $m | D42: Reported / guidance | E42: =Inputs!E46 -> 1283.3 | I42: Q2'26 10-Q, Note 17 Supplemental Consolidating Data (HDMC + LiveWire legal entities). Financial Services entities hold the other $612.5m.
A43: 39 | B43: Non-Financial Services entities: debt, Jun-26 | C43: $m | D43: Reported / guidance | E43: =Inputs!E47 -> 297.342 | I43: Q2'26 10-Q, Note 17: long-term debt only ($300m 4.625% senior notes due 2045); no short-term debt.
A44: 40 | B44: HDMC net cash ex-HDFS (valuation) | C44: $m | D44: Derived (formula) | E44: =Inputs!E48 -> 985.958 | I44: Cash less debt of the Non-Financial Services entities (Note 17). HDFS cash is captured in HDFS equity value.
A45: 41 | B45: Value of LiveWire stake | C45: $m | D45: Analyst assumption | E45: =Inputs!E49 -> 50 | I45: LiveWire is loss-making; nominal option value.
A46: 42 | B46: Diluted shares for valuation | C46: m | D46: Analyst assumption | E46: =Inputs!E50 -> 105 | I46: 104.1m outstanding + ~1m dilution.
A47: 43 | B47: DCF: years to mid-FY2027 cash flow | C47: yrs | D47: Analyst assumption | E47: =Inputs!E51 -> 0.75 | I47: Valuation date Oct-2026; mid-year convention.
A48: 44 | B48: DCF: terminal value timing after last (mid-year) cash flow | C48: yrs | D48: Analyst assumption | E48: =Inputs!E52 -> 0.5 | I48: TV discounted from end-FY2029.
A49: 45 | B49: DCF: floor industrial EV at zero? (1 = yes) | C49: flag | D49: Analyst assumption | E49: =Inputs!E53 -> 1 | I49: Equity holders are not assumed to fund perpetual negative industrial FCF; 0 lets EV go negative.
A50: 46 | B50: Expected short return needed for 'SHORT supported' signal | C50: % | D50: Analyst assumption | E50: =Inputs!E54 -> 0.15 | I50: Hurdle for a crowded short (18% SI, ~3% dividend carry).
A51: 47 | B51: Contribution margin (slope) | C51: % | D51: Derived (formula) | E51: =Inputs!E57 -> 0.46742844 | I51: SLOPE of HDMC gross profit vs. HDMC revenue.
A52: 48 | B52: Fixed manufacturing cost per quarter (-intercept) | C52: $m | D52: Derived (formula) | E52: =Inputs!E58 -> 207.40416 | I52: Q4 losses are fixed-cost under-absorption: GP = CM x revenue - fixed cost.
A53: 49 | B53: R-squared of fit | D53: Derived (formula) | E53: =Inputs!E59 -> 0.98718031
A54: 50 | B54: Base motorcycle revenue per unit (H1'26 avg) | C54: $000 | D54: Derived (formula) | E54: =Inputs!E60 -> 22.016509 | I54: H1'26 motorcycles revenue / H1'26 shipments.
A55: 51 | B55: HDFS funding ratio: (debt + deposits) / finance receivables, Jun-26 | C55: x | D55: Derived (formula) | E55: =Inputs!E61 -> 1.0429982
A56: 52 | B56: Scenario probability | C56: % | D56: Scenario assumption | F56: =Inputs!D65 -> 0.4 | G56: =Inputs!E65 -> 0.4 | H56: =Inputs!F65 -> 0.2 | I56: Analyst view; must sum to 100%.
A57: 53 | B57: Retail growth, H2'26 vs H2'25 | C57: % | D57: Scenario assumption | F57: =Inputs!D66 -> -0.03 | G57: =Inputs!E66 -> 0.04 | H57: =Inputs!F66 -> 0.08 | I57: H1'26 retail +3.7%. Citi checks: Sept 'up double digits'. Guidance implies FY +0.7% to +4.5%.
A58: 54 | B58: Retail growth, FY2027 | C58: % | D58: Scenario assumption | F58: =Inputs!D67 -> -0.05 | G58: =Inputs!E67 -> 0.01 | H58: =Inputs!F67 -> 0.04 | I58: Touring -13% / cruiser -6% industry-wide in 2025 (MIC). Consumer sentiment -11% YoY.
A59: 55 | B59: Retail growth, FY2028 | C59: % | D59: Scenario assumption | F59: =Inputs!D68 -> -0.03 | G59: =Inputs!E68 -> 0 | H59: =Inputs!F68 -> 0.03
A60: 56 | B60: Retail growth, FY2029 | C60: % | D60: Scenario assumption | F60: =Inputs!D69 -> -0.02 | G60: =Inputs!E69 -> 0 | H60: =Inputs!F69 -> 0.02
A61: 57 | B61: FY2026 HDMC shipments | C61: units | D61: Scenario assumption | F61: =Inputs!D70 -> 130000 | G61: =Inputs!E70 -> 136000 | H61: =Inputs!F70 -> 139000 | I61: Guidance 133.5k-138.5k. H1'26 actual 76,504.
A62: 58 | B62: Shipments vs. retail, FY2027 (restock + / destock -) | C62: % | D62: Scenario assumption | F62: =Inputs!D71 -> -0.04 | G62: =Inputs!E71 -> 0.01 | H62: =Inputs!F71 -> 0.02 | I62: Dealer inventory -17% YoY at Q2'26 (lean). Bear: dealers stay lean as demand fades.
A63: 59 | B63: Shipments vs. retail, FY2028 | C63: % | D63: Scenario assumption | F63: =Inputs!D72 -> -0.01 | G63: =Inputs!E72 -> 0 | H63: =Inputs!F72 -> 0.01
A64: 60 | B64: Shipments vs. retail, FY2029 | C64: % | D64: Scenario assumption | F64: =Inputs!D73 -> 0 | G64: =Inputs!E73 -> 0 | H64: =Inputs!F73 -> 0
A65: 61 | B65: Revenue/unit vs. H1'26 avg, H2'26 (price & mix) | C65: % | D65: Scenario assumption | F65: =Inputs!D74 -> -0.02 | G65: =Inputs!E74 -> 0 | H65: =Inputs!F74 -> 0.01 | I65: Sport & Lightweight shipments +45% YoY in Q2'26: mix moving down-market.
A66: 62 | B66: Revenue/unit growth, FY2027 | C66: % | D66: Scenario assumption | F66: =Inputs!D75 -> -0.04 | G66: =Inputs!E75 -> -0.01 | H66: =Inputs!F75 -> 0 | I66: New lower-priced models launching 2027.
A67: 63 | B67: Revenue/unit growth, FY2028 | C67: % | D67: Scenario assumption | F67: =Inputs!D76 -> -0.02 | G67: =Inputs!E76 -> 0 | H67: =Inputs!F76 -> 0.02
A68: 64 | B68: Revenue/unit growth, FY2029 | C68: % | D68: Scenario assumption | F68: =Inputs!D77 -> -0.01 | G68: =Inputs!E77 -> 0.01 | H68: =Inputs!F77 -> 0.02
A69: 65 | B69: Parts & accessories / apparel / other growth, per year | C69: % | D69: Scenario assumption | F69: =Inputs!D78 -> -0.05 | G69: =Inputs!E78 -> -0.01 | H69: =Inputs!F78 -> 0.03 | I69: P&A -5% YoY in Q2'26 (ageing installed base).
A70: 66 | B70: Contribution margin vs. fitted, H2'26 | C70: % | D70: Scenario assumption | F70: =Inputs!D79 -> -0.015 | G70: =Inputs!E79 -> -0.005 | H70: =Inputs!F79 -> 0.005 | I70: Q2'26 gross margin -108bp YoY; tariffs; memory/commodity costs.
A71: 67 | B71: Contribution margin vs. fitted, FY2027+ | C71: % | D71: Scenario assumption | F71: =Inputs!D80 -> -0.02 | G71: =Inputs!E80 -> -0.005 | H71: =Inputs!F80 -> 0.01 | I71: Lower-priced models dilute unit margin (bear) vs. cost savings (bull).
A72: 68 | B72: HDMC operating expense growth, per year | C72: % | D72: Scenario assumption | F72: =Inputs!D81 -> 0.02 | G72: =Inputs!E81 -> 0.01 | H72: =Inputs!F81 -> 0 | I72: Bull assumes Citi's cost-savings case.
A73: 69 | B73: LiveWire operating income, FY2026 | C73: $m | D73: Scenario assumption | F73: =Inputs!D82 -> -80 | G73: =Inputs!E82 -> -75 | H73: =Inputs!F82 -> -70 | I73: Guidance $(70)-(80)m.
A74: 70 | B74: LiveWire operating income, FY2027 | C74: $m | D74: Scenario assumption | F74: =Inputs!D83 -> -80 | G74: =Inputs!E83 -> -65 | H74: =Inputs!F83 -> -55
A75: 71 | B75: LiveWire operating income, FY2028 | C75: $m | D75: Scenario assumption | F75: =Inputs!D84 -> -75 | G75: =Inputs!E84 -> -55 | H75: =Inputs!F84 -> -40
A76: 72 | B76: LiveWire operating income, FY2029 | C76: $m | D76: Scenario assumption | F76: =Inputs!D85 -> -70 | G76: =Inputs!E85 -> -45 | H76: =Inputs!F85 -> -30
A77: 73 | B77: LiveWire revenue growth, per year | C77: % | D77: Scenario assumption | F77: =Inputs!D86 -> 0 | G77: =Inputs!E86 -> 0.2 | H77: =Inputs!F86 -> 0.4
A78: 74 | B78: HDFS operating income, FY2026 | C78: $m | D78: Scenario assumption | F78: =Inputs!D87 -> 55 | G78: =Inputs!E87 -> 60 | H78: =Inputs!F87 -> 65 | I78: Guidance $55-65m (capital-light model).
A79: 75 | B79: HDFS operating income, FY2027 | C79: $m | D79: Scenario assumption | F79: =Inputs!D88 -> 50 | G79: =Inputs!E88 -> 65 | H79: =Inputs!F88 -> 75
A80: 76 | B80: HDFS operating income, FY2028 | C80: $m | D80: Scenario assumption | F80: =Inputs!D89 -> 50 | G80: =Inputs!E89 -> 70 | H80: =Inputs!F89 -> 85
A81: 77 | B81: HDFS operating income, FY2029 | C81: $m | D81: Scenario assumption | F81: =Inputs!D90 -> 50 | G81: =Inputs!E90 -> 72 | H81: =Inputs!F90 -> 90
A82: 78 | B82: HDFS revenue growth, per year | C82: % | D82: Scenario assumption | F82: =Inputs!D91 -> -0.02 | G82: =Inputs!E91 -> 0.03 | H82: =Inputs!F91 -> 0.06
A83: 79 | B83: Share buybacks per quarter | C83: $m | D83: Scenario assumption | F83: =Inputs!D92 -> 25 | G83: =Inputs!E92 -> 40 | H83: =Inputs!F92 -> 60 | I83: H1'26: $100m.
A84: 80 | B84: EV / EBITDA multiple on FY2027E industrial EBITDA | C84: x | D84: Scenario assumption | F84: =Inputs!D93 -> 5.5 | G84: =Inputs!E93 -> 7 | H84: =Inputs!F93 -> 8 | I84: Peers: PII 9.8x, BRP 8.1x (trailing). Bear = auto-OEM multiple.
A85: 81 | B85: P/E on FY2027E HDFS after-tax income | C85: x | D85: Scenario assumption | F85: =Inputs!D94 -> 7 | G85: =Inputs!E94 -> 9 | H85: =Inputs!F94 -> 11 | I85: Consumer finance peers ~8-11x.
A86: 82 | B86: WACC | C86: % | D86: Scenario assumption | F86: =Inputs!D95 -> 0.11 | G86: =Inputs!E95 -> 0.1 | H86: =Inputs!F95 -> 0.095 | I86: Beta 1.3, ERP 5%, rf 4.2%.
A87: 83 | B87: Terminal growth | C87: % | D87: Scenario assumption | F87: =Inputs!D96 -> 0 | G87: =Inputs!E96 -> 0.015 | H87: =Inputs!F96 -> 0.02
A88: 84 | B88: Weight on DCF (vs. multiples) in price target | C88: % | D88: Scenario assumption | F88: =Inputs!D97 -> 0.5 | G88: =Inputs!E97 -> 0.5 | H88: =Inputs!F97 -> 0.5
B90: Structural / methodology assumptions (built into formulas)
B91: HDMC cost structure | D91: Gross profit = contribution margin x HDMC revenue - fixed manufacturing cost per quarter. CM and fixed cost from an OLS fit on Q1'25-Q2'26 (Inputs), plus scenario CM adjustments; fixed cost inflates annually. Explains Q4 losses as under-absorption.
B92: Retail units | D92: Each forecast quarter = same quarter last year x (1 + scenario retail growth for that year); FY2028-29 annual.
B93: Shipments | D93: FY2026 shipments set by scenario (guidance 133.5-138.5k); H2'26 split by the Q3-share input. FY2027+ = retail x (1 + restock/destock factor), spread by the seasonality inputs.
B94: Motorcycle revenue | D94: Shipments x revenue per unit; revenue per unit starts from the H1'26 average and moves with scenario price/mix changes.
B95: Other HDMC revenue | D95: Parts & accessories and apparel/licensing/other grow from the same quarter last year at the scenario rate.
B96: HDMC operating expense | D96: Same quarter last year x (1 + scenario opex growth).
B97: LiveWire | D97: Operating loss set annually by scenario (FY2026 remainder split evenly over Q3/Q4); revenue grows at the scenario rate. NCI absorbs a fixed share of the loss.
B98: HDFS | D98: Operating income set annually by scenario (FY2026 remainder split evenly); revenue grows from the H1'26 average; HDFS expense is the residual.
B99: Below-the-line items | D99: Other income, investment income and interest expense held at fixed quarterly run-rates (not linked to cash balances).
B100: Taxes | D100: Flat effective rate applied to pre-tax income, including tax benefits on losses.
B101: Share count | D101: Diluted shares fall each quarter by buybacks / current share price; no new issuance beyond the SBC already in the base share count.
B102: Dividends | D102: Dividend per share x diluted shares; DPS flat through 2026, then grows at the DPS growth input.
... B110: Market data | D110: Peer multiples and HOG EV/EBITDA, P/E and short interest are static as of 3-6 Oct 2026; the HOG comps row recomputes at the Inputs price.

Sheet Valuation
B1: Valuation summary, scenarios & sensitivities
B3: Probability-weighted scenario analysis | C3: Bear | D3: Base | E3: Bull | F3: Prob.-wtd.
B4: Probability | C4: =Inputs!$D$65 -> 0.4 | D4: =Inputs!$E$65 -> 0.4 | E4: =Inputs!$F$65 -> 0.2 | F4: =SUM(C4:E4) -> 1
B5: FY2027E retail units | C5: =Bear!T6 -> 126793.53 | D5: =Base!T6 -> 138992 | E5: =Bull!T6 -> 145586.15
B6: FY2027E shipments | C6: =Bear!T9 -> 121721.79 | D6: =Base!T9 -> 140381.92 | E6: =Bull!T9 -> 148497.87
B7: FY2027E HDMC revenue ($m) | C7: =Bear!T21 -> 3367.6301 | D7: =Base!T21 -> 3959.1621 | E7: =Bull!T21 -> 4255.8069
B8: FY2027E HDMC gross margin | C8: =Bear!T24 -> 0.19615115 | D8: =Base!T24 -> 0.24869408 | E8: =Bull!T24 -> 0.27859212
B9: FY2027E HDMC operating income ($m) | C9: =Bear!T26 -> -306.38757 | D9: =Base!T26 -> 31.78356 | E9: =Bull!T26 -> 246.82126 | F9: =SUMPRODUCT($C$4:$E$4,C9:E9) -> -60.47735
B10: FY2026E EPS | C10: =Bear!S43 -> -0.23066149 | D10: =Base!S43 -> 0.55290489 | E10: =Bull!S43 -> 1.1123279 | F10: =SUMPRODUCT($C$4:$E$4,C10:E10) -> 0.35136294
B11: FY2027E EPS | C11: =Bear!T43 -> -1.9294901 | D11: =Base!T43 -> 0.798078 | E11: =Bull!T43 -> 2.6564773 | F11: =SUMPRODUCT($C$4:$E$4,C11:E11) -> 0.078730613
B12: FY2027E industrial EBITDA ($m) | C12: =Bear!T49 -> -214.38757 | D12: =Base!T49 -> 138.78356 | E12: =Bull!T49 -> 363.82126
B13: Value per share - multiples SOTP | C13: =Bear!T108 -> 12.432933 | D13: =Base!T108 -> 23.408504 | E13: =Bull!T108 -> 43.635982
B14: Value per share - DCF SOTP | C14: =Bear!T116 -> 12.432933 | D14: =Base!T116 -> 14.156267 | E14: =Bull!T116 -> 42.606146
B15: Scenario value per share (blended) | C15: =Bear!T117 -> 12.432933 | D15: =Base!T117 -> 18.782385 | E15: =Bull!T117 -> 43.121064 | F15: =SUMPRODUCT($C$4:$E$4,C15:E15) -> 21.11034
B16: vs. current price | C16: =Bear!T118 -> -0.53866667 | D16: =Base!T118 -> -0.30306548 | E16: =Bull!T118 -> 0.60003948 | F16: =SUMPRODUCT($C$4:$E$4,C16:E16) -> -0.21668496
B18: Recommendation | C18: Value
B19: Current price | C19: =Inputs!$E$5 -> 26.95
B20: Price target (probability-weighted) | C20: =F15 -> 21.11034
B21: Expected return to a SHORT position (excl. dividends & borrow) | C21: =-(C20/C19-1) -> 0.21668496
B22: Downside to bear case | C22: =C15/Inputs!$E$5-1 -> -0.53866667
B23: Upside to bull case (risk to short) | C23: =E15/Inputs!$E$5-1 -> 0.60003948
B24: Reward / risk (bear downside / bull upside) | C24: =-C22/C23 -> 0.89771871
B25: Dividend carry cost (12m) | C25: =Base!T45/Inputs!$E$5 -> 0.028942486
B26: Consensus average price target | C26: =Inputs!$E$10 -> 28.18
B27: Citi price target | C27: =Inputs!$E$11 -> 33
B28: Model FY2026E EPS (prob.-wtd.) vs. consensus | C28: =F10/Inputs!$E$7-1 -> -0.48328979
B29: Signal | C29: =IF(C21>=Inputs!$E$54,"SHORT supported",IF(C21>0,"Marginal short","Short NOT supported at current price")) -> SHORT supported
B31: Peer comparables (market data, Oct-2026) | C31: Price | D31: Mkt cap $bn | E31: EV $bn | F31: EV/EBITDA | G31: Fwd P/E | H31: P/B | I31: Div. yield
B32: Polaris (PII) | C32: 53.71 | D32: 3.06 | E32: 4.81 | F32: 9.78 | G32: 19.14 | H32: 3.65 | I32: 0.0506
B33: BRP (DOO) | C33: 56.1 | D33: 3.99 | E33: 5.65 | F33: 8.06 | G33: 16.9 | H33: 16.39 | I33: 0.0124
B34: Harley-Davidson (HOG) | C34: =Inputs!$E$5 -> 26.95 | D34: =Inputs!$E$5*Inputs!$E$6/1000 -> 2.8046865 | E34: =D34+Inputs!$E$16/1000 -> 3.7946865 | F34: =E34*1000/Inputs!$E$17 -> 8.8330691 | G34: =Inputs!$E$5/Inputs!$E$18 -> 18.793584 | H34: =Inputs!$E$5*Inputs!$E$6/(Historicals!J54/1000) -> 0.90008646 | I34: =Inputs!$E$19/Inputs!$E$5 -> 0.027829314
B35: Peer average (PII, BRP) | F35: =AVERAGE(F32:F33) -> 8.92 | G35: =AVERAGE(G32:G33) -> 18.02 | H35: =AVERAGE(H32:H33) -> 10.02 | I35: =AVERAGE(I32:I33) -> 0.0315
B36: Peers: StockAnalysis.com (S&P Global data), 3-6 Oct 2026, static. HOG row recomputes at the Inputs price (P/B on Jun-26 total equity). Eicher / Piaggio excluded (non-US listings).
B38: Sensitivity (Base case): FY2027E EPS | D38: Contribution margin vs. Base
B39: FY2027 retail growth (rows) / CM change (cols) | C39: -0.03 | D39: -0.02 | E39: -0.01 | F39: 0 | G39: 0.01 | H39: 0.02
B40: -0.08 | C40: =(Base!$T$41+((Base!$T$21*(1+$B40)/(1+Inputs!$E$67))*(Inputs!$E$57+Inputs!$E$80+C$39)-Base!$T$21*(Inputs!$E$57+Inputs!$E$80))*(1-Inputs!$E$29))/Base!$T$42 -> -1.2524611 | D40: =(Base!$T$41+((Base!$T$21*(1+$B40)/(1+Inputs!$E$67))*(Inputs!$E$57+Inputs!$E$80+D$39)-Base!$T$21*(Inputs!$E$57+Inputs!$E$80))*(1-Inputs!$E$29))/Base!$T$42 -> -0.97991914 | E40: =(Base!$T$41+((Base!$T$21*(1+$B40)/(1+Inputs!$E$67))*(Inputs!$E$57+Inputs!$E$80+E$39)-Base!$T$21*(Inputs!$E$57+Inputs!$E$80))*(1-Inputs!$E$29))/Base!$T$42 -> -0.70737721 | F40: =(Base!$T$41+((Base!$T$21*(1+$B40)/(1+Inputs!$E$67))*(Inputs!$E$57+Inputs!$E$80+F$39)-Base!$T$21*(Inputs!$E$57+Inputs!$E$80))*(1-Inputs!$E$29))/Base!$T$42 -> -0.43483529 | G40: =(Base!$T$41+((Base!$T$21*(1+$B40)/(1+Inputs!$E$67))*(Inputs!$E$57+Inputs!$E$80+G$39)-Base!$T$21*(Inputs!$E$57+Inputs!$E$80))*(1-Inputs!$E$29))/Base!$T$42 -> -0.16229336 | H40: =(Base!$T$41+((Base!$T$21*(1+$B40)/(1+Inputs!$E$67))*(Inputs!$E$57+Inputs!$E$80+H$39)-Base!$T$21*(Inputs!$E$57+Inputs!$E$80))*(1-Inputs!$E$29))/Base!$T$42 -> 0.11024856
B41: -0.05 | C41: =(Base!$T$41+((Base!$T$21*(1+$B41)/(1+Inputs!$E$67))*(Inputs!$E$57+Inputs!$E$80+C$39)-Base!$T$21*(Inputs!$E$57+Inputs!$E$80))*(1-Inputs!$E$29))/Base!$T$42 -> -0.86815167 | D41: =(Base!$T$41+((Base!$T$21*(1+$B41)/(1+Inputs!$E$67))*(Inputs!$E$57+Inputs!$E$80+D$39)-Base!$T$21*(Inputs!$E$57+Inputs!$E$80))*(1-Inputs!$E$29))/Base!$T$42 -> -0.58672251 | E41: =(Base!$T$41+((Base!$T$21*(1+$B41)/(1+Inputs!$E$67))*(Inputs!$E$57+Inputs!$E$80+E$39)-Base!$T$21*(Inputs!$E$57+Inputs!$E$80))*(1-Inputs!$E$29))/Base!$T$42 -> -0.30529335 | F41: =(Base!$T$41+((Base!$T$21*(1+$B41)/(1+Inputs!$E$67))*(Inputs!$E$57+Inputs!$E$80+F$39)-Base!$T$21*(Inputs!$E$57+Inputs!$E$80))*(1-Inputs!$E$29))/Base!$T$42 -> -0.023864191 | G41: =(Base!$T$41+((Base!$T$21*(1+$B41)/(1+Inputs!$E$67))*(Inputs!$E$57+Inputs!$E$80+G$39)-Base!$T$21*(Inputs!$E$57+Inputs!$E$80))*(1-Inputs!$E$29))/Base!$T$42 -> 0.25756497 | H41: =(Base!$T$41+((Base!$T$21*(1+$B41)/(1+Inputs!$E$67))*(Inputs!$E$57+Inputs!$E$80+H$39)-Base!$T$21*(Inputs!$E$57+Inputs!$E$80))*(1-Inputs!$E$29))/Base!$T$42 -> 0.53899413
B42: -0.02 | C42: =(Base!$T$41+((Base!$T$21*(1+$B42)/(1+Inputs!$E$67))*(Inputs!$E$57+Inputs!$E$80+C$39)-Base!$T$21*(Inputs!$E$57+Inputs!$E$80))*(1-Inputs!$E$29))/Base!$T$42 -> -0.48384229 | D42: =(Base!$T$41+((Base!$T$21*(1+$B42)/(1+Inputs!$E$67))*(Inputs!$E$57+Inputs!$E$80+D$39)-Base!$T$21*(Inputs!$E$57+Inputs!$E$80))*(1-Inputs!$E$29))/Base!$T$42 -> -0.19352589 | E42: =(Base!$T$41+((Base!$T$21*(1+$B42)/(1+Inputs!$E$67))*(Inputs!$E$57+Inputs!$E$80+E$39)-Base!$T$21*(Inputs!$E$57+Inputs!$E$80))*(1-Inputs!$E$29))/Base!$T$42 -> 0.096790509 | F42: =(Base!$T$41+((Base!$T$21*(1+$B42)/(1+Inputs!$E$67))*(Inputs!$E$57+Inputs!$E$80+F$39)-Base!$T$21*(Inputs!$E$57+Inputs!$E$80))*(1-Inputs!$E$29))/Base!$T$42 -> 0.38710691 | G42: =(Base!$T$41+((Base!$T$21*(1+$B42)/(1+Inputs!$E$67))*(Inputs!$E$57+Inputs!$E$80+G$39)-Base!$T$21*(Inputs!$E$57+Inputs!$E$80))*(1-Inputs!$E$29))/Base!$T$42 -> 0.6774233 | H42: =(Base!$T$41+((Base!$T$21*(1+$B42)/(1+Inputs!$E$67))*(Inputs!$E$57+Inputs!$E$80+H$39)-Base!$T$21*(Inputs!$E$57+Inputs!$E$80))*(1-Inputs!$E$29))/Base!$T$42 -> 0.9677397
B43: 0.01 | C43: =(Base!$T$41+((Base!$T$21*(1+$B43)/(1+Inputs!$E$67))*(Inputs!$E$57+Inputs!$E$80+C$39)-Base!$T$21*(Inputs!$E$57+Inputs!$E$80))*(1-Inputs!$E$29))/Base!$T$42 -> -0.099532899 | D43: =(Base!$T$41+((Base!$T$21*(1+$B43)/(1+Inputs!$E$67))*(Inputs!$E$57+Inputs!$E$80+D$39)-Base!$T$21*(Inputs!$E$57+Inputs!$E$80))*(1-Inputs!$E$29))/Base!$T$42 -> 0.19967074 | E43: =(Base!$T$41+((Base!$T$21*(1+$B43)/(1+Inputs!$E$67))*(Inputs!$E$57+Inputs!$E$80+E$39)-Base!$T$21*(Inputs!$E$57+Inputs!$E$80))*(1-Inputs!$E$29))/Base!$T$42 -> 0.49887437 | F43: =(Base!$T$41+((Base!$T$21*(1+$B43)/(1+Inputs!$E$67))*(Inputs!$E$57+Inputs!$E$80+F$39)-Base!$T$21*(Inputs!$E$57+Inputs!$E$80))*(1-Inputs!$E$29))/Base!$T$42 -> 0.798078 | G43: =(Base!$T$41+((Base!$T$21*(1+$B43)/(1+Inputs!$E$67))*(Inputs!$E$57+Inputs!$E$80+G$39)-Base!$T$21*(Inputs!$E$57+Inputs!$E$80))*(1-Inputs!$E$29))/Base!$T$42 -> 1.0972816 | H43: =(Base!$T$41+((Base!$T$21*(1+$B43)/(1+Inputs!$E$67))*(Inputs!$E$57+Inputs!$E$80+H$39)-Base!$T$21*(Inputs!$E$57+Inputs!$E$80))*(1-Inputs!$E$29))/Base!$T$42 -> 1.3964853
B44: 0.04 | C44: =(Base!$T$41+((Base!$T$21*(1+$B44)/(1+Inputs!$E$67))*(Inputs!$E$57+Inputs!$E$80+C$39)-Base!$T$21*(Inputs!$E$57+Inputs!$E$80))*(1-Inputs!$E$29))/Base!$T$42 -> 0.28477649 | D44: =(Base!$T$41+((Base!$T$21*(1+$B44)/(1+Inputs!$E$67))*(Inputs!$E$57+Inputs!$E$80+D$39)-Base!$T$21*(Inputs!$E$57+Inputs!$E$80))*(1-Inputs!$E$29))/Base!$T$42 -> 0.59286736 | E44: =(Base!$T$41+((Base!$T$21*(1+$B44)/(1+Inputs!$E$67))*(Inputs!$E$57+Inputs!$E$80+E$39)-Base!$T$21*(Inputs!$E$57+Inputs!$E$80))*(1-Inputs!$E$29))/Base!$T$42 -> 0.90095823 | F44: =(Base!$T$41+((Base!$T$21*(1+$B44)/(1+Inputs!$E$67))*(Inputs!$E$57+Inputs!$E$80+F$39)-Base!$T$21*(Inputs!$E$57+Inputs!$E$80))*(1-Inputs!$E$29))/Base!$T$42 -> 1.2090491 | G44: =(Base!$T$41+((Base!$T$21*(1+$B44)/(1+Inputs!$E$67))*(Inputs!$E$57+Inputs!$E$80+G$39)-Base!$T$21*(Inputs!$E$57+Inputs!$E$80))*(1-Inputs!$E$29))/Base!$T$42 -> 1.51714 | H44: =(Base!$T$41+((Base!$T$21*(1+$B44)/(1+Inputs!$E$67))*(Inputs!$E$57+Inputs!$E$80+H$39)-Base!$T$21*(Inputs!$E$57+Inputs!$E$80))*(1-Inputs!$E$29))/Base!$T$42 -> 1.8252308
B45: 0.07 | C45: =(Base!$T$41+((Base!$T$21*(1+$B45)/(1+Inputs!$E$67))*(Inputs!$E$57+Inputs!$E$80+C$39)-Base!$T$21*(Inputs!$E$57+Inputs!$E$80))*(1-Inputs!$E$29))/Base!$T$42 -> 0.66908588 | D45: =(Base!$T$41+((Base!$T$21*(1+$B45)/(1+Inputs!$E$67))*(Inputs!$E$57+Inputs!$E$80+D$39)-Base!$T$21*(Inputs!$E$57+Inputs!$E$80))*(1-Inputs!$E$29))/Base!$T$42 -> 0.98606398 | E45: =(Base!$T$41+((Base!$T$21*(1+$B45)/(1+Inputs!$E$67))*(Inputs!$E$57+Inputs!$E$80+E$39)-Base!$T$21*(Inputs!$E$57+Inputs!$E$80))*(1-Inputs!$E$29))/Base!$T$42 -> 1.3030421 | F45: =(Base!$T$41+((Base!$T$21*(1+$B45)/(1+Inputs!$E$67))*(Inputs!$E$57+Inputs!$E$80+F$39)-Base!$T$21*(Inputs!$E$57+Inputs!$E$80))*(1-Inputs!$E$29))/Base!$T$42 -> 1.6200202 | G45: =(Base!$T$41+((Base!$T$21*(1+$B45)/(1+Inputs!$E$67))*(Inputs!$E$57+Inputs!$E$80+G$39)-Base!$T$21*(Inputs!$E$57+Inputs!$E$80))*(1-Inputs!$E$29))/Base!$T$42 -> 1.9369983 | H45: =(Base!$T$41+((Base!$T$21*(1+$B45)/(1+Inputs!$E$67))*(Inputs!$E$57+Inputs!$E$80+H$39)-Base!$T$21*(Inputs!$E$57+Inputs!$E$80))*(1-Inputs!$E$29))/Base!$T$42 -> 2.2539764
B46: Revenue scaled with retail growth; incremental gross profit taxed; opex and fixed cost held at Base.
B48: Sensitivity (Base case): multiples-SOTP value/share | D48: EV / EBITDA multiple
B49: HDMC net cash $m (rows) / multiple (cols) | C49: 5 | D49: 6 | E49: 7 | F49: 8 | G49: 9 | H49: 10
B50: 600 | C50: =(MAX(0,Base!$T$100*C$49)+Base!$T$104+Base!$T$105+$B50)/Inputs!$E$50 -> 17.089217 | D50: =(MAX(0,Base!$T$100*D$49)+Base!$T$104+Base!$T$105+$B50)/Inputs!$E$50 -> 18.410965 | E50: =(MAX(0,Base!$T$100*E$49)+Base!$T$104+Base!$T$105+$B50)/Inputs!$E$50 -> 19.732714 | F50: =(MAX(0,Base!$T$100*F$49)+Base!$T$104+Base!$T$105+$B50)/Inputs!$E$50 -> 21.054462 | G50: =(MAX(0,Base!$T$100*G$49)+Base!$T$104+Base!$T$105+$B50)/Inputs!$E$50 -> 22.37621 | H50: =(MAX(0,Base!$T$100*H$49)+Base!$T$104+Base!$T$105+$B50)/Inputs!$E$50 -> 23.697958
B51: 900 | C51: =(MAX(0,Base!$T$100*C$49)+Base!$T$104+Base!$T$105+$B51)/Inputs!$E$50 -> 19.94636 | D51: =(MAX(0,Base!$T$100*D$49)+Base!$T$104+Base!$T$105+$B51)/Inputs!$E$50 -> 21.268108 | E51: =(MAX(0,Base!$T$100*E$49)+Base!$T$104+Base!$T$105+$B51)/Inputs!$E$50 -> 22.589856 | F51: =(MAX(0,Base!$T$100*F$49)+Base!$T$104+Base!$T$105+$B51)/Inputs!$E$50 -> 23.911605 | G51: =(MAX(0,Base!$T$100*G$49)+Base!$T$104+Base!$T$105+$B51)/Inputs!$E$50 -> 25.233353 | H51: =(MAX(0,Base!$T$100*H$49)+Base!$T$104+Base!$T$105+$B51)/Inputs!$E$50 -> 26.555101
B52: 1200 | C52: =(MAX(0,Base!$T$100*C$49)+Base!$T$104+Base!$T$105+$B52)/Inputs!$E$50 -> 22.803503 | D52: =(MAX(0,Base!$T$100*D$49)+Base!$T$104+Base!$T$105+$B52)/Inputs!$E$50 -> 24.125251 | E52: =(MAX(0,Base!$T$100*E$49)+Base!$T$104+Base!$T$105+$B52)/Inputs!$E$50 -> 25.446999 | F52: =(MAX(0,Base!$T$100*F$49)+Base!$T$104+Base!$T$105+$B52)/Inputs!$E$50 -> 26.768747 | G52: =(MAX(0,Base!$T$100*G$49)+Base!$T$104+Base!$T$105+$B52)/Inputs!$E$50 -> 28.090496 | H52: =(MAX(0,Base!$T$100*H$49)+Base!$T$104+Base!$T$105+$B52)/Inputs!$E$50 -> 29.412244
B53: 1500 | C53: =(MAX(0,Base!$T$100*C$49)+Base!$T$104+Base!$T$105+$B53)/Inputs!$E$50 -> 25.660646 | D53: =(MAX(0,Base!$T$100*D$49)+Base!$T$104+Base!$T$105+$B53)/Inputs!$E$50 -> 26.982394 | E53: =(MAX(0,Base!$T$100*E$49)+Base!$T$104+Base!$T$105+$B53)/Inputs!$E$50 -> 28.304142 | F53: =(MAX(0,Base!$T$100*F$49)+Base!$T$104+Base!$T$105+$B53)/Inputs!$E$50 -> 29.62589 | G53: =(MAX(0,Base!$T$100*G$49)+Base!$T$104+Base!$T$105+$B53)/Inputs!$E$50 -> 30.947639 | H53: =(MAX(0,Base!$T$100*H$49)+Base!$T$104+Base!$T$105+$B53)/Inputs!$E$50 -> 32.269387
B54: 1800 | C54: =(MAX(0,Base!$T$100*C$49)+Base!$T$104+Base!$T$105+$B54)/Inputs!$E$50 -> 28.517789 | D54: =(MAX(0,Base!$T$100*D$49)+Base!$T$104+Base!$T$105+$B54)/Inputs!$E$50 -> 29.839537 | E54: =(MAX(0,Base!$T$100*E$49)+Base!$T$104+Base!$T$105+$B54)/Inputs!$E$50 -> 31.161285 | F54: =(MAX(0,Base!$T$100*F$49)+Base!$T$104+Base!$T$105+$B54)/Inputs!$E$50 -> 32.483033 | G54: =(MAX(0,Base!$T$100*G$49)+Base!$T$104+Base!$T$105+$B54)/Inputs!$E$50 -> 33.804781 | H54: =(MAX(0,Base!$T$100*H$49)+Base!$T$104+Base!$T$105+$B54)/Inputs!$E$50 -> 35.12653
B56: Sensitivity: probability-weighted price target | D56: Bull-case probability
B57: Bear probability (rows) / Bull probability (cols); Base = remainder | C57: 0.1 | D57: 0.15 | E57: 0.2 | F57: 0.25 | G57: 0.3
B58: 0.2 | C58: =$B58*$C$15+C$57*$E$15+(1-$B58-C$57)*$D$15 -> 19.946363 | D58: =$B58*$C$15+D$57*$E$15+(1-$B58-D$57)*$D$15 -> 21.163297 | E58: =$B58*$C$15+E$57*$E$15+(1-$B58-E$57)*$D$15 -> 22.380231 | F58: =$B58*$C$15+F$57*$E$15+(1-$B58-F$57)*$D$15 -> 23.597165 | G58: =$B58*$C$15+G$57*$E$15+(1-$B58-G$57)*$D$15 -> 24.814099
B59: 0.3 | C59: =$B59*$C$15+C$57*$E$15+(1-$B59-C$57)*$D$15 -> 19.311418 | D59: =$B59*$C$15+D$57*$E$15+(1-$B59-D$57)*$D$15 -> 20.528352 | E59: =$B59*$C$15+E$57*$E$15+(1-$B59-E$57)*$D$15 -> 21.745285 | F59: =$B59*$C$15+F$57*$E$15+(1-$B59-F$57)*$D$15 -> 22.962219 | G59: =$B59*$C$15+G$57*$E$15+(1-$B59-G$57)*$D$15 -> 24.179153
B60: 0.4 | C60: =$B60*$C$15+C$57*$E$15+(1-$B60-C$57)*$D$15 -> 18.676472 | D60: =$B60*$C$15+D$57*$E$15+(1-$B60-D$57)*$D$15 -> 19.893406 | E60: =$B60*$C$15+E$57*$E$15+(1-$B60-E$57)*$D$15 -> 21.11034 | F60: =$B60*$C$15+F$57*$E$15+(1-$B60-F$57)*$D$15 -> 22.327274 | G60: =$B60*$C$15+G$57*$E$15+(1-$B60-G$57)*$D$15 -> 23.544208
B61: 0.5 | C61: =$B61*$C$15+C$57*$E$15+(1-$B61-C$57)*$D$15 -> 18.041527 | D61: =$B61*$C$15+D$57*$E$15+(1-$B61-D$57)*$D$15 -> 19.258461 | E61: =$B61*$C$15+E$57*$E$15+(1-$B61-E$57)*$D$15 -> 20.475395 | F61: =$B61*$C$15+F$57*$E$15+(1-$B61-F$57)*$D$15 -> 21.692329 | G61: =$B61*$C$15+G$57*$E$15+(1-$B61-G$57)*$D$15 -> 22.909263
B62: 0.6 | C62: =$B62*$C$15+C$57*$E$15+(1-$B62-C$57)*$D$15 -> 17.406582 | D62: =$B62*$C$15+D$57*$E$15+(1-$B62-D$57)*$D$15 -> 18.623516 | E62: =$B62*$C$15+E$57*$E$15+(1-$B62-E$57)*$D$15 -> 19.84045 | F62: =$B62*$C$15+F$57*$E$15+(1-$B62-F$57)*$D$15 -> 21.057384 | G62: =$B62*$C$15+G$57*$E$15+(1-$B62-G$57)*$D$15 -> 22.274318
B63: Note: in Base/Bear the industrial DCF is floored at zero (Inputs flag); value then rests on HDFS + net cash.

Sheet Base
A1: Harley-Davidson (HOG) - integrated model: BASE CASE ($ millions unless noted)
A2: Blue = reported | Black = formula | Red = assumption (see Inputs) | Purple = consensus/market. Shaded columns = forecast.
C4: Q3'24 | D4: Q4'24 | E4: Q1'25 | F4: Q2'25 | G4: Q3'25 | H4: Q4'25 | I4: Q1'26 | J4: Q2'26 | K4: Q3'26E | L4: Q4'26E | M4: Q1'27E | N4: Q2'27E | O4: Q3'27E | P4: Q4'27E | R4: FY2025A | S4: FY2026E | T4: FY2027E | U4: FY2028E | V4: FY2029E
A5: Unit drivers
A6: Retail sales - worldwide | B6: units | C6: =Historicals!C32+Historicals!C33+Historicals!C34+Historicals!C35 -> 36166 | D6: =Historicals!D32+Historicals!D33+Historicals!D34+Historicals!D35 -> 25660 | E6: =Historicals!E32+Historicals!E33+Historicals!E34+Historicals!E35 -> 31010 | F6: =Historicals!F32+Historicals!F33+Historicals!F34+Historicals!F35 -> 42254 | G6: =Historicals!G32+Historicals!G33+Historicals!G34+Historicals!G35 -> 33984 | H6: =Historicals!H32+Historicals!H33+Historicals!H34+Historicals!H35 -> 25287 | I6: =Historicals!I32+Historicals!I33+Historicals!I34+Historicals!I35 -> 33507 | J6: =Historicals!J32+Historicals!J33+Historicals!J34+Historicals!J35 -> 42467 | K6: =G6*(1+Inputs!$E$66) -> 35343.36 | L6: =H6*(1+Inputs!$E$66) -> 26298.48 | M6: =I6*(1+Inputs!$E$67) -> 33842.07 | N6: =J6*(1+Inputs!$E$67) -> 42891.67 | O6: =K6*(1+Inputs!$E$67) -> 35696.794 | P6: =L6*(1+Inputs!$E$67) -> 26561.465 | R6: =SUM(E6:H6) -> 132535 | S6: =SUM(I6:L6) -> 137615.84 | T6: =SUM(M6:P6) -> 138992 | U6: =T6*(1+Inputs!$E$68) -> 138992 | V6: =U6*(1+Inputs!$E$69) -> 138992
A7: of which North America | B7: units | C7: =Historicals!C32 -> 24573 | D7: =Historicals!D32 -> 15127 | E7: =Historicals!E32 -> 20892 | F7: =Historicals!F32 -> 28931 | G7: =Historicals!G32 -> 23462 | H7: =Historicals!H32 -> 15847 | I7: =Historicals!I32 -> 23803 | J7: =Historicals!J32 -> 29751 | R7: =SUM(E7:H7) -> 89132
A8: Retail growth YoY | B8: % | G8: =G6/C6-1 -> -0.060332909 | H8: =H6/D6-1 -> -0.014536243 | I8: =I6/E6-1 -> 0.080522412 | J8: =J6/F6-1 -> 0.0050409429 | K8: =K6/G6-1 -> 0.04 | L8: =L6/H6-1 -> 0.04 | M8: =M6/I6-1 -> 0.01 | N8: =N6/J6-1 -> 0.01 | ... P8: =P6/L6-1 -> 0.01 | S8: =S6/R6-1 -> 0.038335836 | T8: =T6/S6-1 -> 0.01 | U8: =U6/T6-1 -> 0 | V8: =V6/U6-1 -> 0
A9: HDMC shipments - worldwide | B9: units | C9: =Historicals!C27 -> 27520 | D9: =Historicals!D27 -> 14010 | E9: =Historicals!E27 -> 38601 | F9: =Historicals!F27 -> 35837 | G9: =Historicals!G27 -> 36524 | H9: =Historicals!H27 -> 13515 | I9: =Historicals!I27 -> 37295 | J9: =Historicals!J27 -> 39209 | K9: =(Inputs!$E$70-I9-J9)*Inputs!$E$38 -> 35697.6 | L9: =Inputs!$E$70-I9-J9-K9 -> 23798.4 | M9: =$T9*Inputs!$E$39 -> 39306.937 | N9: =$T9*Inputs!$E$40 -> 40710.756 | O9: =$T9*Inputs!$E$41 -> 36499.299 | P9: =$T9*Inputs!$E$42 -> 23864.926 | R9: =SUM(E9:H9) -> 124477 | S9: =SUM(I9:L9) -> 136000 | T9: =T6*(1+Inputs!$E$71) -> 140381.92 | U9: =U6*(1+Inputs!$E$72) -> 138992 | V9: =V6*(1+Inputs!$E$73) -> 138992
A10: Shipment growth YoY | B10: % | G10: =G9/C9-1 -> 0.32718023 | H10: =H9/D9-1 -> -0.035331906 | I10: =I9/E9-1 -> -0.03383332 | J10: =J9/F9-1 -> 0.094092697 | K10: =K9/G9-1 -> -0.022626218 | L10: =L9/H9-1 -> 0.7608879 | M10: =M9/I9-1 -> 0.053946565 | N10: =N9/J9-1 -> 0.038301317 | ... P10: =P9/L9-1 -> 0.0027954033 | S10: =S9/R9-1 -> 0.092571318 | T10: =T9/S9-1 -> 0.032219988 | U10: =U9/T9-1 -> -0.0099009901 | V10: =V9/U9-1 -> 0
A11: Implied dealer inventory change (shipments - retail) | B11: units | C11: =C9-C6 -> -8646 | D11: =D9-D6 -> -11650 | E11: =E9-E6 -> 7591 | F11: =F9-F6 -> -6417 | G11: =G9-G6 -> 2540 | H11: =H9-H6 -> -11772 | I11: =I9-I6 -> 3788 | J11: =J9-J6 -> -3258 | ... P11: =P9-P6 -> -2696.5387 | R11: =R9-R6 -> -8058 | S11: =S9-S6 -> -1615.84 | T11: =T9-T6 -> 1389.92 | U11: =U9-U6 -> 0 | V11: =V9-V6 -> 0
A12: Reported global dealer inventory, YoY | B12: % | G12: =Historicals!G36 -> -0.13 | H12: =Historicals!H36 -> -0.17 | I12: =Historicals!I36 -> -0.22 | J12: =Historicals!J36 -> -0.17
A13: Sport & Lightweight share of shipments | B13: % | C13: =Historicals!C30/Historicals!C27 -> 0.06431686 | D13: =Historicals!D30/Historicals!D27 -> 0.1076374 | E13: =Historicals!E30/Historicals!E27 -> 0.054609984 | F13: =Historicals!F30/Historicals!F27 -> 0.088958339 | G13: =Historicals!G30/Historicals!G27 -> 0.071952689 | H13: =Historicals!H30/Historicals!H27 -> 0.12682205 | I13: =Historicals!I30/Historicals!I27 -> 0.10004022 | J13: =Historicals!J30/Historicals!J27 -> 0.11775358
A14: Touring share of shipments | B14: % | C14: =Historicals!C28/Historicals!C27 -> 0.56297238 | D14: =Historicals!D28/Historicals!D27 -> 0.39707352 | E14: =Historicals!E28/Historicals!E27 -> 0.6134038 | F14: =Historicals!F28/Historicals!F27 -> 0.50450652 | G14: =Historicals!G28/Historicals!G27 -> 0.60330194 | H14: =Historicals!H28/Historicals!H27 -> 0.40392157 | I14: =Historicals!I28/Historicals!I27 -> 0.57702105 | J14: =Historicals!J28/Historicals!J27 -> 0.50093091
A16: Income statement
A17: Motorcycle revenue per unit | B17: $000 | C17: =Historicals!C6/Historicals!C27 -> 22.370203 | D17: =Historicals!D6/Historicals!D27 -> 16.52177 | E17: =Historicals!E6/Historicals!E27 -> 22.379291 | F17: =Historicals!F6/Historicals!F27 -> 21.71083 | G17: =Historicals!G6/Historicals!G27 -> 22.502026 | H17: =Historicals!H6/Historicals!H27 -> 14.34569 | I17: =Historicals!I6/Historicals!I27 -> 22.423757 | J17: =Historicals!J6/Historicals!J27 -> 21.629141 | K17: =Inputs!$E$60*(1+Inputs!$E$74) -> 22.016509 | L17: =Inputs!$E$60*(1+Inputs!$E$74) -> 22.016509 | M17: =$K17*(1+Inputs!$E$75) -> 21.796344 | N17: =$K17*(1+Inputs!$E$75) -> 21.796344 | O17: =$K17*(1+Inputs!$E$75) -> 21.796344 | P17: =$K17*(1+Inputs!$E$75) -> 21.796344 | R17: =R18/R9*1000 -> 21.350611 | S17: =S18/S9*1000 -> 22.016509 | T17: =T18/T9*1000 -> 21.796344 | U17: =T17*(1+Inputs!$E$76) -> 21.796344 | V17: =U17*(1+Inputs!$E$77) -> 22.014307
A18: HDMC - Motorcycles revenue | B18: $m | C18: =Historicals!C6/1000 -> 615.628 | D18: =Historicals!D6/1000 -> 231.47 | E18: =Historicals!E6/1000 -> 863.863 | F18: =Historicals!F6/1000 -> 778.051 | G18: =Historicals!G6/1000 -> 821.864 | H18: =Historicals!H6/1000 -> 193.882 | I18: =Historicals!I6/1000 -> 836.294 | J18: =Historicals!J6/1000 -> 848.057 | K18: =K9*K17/1000 -> 785.93653 | L18: =L9*L17/1000 -> 523.95769 | M18: =M9*M17/1000 -> 856.74752 | N18: =N9*N17/1000 -> 887.34564 | O18: =O9*O17/1000 -> 795.55127 | P18: =P9*P17/1000 -> 520.16814 | R18: =SUM(E18:H18) -> 2657.66 | S18: =SUM(I18:L18) -> 2994.2452 | T18: =SUM(M18:P18) -> 3059.8126 | U18: =U9*U17/1000 -> 3029.5174 | V18: =V9*V17/1000 -> 3059.8126
A19: HDMC - Parts & accessories | B19: $m | C19: =(Historicals!C7)/1000 -> 174.301 | D19: =(Historicals!D7)/1000 -> 117.605 | E19: =(Historicals!E7)/1000 -> 143.433 | F19: =(Historicals!F7)/1000 -> 186.874 | G19: =(Historicals!G7)/1000 -> 167.252 | H19: =(Historicals!H7)/1000 -> 116.513 | I19: =(Historicals!I7)/1000 -> 142.243 | J19: =(Historicals!J7)/1000 -> 176.95 | K19: =G19*(1+Inputs!$E$78) -> 165.57948 | L19: =H19*(1+Inputs!$E$78) -> 115.34787 | M19: =I19*(1+Inputs!$E$78) -> 140.82057 | N19: =J19*(1+Inputs!$E$78) -> 175.1805 | O19: =K19*(1+Inputs!$E$78) -> 163.92369 | P19: =L19*(1+Inputs!$E$78) -> 114.19439 | R19: =SUM(E19:H19) -> 614.072 | S19: =SUM(I19:L19) -> 600.12035 | T19: =SUM(M19:P19) -> 594.11915 | U19: =T19*(1+Inputs!$E$78) -> 588.17796 | V19: =U19*(1+Inputs!$E$78) -> 582.29618
A20: HDMC - Apparel, licensing & other | B20: $m | C20: =(Historicals!C8+Historicals!C9+Historicals!C10)/1000 -> 86.476 | D20: =(Historicals!D8+Historicals!D9+Historicals!D10)/1000 -> 71.414 | E20: =(Historicals!E8+Historicals!E9+Historicals!E10)/1000 -> 74.209 | F20: =(Historicals!F8+Historicals!F9+Historicals!F10)/1000 -> 78.724 | G20: =(Historicals!G8+Historicals!G9+Historicals!G10)/1000 -> 84.843 | H20: =(Historicals!H8+Historicals!H9+Historicals!H10)/1000 -> 68.8 | I20: =(Historicals!I8+Historicals!I9+Historicals!I10)/1000 -> 76.934 | J20: =(Historicals!J8+Historicals!J9+Historicals!J10)/1000 -> 79.273 | K20: =G20*(1+Inputs!$E$78) -> 83.99457 | L20: =H20*(1+Inputs!$E$78) -> 68.112 | M20: =I20*(1+Inputs!$E$78) -> 76.16466 | N20: =J20*(1+Inputs!$E$78) -> 78.48027 | O20: =K20*(1+Inputs!$E$78) -> 83.154624 | P20: =L20*(1+Inputs!$E$78) -> 67.43088 | R20: =SUM(E20:H20) -> 306.576 | S20: =SUM(I20:L20) -> 308.31357 | T20: =SUM(M20:P20) -> 305.23043 | U20: =T20*(1+Inputs!$E$78) -> 302.17813 | V20: =U20*(1+Inputs!$E$78) -> 299.15635
A21: HDMC revenue | B21: $m | C21: =C18+C19+C20 -> 876.405 | D21: =D18+D19+D20 -> 420.489 | E21: =E18+E19+E20 -> 1081.505 | F21: =F18+F19+F20 -> 1043.649 | G21: =G18+G19+G20 -> 1073.959 | H21: =H18+H19+H20 -> 379.195 | I21: =I18+I19+I20 -> 1055.471 | J21: =J18+J19+J20 -> 1104.28 | ... P21: =P18+P19+P20 -> 701.79341 | R21: =R18+R19+R20 -> 3578.308 | S21: =S18+S19+S20 -> 3902.6791 | T21: =T18+T19+T20 -> 3959.1621 | U21: =U18+U19+U20 -> 3919.8735 | V21: =V18+V19+V20 -> 3941.2651
A22: HDMC revenue growth YoY | B22: % | G22: =G21/C21-1 -> 0.22541405 | H22: =H21/D21-1 -> -0.098204709 | I22: =I21/E21-1 -> -0.024072011 | J22: =J21/F21-1 -> 0.058095203 | K22: =K21/G21-1 -> -0.035800641 | L22: =L21/H21-1 -> 0.86557723 | M22: =M21/I21-1 -> 0.017301989 | N22: =N21/J21-1 -> 0.033258244 | ... P22: =P21/L21-1 -> -0.007950254 | S22: =S21/R21-1 -> 0.090649306 | T22: =T21/S21-1 -> 0.01447288 | U22: =U21/T21-1 -> -0.0099234808 | V22: =V21/U21-1 -> 0.0054572203
A23: HDMC gross profit | B23: $m | C23: =Historicals!C11/1000 -> 263.813 | D23: =Historicals!D11/1000 -> -3.17 | E23: =Historicals!E11/1000 -> 315.244 | F23: =Historicals!F11/1000 -> 298.705 | G23: =Historicals!G11/1000 -> 283.11 | H23: =Historicals!H11/1000 -> -30.467 | I23: =Historicals!I11/1000 -> 266.989 | J23: =Historicals!J11/1000 -> 304.126 | K23: =(Inputs!$E$57+Inputs!$E$79)*K21-Inputs!$E$58*(1+Inputs!$E$43)^0 -> 271.44538 | L23: =(Inputs!$E$57+Inputs!$E$79)*L21-Inputs!$E$58*(1+Inputs!$E$43)^0 -> 119.72584 | M23: =(Inputs!$E$57+Inputs!$E$80)*M21-Inputs!$E$58*(1+Inputs!$E$43)^1 -> 284.97232 | N23: =(Inputs!$E$57+Inputs!$E$80)*N21-Inputs!$E$58*(1+Inputs!$E$43)^1 -> 316.08157 | O23: =(Inputs!$E$57+Inputs!$E$80)*O21-Inputs!$E$58*(1+Inputs!$E$43)^1 -> 270.58932 | P23: =(Inputs!$E$57+Inputs!$E$80)*P21-Inputs!$E$58*(1+Inputs!$E$43)^1 -> 112.97699 | R23: =SUM(E23:H23) -> 866.592 | S23: =SUM(I23:L23) -> 962.28622 | T23: =SUM(M23:P23) -> 984.6202 | U23: =(Inputs!$E$57+Inputs!$E$80)*U21-4*Inputs!$E$58*(1+Inputs!$E$43)^2 -> 949.52782 | V23: =(Inputs!$E$57+Inputs!$E$80)*V21-4*Inputs!$E$58*(1+Inputs!$E$43)^3 -> 942.15725
A24: HDMC gross margin | B24: % | C24: =C23/C21 -> 0.30101722 | D24: =D23/D21 -> -0.0075388417 | E24: =E23/E21 -> 0.2914864 | F24: =F23/F21 -> 0.28621213 | G24: =G23/G21 -> 0.26361342 | H24: =H23/H21 -> -0.080346524 | I24: =I23/I21 -> 0.25295721 | J24: =J23/J21 -> 0.2754066 | ... P24: =P23/P21 -> 0.16098325 | R24: =R23/R21 -> 0.24217926 | S24: =S23/S21 -> 0.24657067 | T24: =T23/T21 -> 0.24869408 | U24: =U23/U21 -> 0.2422343 | V24: =V23/V21 -> 0.23904945
A25: HDMC operating expense | B25: $m | C25: =Historicals!C12/1000 -> 208.676 | D25: =Historicals!D12/1000 -> 210.472 | E25: =Historicals!E12/1000 -> 198.972 | F25: =Historicals!F12/1000 -> 237.389 | G25: =Historicals!G12/1000 -> 228.991 | H25: =Historicals!H12/1000 -> 229.97 | I25: =Historicals!I12/1000 -> 248.064 | J25: =Historicals!J12/1000 -> 231.788 | K25: =G25*(1+Inputs!$E$81) -> 231.28091 | L25: =H25*(1+Inputs!$E$81) -> 232.2697 | M25: =I25*(1+Inputs!$E$81) -> 250.54464 | N25: =J25*(1+Inputs!$E$81) -> 234.10588 | O25: =K25*(1+Inputs!$E$81) -> 233.59372 | P25: =L25*(1+Inputs!$E$81) -> 234.5924 | R25: =SUM(E25:H25) -> 895.322 | S25: =SUM(I25:L25) -> 943.40261 | T25: =SUM(M25:P25) -> 952.83664 | U25: =T25*(1+Inputs!$E$81) -> 962.365 | V25: =U25*(1+Inputs!$E$81) -> 971.98865
A26: HDMC operating income | B26: $m | C26: =C23-C25 -> 55.137 | D26: =D23-D25 -> -213.642 | E26: =E23-E25 -> 116.272 | F26: =F23-F25 -> 61.316 | G26: =G23-G25 -> 54.119 | H26: =H23-H25 -> -260.437 | I26: =I23-I25 -> 18.925 | J26: =J23-J25 -> 72.338 | ... P26: =P23-P25 -> -121.61541 | R26: =R23-R25 -> -28.73 | S26: =S23-S25 -> 18.883607 | T26: =T23-T25 -> 31.78356 | U26: =U23-U25 -> -12.837184 | V26: =V23-V25 -> -29.831406
A27: HDMC operating margin | B27: % | C27: =C26/C21 -> 0.062912694 | D27: =D26/D21 -> -0.50807988 | E27: =E26/E21 -> 0.10750944 | F27: =F26/F21 -> 0.058751553 | G27: =G26/G21 -> 0.050392054 | H27: =H26/H21 -> -0.68681549 | I27: =I26/I21 -> 0.017930384 | J27: =J26/J21 -> 0.065506937 | ... P27: =P26/P21 -> -0.17329232 | R27: =R26/R21 -> -0.0080289343 | S27: =S26/S21 -> 0.0048386265 | T27: =T26/T21 -> 0.0080278502 | U27: =U26/U21 -> -0.0032748974 | V27: =V26/V21 -> -0.0075689926
A28: LiveWire revenue | B28: $m | C28: =Historicals!C13/1000 -> 4.808 | D28: =Historicals!D13/1000 -> 10.4 | E28: =Historicals!E13/1000 -> 2.743 | F28: =Historicals!F13/1000 -> 6.011 | G28: =Historicals!G13/1000 -> 5.563 | H28: =Historicals!H13/1000 -> 11.354 | I28: =Historicals!I13/1000 -> 5.116 | J28: =Historicals!J13/1000 -> 9.114 | K28: =G28*(1+Inputs!$E$86) -> 6.6756 | L28: =H28*(1+Inputs!$E$86) -> 13.6248 | M28: =I28*(1+Inputs!$E$86) -> 6.1392 | N28: =J28*(1+Inputs!$E$86) -> 10.9368 | O28: =K28*(1+Inputs!$E$86) -> 8.01072 | P28: =L28*(1+Inputs!$E$86) -> 16.34976 | R28: =SUM(E28:H28) -> 25.671 | S28: =SUM(I28:L28) -> 34.5304 | T28: =SUM(M28:P28) -> 41.43648 | U28: =T28*(1+Inputs!$E$86) -> 49.723776 | V28: =U28*(1+Inputs!$E$86) -> 59.668531
A29: LiveWire operating income (loss) | B29: $m | C29: =(Historicals!C14-Historicals!C15)/1000 -> -26.085 | D29: =(Historicals!D14-Historicals!D15)/1000 -> -26.146 | E29: =(Historicals!E14-Historicals!E15)/1000 -> -19.809 | F29: =(Historicals!F14-Historicals!F15)/1000 -> -18.653 | G29: =(Historicals!G14-Historicals!G15)/1000 -> -18.181 | H29: =(Historicals!H14-Historicals!H15)/1000 -> -18.374 | I29: =(Historicals!I14-Historicals!I15)/1000 -> -17.671 | J29: =(Historicals!J14-Historicals!J15)/1000 -> -17.927 | K29: =(Inputs!$E$82-I29-J29)/2 -> -19.701 | L29: =(Inputs!$E$82-I29-J29)/2 -> -19.701 | M29: =Inputs!$E$83/4 -> -16.25 | N29: =Inputs!$E$83/4 -> -16.25 | O29: =Inputs!$E$83/4 -> -16.25 | P29: =Inputs!$E$83/4 -> -16.25 | R29: =SUM(E29:H29) -> -75.017 | S29: =SUM(I29:L29) -> -75 | T29: =SUM(M29:P29) -> -65 | U29: =Inputs!$E$84 -> -55 | V29: =Inputs!$E$85 -> -45
A30: HDFS revenue | B30: $m | C30: =Historicals!C16/1000 -> 269.482 | D30: =Historicals!D16/1000 -> 256.72 | E30: =Historicals!E16/1000 -> 244.961 | F30: =Historicals!F16/1000 -> 257.438 | G30: =Historicals!G16/1000 -> 261.188 | H30: =Historicals!H16/1000 -> 105.609 | I30: =Historicals!I16/1000 -> 111.944 | J30: =Historicals!J16/1000 -> 117.043 | K30: =AVERAGE($I30:$J30)*(1+Inputs!$E$91)^0.5 -> 116.19821 | L30: =AVERAGE($I30:$J30)*(1+Inputs!$E$91)^0.5 -> 116.19821 | M30: =AVERAGE($I30:$J30)*(1+Inputs!$E$91)^1.5 -> 119.68416 | N30: =AVERAGE($I30:$J30)*(1+Inputs!$E$91)^1.5 -> 119.68416 | O30: =AVERAGE($I30:$J30)*(1+Inputs!$E$91)^1.5 -> 119.68416 | P30: =AVERAGE($I30:$J30)*(1+Inputs!$E$91)^1.5 -> 119.68416 | R30: =SUM(E30:H30) -> 869.196 | S30: =SUM(I30:L30) -> 461.38342 | T30: =SUM(M30:P30) -> 478.73663 | U30: =T30*(1+Inputs!$E$91) -> 493.09873 | V30: =U30*(1+Inputs!$E$91) -> 507.89169
A31: HDFS operating income | B31: $m | C31: =Historicals!C17/1000 -> 76.744 | D31: =Historicals!D17/1000 -> 46.44 | E31: =Historicals!E17/1000 -> 64.036 | F31: =Historicals!F17/1000 -> 69.773 | G31: =Historicals!G17/1000 -> 438.82 | H31: =Historicals!H17/1000 -> -82.247 | I31: =Historicals!I17/1000 -> 22.24 | J31: =Historicals!J17/1000 -> 21.599 | K31: =(Inputs!$E$87-I31-J31)/2 -> 8.0805 | L31: =(Inputs!$E$87-I31-J31)/2 -> 8.0805 | M31: =Inputs!$E$88/4 -> 16.25 | N31: =Inputs!$E$88/4 -> 16.25 | O31: =Inputs!$E$88/4 -> 16.25 | P31: =Inputs!$E$88/4 -> 16.25 | R31: =SUM(E31:H31) -> 490.382 | S31: =SUM(I31:L31) -> 60 | T31: =SUM(M31:P31) -> 65 | U31: =Inputs!$E$89 -> 70 | V31: =Inputs!$E$90 -> 72
A32: Total revenue | B32: $m | C32: =C21+C28+C30 -> 1150.695 | D32: =D21+D28+D30 -> 687.609 | E32: =E21+E28+E30 -> 1329.209 | F32: =F21+F28+F30 -> 1307.098 | G32: =G21+G28+G30 -> 1340.71 | H32: =H21+H28+H30 -> 496.158 | I32: =I21+I28+I30 -> 1172.531 | J32: =J21+J28+J30 -> 1230.437 | ... P32: =P21+P28+P30 -> 837.82733 | R32: =R21+R28+R30 -> 4473.175 | S32: =S21+S28+S30 -> 4398.593 | T32: =T21+T28+T30 -> 4479.3353 | U32: =U21+U28+U30 -> 4462.696 | V32: =V21+V28+V30 -> 4508.8253
A33: Consolidated operating income | B33: $m | C33: =C26+C29+C31 -> 105.796 | D33: =D26+D29+D31 -> -193.348 | E33: =E26+E29+E31 -> 160.499 | F33: =F26+F29+F31 -> 112.436 | G33: =G26+G29+G31 -> 474.758 | H33: =H26+H29+H31 -> -361.058 | I33: =I26+I29+I31 -> 23.494 | J33: =J26+J29+J31 -> 76.01 | ... P33: =P26+P29+P31 -> -121.61541 | R33: =R26+R29+R31 -> 386.635 | S33: =S26+S29+S31 -> 3.8836068 | T33: =T26+T29+T31 -> 31.78356 | U33: =U26+U29+U31 -> 2.1628164 | V33: =V26+V29+V31 -> -2.8314064
A34: Other income, net | B34: $m | C34: =Historicals!C18/1000 -> 18.408 | D34: =Historicals!D18/1000 -> 17.445 | E34: =Historicals!E18/1000 -> 16.273 | F34: =Historicals!F18/1000 -> 14.477 | G34: =Historicals!G18/1000 -> 14.706 | H34: =Historicals!H18/1000 -> 15.814 | I34: =Historicals!I18/1000 -> 13.477 | J34: =Historicals!J18/1000 -> 11.047 | K34: =Inputs!$E$30 -> 12 | L34: =Inputs!$E$30 -> 12 | M34: =Inputs!$E$30 -> 12 | N34: =Inputs!$E$30 -> 12 | O34: =Inputs!$E$30 -> 12 | P34: =Inputs!$E$30 -> 12 | R34: =SUM(E34:H34) -> 61.27 | S34: =SUM(I34:L34) -> 48.524 | T34: =SUM(M34:P34) -> 48 | U34: =4*Inputs!$E$30 -> 48 | V34: =4*Inputs!$E$30 -> 48
A35: Investment income | B35: $m | C35: =Historicals!C19/1000 -> 16.45 | D35: =Historicals!D19/1000 -> 13.3 | E35: =Historicals!E19/1000 -> 8.941 | F35: =Historicals!F19/1000 -> 10.95 | G35: =Historicals!G19/1000 -> 12.267 | H35: =Historicals!H19/1000 -> 12.112 | I35: =Historicals!I19/1000 -> 8.696 | J35: =Historicals!J19/1000 -> 11.84 | K35: =Inputs!$E$31 -> 9 | L35: =Inputs!$E$31 -> 9 | M35: =Inputs!$E$31 -> 9 | N35: =Inputs!$E$31 -> 9 | O35: =Inputs!$E$31 -> 9 | P35: =Inputs!$E$31 -> 9 | R35: =SUM(E35:H35) -> 44.27 | S35: =SUM(I35:L35) -> 38.536 | T35: =SUM(M35:P35) -> 36 | U35: =4*Inputs!$E$31 -> 36 | V35: =4*Inputs!$E$31 -> 36
A36: Interest expense | B36: $m | C36: =-Historicals!C20/1000 -> -7.707 | D36: =-Historicals!D20/1000 -> -7.683 | E36: =-Historicals!E20/1000 -> -7.686 | F36: =-Historicals!F20/1000 -> -7.696 | G36: =-Historicals!G20/1000 -> -10.182 | H36: =-Historicals!H20/1000 -> -7.88 | I36: =-Historicals!I20/1000 -> -3.57 | J36: =-Historicals!J20/1000 -> -3.622 | K36: =-Inputs!$E$32 -> -3.6 | L36: =-Inputs!$E$32 -> -3.6 | M36: =-Inputs!$E$32 -> -3.6 | N36: =-Inputs!$E$32 -> -3.6 | O36: =-Inputs!$E$32 -> -3.6 | P36: =-Inputs!$E$32 -> -3.6 | R36: =SUM(E36:H36) -> -33.444 | S36: =SUM(I36:L36) -> -14.392 | T36: =SUM(M36:P36) -> -14.4 | U36: =-4*Inputs!$E$32 -> -14.4 | V36: =-4*Inputs!$E$32 -> -14.4
A37: Pre-tax income | B37: $m | C37: =C33+C34+C35+C36 -> 132.947 | D37: =D33+D34+D35+D36 -> -170.286 | E37: =E33+E34+E35+E36 -> 178.027 | F37: =F33+F34+F35+F36 -> 130.167 | G37: =G33+G34+G35+G36 -> 491.549 | H37: =H33+H34+H35+H36 -> -341.012 | I37: =I33+I34+I35+I36 -> 42.097 | J37: =J33+J34+J35+J36 -> 95.275 | ... P37: =P33+P34+P35+P36 -> -104.21541 | R37: =R33+R34+R35+R36 -> 458.731 | S37: =S33+S34+S35+S36 -> 76.551607 | T37: =T33+T34+T35+T36 -> 101.38356 | U37: =U33+U34+U35+U36 -> 71.762816 | V37: =V33+V34+V35+V36 -> 66.768594
A38: Income tax | B38: $m | C38: =-Historicals!C21/1000 -> -16.98 | D38: =-Historicals!D21/1000 -> 51.857 | E38: =-Historicals!E21/1000 -> -47.23 | F38: =-Historicals!F21/1000 -> -24.422 | G38: =-Historicals!G21/1000 -> -116.384 | H38: =-Historicals!H21/1000 -> 58.459 | I38: =-Historicals!I21/1000 -> -17.974 | J38: =-Historicals!J21/1000 -> -16.294 | K38: =-K37*Inputs!$E$29 -> -10.567113 | L38: =-L37*Inputs!$E$29 -> 24.555804 | M38: =-M37*Inputs!$E$29 -> -11.920365 | N38: =-N37*Inputs!$E$29 -> -22.856409 | O38: =-O37*Inputs!$E$29 -> -12.510989 | P38: =-P37*Inputs!$E$29 -> 23.969544 | R38: =SUM(E38:H38) -> -129.577 | S38: =SUM(I38:L38) -> -20.27931 | T38: =SUM(M38:P38) -> -23.318219 | U38: =-U37*Inputs!$E$29 -> -16.505448 | V38: =-V37*Inputs!$E$29 -> -15.356777
A39: Net income (incl. NCI) | B39: $m | C39: =C37+C38 -> 115.967 | D39: =D37+D38 -> -118.429 | E39: =E37+E38 -> 130.797 | F39: =F37+F38 -> 105.745 | G39: =G37+G38 -> 375.165 | H39: =H37+H38 -> -282.553 | I39: =I37+I38 -> 24.123 | J39: =J37+J38 -> 78.981 | ... P39: =P37+P38 -> -80.245866 | R39: =R37+R38 -> 329.154 | S39: =S37+S38 -> 56.272297 | T39: =T37+T38 -> 78.065342 | U39: =U37+U38 -> 55.257369 | V39: =V37+V38 -> 51.411817
A40: Add: loss attributable to NCI | B40: $m | C40: =Historicals!C22/1000 -> 3.073 | D40: =Historicals!D22/1000 -> 1.538 | E40: =Historicals!E22/1000 -> 2.307 | F40: =Historicals!F22/1000 -> 1.824 | G40: =Historicals!G22/1000 -> 2.201 | H40: =Historicals!H22/1000 -> 3.252 | I40: =Historicals!I22/1000 -> 0.65 | J40: =Historicals!J22/1000 -> 0.824 | K40: =-K29*Inputs!$E$35 -> 0.98505 | L40: =-L29*Inputs!$E$35 -> 0.98505 | M40: =-M29*Inputs!$E$35 -> 0.8125 | N40: =-N29*Inputs!$E$35 -> 0.8125 | O40: =-O29*Inputs!$E$35 -> 0.8125 | P40: =-P29*Inputs!$E$35 -> 0.8125 | R40: =SUM(E40:H40) -> 9.584 | S40: =SUM(I40:L40) -> 3.4441 | T40: =SUM(M40:P40) -> 3.25 | U40: =-U29*Inputs!$E$35 -> 2.75 | V40: =-V29*Inputs!$E$35 -> 2.25
A41: Net income attributable to HOG | B41: $m | C41: =C39+C40 -> 119.04 | D41: =D39+D40 -> -116.891 | E41: =E39+E40 -> 133.104 | F41: =F39+F40 -> 107.569 | G41: =G39+G40 -> 377.366 | H41: =H39+H40 -> -279.301 | I41: =I39+I40 -> 24.773 | J41: =J39+J40 -> 79.805 | ... P41: =P39+P40 -> -79.433366 | R41: =R39+R40 -> 338.738 | S41: =S39+S40 -> 59.716397 | T41: =T39+T40 -> 81.315342 | U41: =U39+U40 -> 58.007369 | V41: =V39+V40 -> 53.661817
A42: Diluted shares | B42: m | C42: =Historicals!C23/1000 -> 130.963 | D42: =Historicals!D23/1000 -> 126.264 | E42: =Historicals!E23/1000 -> 124.724 | F42: =Historicals!F23/1000 -> 122.203 | G42: =Historicals!G23/1000 -> 121.676 | H42: =Historicals!H23/1000 -> 114.311 | I42: =Historicals!I23/1000 -> 110.768 | J42: =Historicals!J23/1000 -> 108.568 | K42: =J42-Inputs!$E$92/Inputs!$E$5 -> 107.08377 | L42: =K42-Inputs!$E$92/Inputs!$E$5 -> 105.59954 | M42: =L42-Inputs!$E$92/Inputs!$E$5 -> 104.11531 | N42: =M42-Inputs!$E$92/Inputs!$E$5 -> 102.63108 | O42: =N42-Inputs!$E$92/Inputs!$E$5 -> 101.14685 | P42: =O42-Inputs!$E$92/Inputs!$E$5 -> 99.66262 | R42: =AVERAGE(E42:H42) -> 120.7285 | S42: =AVERAGE(I42:L42) -> 108.00483 | T42: =AVERAGE(M42:P42) -> 101.88896 | U42: =T42-4*Inputs!$E$92/Inputs!$E$5 -> 95.952045 | V42: =U42-4*Inputs!$E$92/Inputs!$E$5 -> 90.015124
A43: Diluted EPS | B43: $ | C43: =C41/C42 -> 0.90895902 | D43: =D41/D42 -> -0.92576665 | E43: =E41/E42 -> 1.0671884 | F43: =F41/F42 -> 0.88024844 | G43: =G41/G42 -> 3.1014004 | H43: =H41/H42 -> -2.4433432 | I43: =I41/I42 -> 0.22364762 | J43: =J41/J42 -> 0.73506927 | ... P43: =P41/P42 -> -0.79702266 | R43: =R41/R42 -> 2.8057832 | S43: =S41/S42 -> 0.55290489 | T43: =T41/T42 -> 0.798078 | U43: =U41/U42 -> 0.60454542 | V43: =V41/V42 -> 0.59614223
A44: Diluted EPS - as reported (check) | B44: $ | C44: =Historicals!C24 -> 0.91 | D44: =Historicals!D24 -> -0.93 | E44: =Historicals!E24 -> 1.07 | F44: =Historicals!F24 -> 0.88 | G44: =Historicals!G24 -> 3.1 | H44: =Historicals!H24 -> -2.44 | I44: =Historicals!I24 -> 0.22 | J44: =Historicals!J24 -> 0.75
A45: Dividends per share | B45: $ | C45: =Historicals!C25 -> 0.1725 | D45: =Historicals!D25 -> 0.1725 | E45: =Historicals!E25 -> 0.18 | F45: =Historicals!F25 -> 0.18 | G45: =Historicals!G25 -> 0.18 | H45: =Historicals!H25 -> 0.18 | I45: =Historicals!I25 -> 0.1875 | J45: =Historicals!J25 -> 0.1875 | K45: =J45 -> 0.1875 | L45: =J45 -> 0.1875 | M45: =$J45*(1+Inputs!$E$45) -> 0.195 | N45: =$J45*(1+Inputs!$E$45) -> 0.195 | O45: =$J45*(1+Inputs!$E$45) -> 0.195 | P45: =$J45*(1+Inputs!$E$45) -> 0.195 | R45: =SUM(E45:H45) -> 0.72 | S45: =SUM(I45:L45) -> 0.75 | T45: =SUM(M45:P45) -> 0.78 | U45: =T45*(1+Inputs!$E$45) -> 0.8112 | V45: =U45*(1+Inputs!$E$45) -> 0.843648
A47: EBITDA & segment profit
A48: D&A | B48: $m | C48: =Historicals!C57/1000 -> 39.19 | D48: =Historicals!D57/1000 -> 41.11 | E48: =Historicals!E57/1000 -> 41.7 | F48: =Historicals!F57/1000 -> 40.43 | G48: =Historicals!G57/1000 -> 44.21 | H48: =Historicals!H57/1000 -> 46.03 | I48: =Historicals!I57/1000 -> 44.14 | J48: =Historicals!J57/1000 -> 42.56 | K48: =Inputs!$E$33 -> 43 | L48: =Inputs!$E$33 -> 43 | M48: =Inputs!$E$33 -> 43 | N48: =Inputs!$E$33 -> 43 | O48: =Inputs!$E$33 -> 43 | P48: =Inputs!$E$33 -> 43 | R48: =SUM(E48:H48) -> 172.37 | S48: =SUM(I48:L48) -> 172.7 | T48: =SUM(M48:P48) -> 172 | U48: =4*Inputs!$E$33 -> 172 | V48: =4*Inputs!$E$33 -> 172
A49: Industrial EBITDA (HDMC + LiveWire + D&A) | B49: $m | C49: =C26+C29+C48 -> 68.242 | D49: =D26+D29+D48 -> -198.678 | E49: =E26+E29+E48 -> 138.163 | F49: =F26+F29+F48 -> 83.093 | G49: =G26+G29+G48 -> 80.148 | H49: =H26+H29+H48 -> -232.781 | I49: =I26+I29+I48 -> 45.394 | J49: =J26+J29+J48 -> 96.971 | ... P49: =P26+P29+P48 -> -94.865411 | R49: =R26+R29+R48 -> 68.623 | S49: =S26+S29+S48 -> 116.58361 | T49: =T26+T29+T48 -> 138.78356 | U49: =U26+U29+U48 -> 104.16282 | V49: =V26+V29+V48 -> 97.168594
A50: Consolidated EBITDA | B50: $m | C50: =C33+C48 -> 144.986 | D50: =D33+D48 -> -152.238 | E50: =E33+E48 -> 202.199 | F50: =F33+F48 -> 152.866 | G50: =G33+G48 -> 518.968 | H50: =H33+H48 -> -315.028 | I50: =I33+I48 -> 67.634 | J50: =J33+J48 -> 118.57 | ... P50: =P33+P48 -> -78.615411 | R50: =R33+R48 -> 559.005 | S50: =S33+S48 -> 176.58361 | T50: =T33+T48 -> 203.78356 | U50: =U33+U48 -> 174.16282 | V50: =V33+V48 -> 169.16859
A51: Consensus EPS | B51: $ | S51: =Inputs!$E$7 -> 0.68
A52: Model EPS vs. consensus | B52: % | S52: =S43/S51-1 -> -0.18690457
A53: Check: FY26 HDMC op. income within guidance $10-50m? | S53: =IF(AND(S26>=Inputs!$E$24,S26<=Inputs!$E$25),"Yes","No") -> Yes
A55: Balance sheet (period end)
A56: Cash & equivalents (incl. restricted) | B56: $m | C56: =(Historicals!C38+Historicals!C39)/1000 -> 2391.82 | D56: =(Historicals!D38+Historicals!D39)/1000 -> 1725.269 | E56: =(Historicals!E38+Historicals!E39)/1000 -> 2081.307 | F56: =(Historicals!F38+Historicals!F39)/1000 -> 1737.446 | G56: =(Historicals!G38+Historicals!G39)/1000 -> 1826.568 | H56: =(Historicals!H38+Historicals!H39)/1000 -> 3091.744 | I56: =(Historicals!I38+Historicals!I39)/1000 -> 1805.068 | J56: =(Historicals!J38+Historicals!J39)/1000 -> 1895.789 | K56: =J56+K87 -> 1787.9321 | L56: =K56+L87 -> 1571.0883 | M56: =L56+M87 -> 1771.7076 | N56: =M56+N87 -> 1698.7231 | O56: =N56+O87 -> 1623.2269 | P56: =O56+P87 -> 1434.3303 | R56: =H56 -> 3091.744 | S56: =L56 -> 1571.0883 | T56: =P56 -> 1434.3303 | U56: =T56+U87 -> 1279.9651 | V56: =U56+V87 -> 1120.7426
A57: Accounts receivable | B57: $m | C57: =Historicals!C40/1000 -> 307.701 | D57: =Historicals!D40/1000 -> 234.315 | E57: =Historicals!E40/1000 -> 313.334 | F57: =Historicals!F40/1000 -> 325.756 | G57: =Historicals!G40/1000 -> 305.01 | H57: =Historicals!H40/1000 -> 225.76 | I57: =Historicals!I40/1000 -> 285.786 | J57: =Historicals!J40/1000 -> 301.788 | K57: =G57*($S$21/$R$21) -> 332.65894 | L57: =H57*($S$21/$R$21) -> 246.22499 | M57: =I57*($T$21/$S$21) -> 289.92215 | N57: =J57*($T$21/$S$21) -> 306.15574 | O57: =K57*($T$21/$S$21) -> 337.47348 | P57: =L57*($T$21/$S$21) -> 249.78857 | R57: =H57 -> 225.76 | S57: =L57 -> 246.22499 | T57: =P57 -> 249.78857 | U57: =T57*U21/T21 -> 247.3098 | V57: =U57*V21/U21 -> 248.65942
A58: Finance receivables (total) | B58: $m | C58: =(Historicals!C41+Historicals!C42+Historicals!C45)/1000 -> 7800.387 | D58: =(Historicals!D41+Historicals!D42+Historicals!D45)/1000 -> 7288.294 | E58: =(Historicals!E41+Historicals!E42+Historicals!E45)/1000 -> 7399.607 | F58: =(Historicals!F41+Historicals!F42+Historicals!F45)/1000 -> 7326.222 | G58: =(Historicals!G41+Historicals!G42+Historicals!G45)/1000 -> 5964.434 | H58: =(Historicals!H41+Historicals!H42+Historicals!H45)/1000 -> 1965.224 | I58: =(Historicals!I41+Historicals!I42+Historicals!I45)/1000 -> 2441.403 | J58: =(Historicals!J41+Historicals!J42+Historicals!J45)/1000 -> 2645.18 | K58: =J58*(1+Inputs!$E$44)^0.25 -> 2645.18 | L58: =K58*(1+Inputs!$E$44)^0.25 -> 2645.18 | M58: =L58*(1+Inputs!$E$44)^0.25 -> 2645.18 | N58: =M58*(1+Inputs!$E$44)^0.25 -> 2645.18 | O58: =N58*(1+Inputs!$E$44)^0.25 -> 2645.18 | P58: =O58*(1+Inputs!$E$44)^0.25 -> 2645.18 | R58: =H58 -> 1965.224 | S58: =L58 -> 2645.18 | T58: =P58 -> 2645.18 | U58: =T58*(1+Inputs!$E$44) -> 2645.18 | V58: =U58*(1+Inputs!$E$44) -> 2645.18
A59: Inventories | B59: $m | C59: =Historicals!C43/1000 -> 681.864 | D59: =Historicals!D43/1000 -> 745.793 | E59: =Historicals!E43/1000 -> 712.312 | F59: =Historicals!F43/1000 -> 630.287 | G59: =Historicals!G43/1000 -> 512.186 | H59: =Historicals!H43/1000 -> 730.898 | I59: =Historicals!I43/1000 -> 622.189 | J59: =Historicals!J43/1000 -> 500.935 | K59: =G59*($S$21/$R$21) -> 558.61531 | L59: =H59*($S$21/$R$21) -> 797.1534 | M59: =I59*($T$21/$S$21) -> 631.19387 | N59: =J59*($T$21/$S$21) -> 508.18497 | O59: =K59*($T$21/$S$21) -> 566.70008 | P59: =L59*($T$21/$S$21) -> 808.6905 | R59: =H59 -> 730.898 | S59: =L59 -> 797.1534 | T59: =P59 -> 808.6905 | U59: =T59*(U21-U23)/(T21-T23) -> 807.54965 | V59: =U59*(V21-V23)/(U21-U23) -> 815.36925
A60: Other current assets | B60: $m | C60: =Historicals!C44/1000 -> 208 | D60: =Historicals!D44/1000 -> 259.764 | E60: =Historicals!E44/1000 -> 253.687 | F60: =Historicals!F44/1000 -> 327.26 | G60: =Historicals!G44/1000 -> 297.444 | H60: =Historicals!H44/1000 -> 292.383 | I60: =Historicals!I44/1000 -> 415.301 | J60: =Historicals!J44/1000 -> 250.42 | K60: =J60 -> 250.42 | L60: =K60 -> 250.42 | M60: =L60 -> 250.42 | N60: =M60 -> 250.42 | O60: =N60 -> 250.42 | P60: =O60 -> 250.42 | R60: =H60 -> 292.383 | S60: =L60 -> 250.42 | T60: =P60 -> 250.42 | U60: =T60 -> 250.42 | V60: =U60 -> 250.42
A61: Other long-term assets (incl. PP&E) | B61: $m | C61: =Historicals!C46/1000 -> 1636.887 | D61: =Historicals!D46/1000 -> 1628.144 | E61: =Historicals!E46/1000 -> 1622.134 | F61: =Historicals!F46/1000 -> 1703.474 | G61: =Historicals!G46/1000 -> 1660.742 | H61: =Historicals!H46/1000 -> 1738.806 | I61: =Historicals!I46/1000 -> 1675.914 | J61: =Historicals!J46/1000 -> 1651.753 | K61: =J61-K79-K48 -> 1681.406 | L61: =K61-L79-L48 -> 1711.059 | M61: =L61-M79-M48 -> 1714.309 | N61: =M61-N79-N48 -> 1717.559 | O61: =N61-O79-O48 -> 1720.809 | P61: =O61-P79-P48 -> 1724.059 | R61: =H61 -> 1738.806 | S61: =L61 -> 1711.059 | T61: =P61 -> 1724.059 | U61: =T61-U79-U48 -> 1737.059 | V61: =U61-V79-V48 -> 1750.059
A62: Total assets | B62: $m | C62: =C56+C57+C58+C59+C60+C61 -> 13026.659 | D62: =D56+D57+D58+D59+D60+D61 -> 11881.579 | E62: =E56+E57+E58+E59+E60+E61 -> 12382.381 | F62: =F56+F57+F58+F59+F60+F61 -> 12050.445 | G62: =G56+G57+G58+G59+G60+G61 -> 10566.384 | H62: =H56+H57+H58+H59+H60+H61 -> 8044.815 | I62: =I56+I57+I58+I59+I60+I61 -> 7245.661 | J62: =J56+J57+J58+J59+J60+J61 -> 7245.865 | ... P62: =P56+P57+P58+P59+P60+P61 -> 7112.4684 | R62: =R56+R57+R58+R59+R60+R61 -> 8044.815 | S62: =S56+S57+S58+S59+S60+S61 -> 7221.1257 | T62: =T56+T57+T58+T59+T60+T61 -> 7112.4684 | U62: =U56+U57+U58+U59+U60+U61 -> 6967.4836 | V62: =V56+V57+V58+V59+V60+V61 -> 6830.4302
A63: Accounts payable & accrued | B63: $m | C63: =Historicals!C48/1000 -> 931.971 | D63: =Historicals!D48/1000 -> 892.678 | E63: =Historicals!E48/1000 -> 1105.802 | F63: =Historicals!F48/1000 -> 1040.616 | G63: =Historicals!G48/1000 -> 971.411 | H63: =Historicals!H48/1000 -> 1061.194 | I63: =Historicals!I48/1000 -> 1232.554 | J63: =Historicals!J48/1000 -> 1033.42 | K63: =G63*($S$21/$R$21) -> 1059.4687 | L63: =H63*($S$21/$R$21) -> 1157.3905 | M63: =I63*($T$21/$S$21) -> 1250.3926 | N63: =J63*($T$21/$S$21) -> 1048.3766 | O63: =K63*($T$21/$S$21) -> 1074.8023 | P63: =L63*($T$21/$S$21) -> 1174.1413 | R63: =H63 -> 1061.194 | S63: =L63 -> 1157.3905 | T63: =P63 -> 1174.1413 | U63: =T63*(U21-U23+U25)/(T21-T23+T25) -> 1175.7354 | V63: =U63*(V21-V23+V25)/(U21-U23+U25) -> 1187.2113
A64: Debt & deposits (mostly HDFS funding) | B64: $m | C64: =(Historicals!C49+Historicals!C50+Historicals!C51+Historicals!C52)/1000 -> 7977.053 | D64: =(Historicals!D49+Historicals!D50+Historicals!D51+Historicals!D52)/1000 -> 7133.481 | E64: =(Historicals!E49+Historicals!E50+Historicals!E51+Historicals!E52)/1000 -> 7479.237 | F64: =(Historicals!F49+Historicals!F50+Historicals!F51+Historicals!F52)/1000 -> 7097.835 | G64: =(Historicals!G49+Historicals!G50+Historicals!G51+Historicals!G52)/1000 -> 5454.488 | H64: =(Historicals!H49+Historicals!H50+Historicals!H51+Historicals!H52)/1000 -> 3247.112 | I64: =(Historicals!I49+Historicals!I50+Historicals!I51+Historicals!I52)/1000 -> 2380.438 | J64: =(Historicals!J49+Historicals!J50+Historicals!J51+Historicals!J52)/1000 -> 2508.875 | K64: =K58*Inputs!$E$61-Inputs!$E$26 -> 2508.875 | L64: =L58*Inputs!$E$61-Inputs!$E$26 -> 2508.875 | M64: =M58*Inputs!$E$61-Inputs!$E$26 -> 2508.875 | N64: =N58*Inputs!$E$61-Inputs!$E$26 -> 2508.875 | O64: =O58*Inputs!$E$61-Inputs!$E$26 -> 2508.875 | P64: =P58*Inputs!$E$61-Inputs!$E$26 -> 2508.875 | R64: =H64 -> 3247.112 | S64: =L64 -> 2508.875 | T64: =P64 -> 2508.875 | U64: =U58*Inputs!$E$61-Inputs!$E$26 -> 2508.875 | V64: =V58*Inputs!$E$61-Inputs!$E$26 -> 2508.875
A65: Other long-term liabilities | B65: $m | C65: =Historicals!C53/1000 -> 692.523 | D65: =Historicals!D53/1000 -> 696.92 | E65: =Historicals!E53/1000 -> 623.652 | F65: =Historicals!F53/1000 -> 604.061 | G65: =Historicals!G53/1000 -> 579.106 | H65: =Historicals!H53/1000 -> 579.659 | I65: =Historicals!I53/1000 -> 552.534 | J65: =Historicals!J53/1000 -> 587.551 | K65: =J65 -> 587.551 | L65: =K65 -> 587.551 | M65: =L65 -> 587.551 | N65: =M65 -> 587.551 | O65: =N65 -> 587.551 | P65: =O65 -> 587.551 | R65: =H65 -> 579.659 | S65: =L65 -> 587.551 | T65: =P65 -> 587.551 | U65: =T65 -> 587.551 | V65: =U65 -> 587.551
A66: Total equity (incl. NCI) | B66: $m | C66: =Historicals!C54/1000 -> 3425.112 | D66: =Historicals!D54/1000 -> 3158.5 | E66: =Historicals!E54/1000 -> 3173.69 | F66: =Historicals!F54/1000 -> 3307.933 | G66: =Historicals!G54/1000 -> 3561.379 | H66: =Historicals!H54/1000 -> 3156.85 | I66: =Historicals!I54/1000 -> 3080.135 | J66: =Historicals!J54/1000 -> 3116.019 | K66: =J66+K39+K73+K83+K84 -> 3100.3177 | L66: =K66+L39+L73+L83+L84 -> 2967.3092 | M66: =L66+M39+M73+M83+M84 -> 2955.914 | N66: =M66+N39+N73+N83+N84 -> 2981.4202 | O66: =N66+O39+O73+O83+O84 -> 2972.5812 | P66: =O66+P39+P73+P83+P84 -> 2841.9011 | R66: =H66 -> 3156.85 | S66: =L66 -> 2967.3092 | T66: =P66 -> 2841.9011 | U66: =T66+U39+U73+U83+U84 -> 2695.3222 | V66: =U66+V39+V73+V83+V84 -> 2546.7929
A67: Total liabilities & equity | B67: $m | C67: =C63+C64+C65+C66 -> 13026.659 | D67: =D63+D64+D65+D66 -> 11881.579 | E67: =E63+E64+E65+E66 -> 12382.381 | F67: =F63+F64+F65+F66 -> 12050.445 | G67: =G63+G64+G65+G66 -> 10566.384 | H67: =H63+H64+H65+H66 -> 8044.815 | I67: =I63+I64+I65+I66 -> 7245.661 | J67: =J63+J64+J65+J66 -> 7245.865 | ... P67: =P63+P64+P65+P66 -> 7112.4684 | R67: =R63+R64+R65+R66 -> 8044.815 | S67: =S63+S64+S65+S66 -> 7221.1257 | T67: =T63+T64+T65+T66 -> 7112.4684 | U67: =U63+U64+U65+U66 -> 6967.4836 | V67: =V63+V64+V65+V66 -> 6830.4302
A68: Balance check (assets - L&E) | B68: $m | C68: =ROUND(C62-C67,3) -> 0 | D68: =ROUND(D62-D67,3) -> 0 | E68: =ROUND(E62-E67,3) -> 0 | F68: =ROUND(F62-F67,3) -> 0 | G68: =ROUND(G62-G67,3) -> 0 | H68: =ROUND(H62-H67,3) -> 0 | I68: =ROUND(I62-I67,3) -> 0 | J68: =ROUND(J62-J67,3) -> 0 | ... P68: =ROUND(P62-P67,3) -> 0 | R68: =ROUND(R62-R67,3) -> 0 | S68: =ROUND(S62-S67,3) -> 0 | T68: =ROUND(T62-T67,3) -> 0 | U68: =ROUND(U62-U67,3) -> 0 | V68: =ROUND(V62-V67,3) -> 0
A70: Cash flow statement
A71: Net income (incl. NCI) | B71: $m | C71: =C39 -> 115.967 | D71: =D39 -> -118.429 | E71: =E39 -> 130.797 | F71: =F39 -> 105.745 | G71: =G39 -> 375.165 | H71: =H39 -> -282.553 | I71: =I39 -> 24.123 | J71: =J39 -> 78.981 | ... P71: =P39 -> -80.245866 | R71: =SUM(E71:H71) -> 329.154 | S71: =SUM(I71:L71) -> 56.272297 | T71: =SUM(M71:P71) -> 78.065342 | U71: =U39 -> 55.257369 | V71: =V39 -> 51.411817
A72: D&A | B72: $m | C72: =Historicals!C57/1000 -> 39.19 | D72: =Historicals!D57/1000 -> 41.11 | E72: =Historicals!E57/1000 -> 41.7 | F72: =Historicals!F57/1000 -> 40.43 | G72: =Historicals!G57/1000 -> 44.21 | H72: =Historicals!H57/1000 -> 46.03 | I72: =Historicals!I57/1000 -> 44.14 | J72: =Historicals!J57/1000 -> 42.56 | K72: =K48 -> 43 | L72: =L48 -> 43 | M72: =M48 -> 43 | N72: =N48 -> 43 | O72: =O48 -> 43 | P72: =P48 -> 43 | R72: =SUM(E72:H72) -> 172.37 | S72: =SUM(I72:L72) -> 172.7 | T72: =SUM(M72:P72) -> 172 | U72: =U48 -> 172 | V72: =V48 -> 172
A73: Stock-based compensation | B73: $m | C73: =Historicals!C58/1000 -> 10.83 | D73: =Historicals!D58/1000 -> 9.19 | E73: =Historicals!E58/1000 -> 6.82 | F73: =Historicals!F58/1000 -> 10.59 | G73: =Historicals!G58/1000 -> 8.43 | H73: =Historicals!H58/1000 -> 5.91 | I73: =Historicals!I58/1000 -> 8.54 | J73: =Historicals!J58/1000 -> 9.49 | K73: =Inputs!$E$34 -> 9 | L73: =Inputs!$E$34 -> 9 | M73: =Inputs!$E$34 -> 9 | N73: =Inputs!$E$34 -> 9 | O73: =Inputs!$E$34 -> 9 | P73: =Inputs!$E$34 -> 9 | R73: =SUM(E73:H73) -> 31.75 | S73: =SUM(I73:L73) -> 36.03 | T73: =SUM(M73:P73) -> 36 | U73: =4*Inputs!$E$34 -> 36 | V73: =4*Inputs!$E$34 -> 36
A74: (Increase)/decrease in receivables | B74: $m | K74: =-(K57-J57) -> -30.870945 | L74: =-(L57-K57) -> 86.433957 | M74: =-(M57-L57) -> -43.697159 | N74: =-(N57-M57) -> -16.233595 | O74: =-(O57-N57) -> -31.317736 | P74: =-(P57-O57) -> 87.684906 | R74: =SUM(E74:H74) -> 0 | S74: =SUM(I74:L74) -> 55.563013 | T74: =SUM(M74:P74) -> -3.5635848 | U74: =-(U57-T57) -> 2.4787721 | V74: =-(V57-U57) -> -1.3496241
A75: (Increase)/decrease in inventories | B75: $m | K75: =-(K59-J59) -> -57.680305 | L75: =-(L59-K59) -> -238.53809 | M75: =-(M59-L59) -> 165.95953 | N75: =-(N59-M59) -> 123.00889 | O75: =-(O59-N59) -> -58.515105 | P75: =-(P59-O59) -> -241.99042 | R75: =SUM(E75:H75) -> 0 | S75: =SUM(I75:L75) -> -296.2184 | T75: =SUM(M75:P75) -> -11.537106 | U75: =-(U59-T59) -> 1.1408484 | V75: =-(V59-U59) -> -7.8195927
A76: Increase/(decrease) in payables & accrued | B76: $m | K76: =(K63-J63) -> 26.048733 | L76: =(L63-K63) -> 97.921767 | M76: =(M63-L63) -> 93.002107 | N76: =(N63-M63) -> -202.01604 | O76: =(O63-N63) -> 26.425733 | P76: =(P63-O63) -> 99.338977 | R76: =SUM(E76:H76) -> 0 | S76: =SUM(I76:L76) -> 123.9705 | T76: =SUM(M76:P76) -> 16.750774 | U76: =(U63-T63) -> 1.5940935 | V76: =(V63-U63) -> 11.475948
A77: Other operating items (historical plug) | B77: $m | C77: =C78-C71-C72-C73 -> 187.026 | D77: =D78-D71-D72-D73 -> 201.307 | E77: =E78-E71-E72-E73 -> -37.783 | F77: =F78-F71-F72-F73 -> 211.193 | G77: =G78-G71-G72-G73 -> -520.394 | H77: =H78-H71-H72-H73 -> 382.632 | I77: =I78-I71-I72-I73 -> -304.824 | J77: =J78-J71-J72-J73 -> 37.305 | K77: =0 -> 0 | L77: =0 -> 0 | M77: =0 -> 0 | N77: =0 -> 0 | O77: =0 -> 0 | P77: =0 -> 0 | R77: =SUM(E77:H77) -> 35.648 | S77: =SUM(I77:L77) -> -267.519 | T77: =SUM(M77:P77) -> 0 | U77: =0 -> 0 | V77: =0 -> 0
A78: Cash from operations | B78: $m | C78: =Historicals!C56/1000 -> 353.013 | D78: =Historicals!D56/1000 -> 133.178 | E78: =Historicals!E56/1000 -> 141.534 | F78: =Historicals!F56/1000 -> 367.958 | G78: =Historicals!G56/1000 -> -92.589 | H78: =Historicals!H56/1000 -> 152.019 | I78: =Historicals!I56/1000 -> -228.021 | J78: =Historicals!J56/1000 -> 168.336 | K78: =SUM(K71:K77) -> 24.87434 | L78: =SUM(L71:L77) -> -84.390927 | M78: =SUM(M71:M77) -> 307.17179 | N78: =SUM(N71:N77) -> 33.278539 | O78: =SUM(O71:O77) -> 30.477507 | P78: =SUM(P71:P77) -> -83.212408 | R78: =SUM(E78:H78) -> 568.922 | S78: =SUM(I78:L78) -> -119.20159 | T78: =SUM(M78:P78) -> 287.71543 | U78: =SUM(U71:U77) -> 268.47108 | V78: =SUM(V71:V77) -> 261.71855
A79: Capital expenditures | B79: $m | C79: =Historicals!C59/1000 -> -52.589 | D79: =Historicals!D59/1000 -> -56.139 | E79: =Historicals!E59/1000 -> -29.973 | F79: =Historicals!F59/1000 -> -35.587 | G79: =Historicals!G59/1000 -> -36.53 | H79: =Historicals!H59/1000 -> -51.589 | I79: =Historicals!I59/1000 -> -31.792 | J79: =Historicals!J59/1000 -> -12.902 | K79: =-(Inputs!$E$36+I79+J79)/2 -> -72.653 | L79: =-(Inputs!$E$36+I79+J79)/2 -> -72.653 | M79: =-Inputs!$E$37/4 -> -46.25 | N79: =-Inputs!$E$37/4 -> -46.25 | O79: =-Inputs!$E$37/4 -> -46.25 | P79: =-Inputs!$E$37/4 -> -46.25 | R79: =SUM(E79:H79) -> -153.679 | S79: =SUM(I79:L79) -> -190 | T79: =SUM(M79:P79) -> -185 | U79: =-Inputs!$E$37 -> -185 | V79: =-Inputs!$E$37 -> -185
A80: (Increase)/decrease in finance receivables | B80: $m | K80: =-(K58-J58) -> 0 | L80: =-(L58-K58) -> 0 | M80: =-(M58-L58) -> 0 | N80: =-(N58-M58) -> 0 | O80: =-(O58-N58) -> 0 | P80: =-(P58-O58) -> 0 | R80: =SUM(E80:H80) -> 0 | S80: =SUM(I80:L80) -> 0 | T80: =SUM(M80:P80) -> 0 | U80: =-(U58-T58) -> 0 | V80: =-(V58-U58) -> 0
A81: Cash from investing | B81: $m | C81: =Historicals!C60/1000 -> -89.148 | D81: =Historicals!D60/1000 -> 102.847 | E81: =Historicals!E60/1000 -> 61.395 | F81: =Historicals!F60/1000 -> -151.249 | G81: =Historicals!G60/1000 -> 295.331 | H81: =Historicals!H60/1000 -> 3573.298 | I81: =Historicals!I60/1000 -> -92.004 | J81: =Historicals!J60/1000 -> -174.734 | K81: =K79+K80 -> -72.653 | L81: =L79+L80 -> -72.653 | M81: =M79+M80 -> -46.25 | N81: =N79+N80 -> -46.25 | O81: =O79+O80 -> -46.25 | P81: =P79+P80 -> -46.25 | R81: =SUM(E81:H81) -> 3778.775 | S81: =SUM(I81:L81) -> -412.044 | T81: =SUM(M81:P81) -> -185 | U81: =U79+U80 -> -185 | V81: =V79+V80 -> -185
A82: Increase/(decrease) in debt & deposits | B82: $m | K82: =(K64-J64) -> 0 | L82: =(L64-K64) -> 0 | M82: =(M64-L64) -> 0 | N82: =(N64-M64) -> 0 | O82: =(O64-N64) -> 0 | P82: =(P64-O64) -> 0 | R82: =SUM(E82:H82) -> 0 | S82: =SUM(I82:L82) -> 0 | T82: =SUM(M82:P82) -> 0 | U82: =(U64-T64) -> 0 | V82: =(V64-U64) -> 0
A83: Dividends | B83: $m | C83: =Historicals!C61/1000 -> -22.095 | D83: =Historicals!D61/1000 -> -21.77 | E83: =Historicals!E61/1000 -> -22.921 | F83: =Historicals!F61/1000 -> -21.835 | G83: =Historicals!G61/1000 -> -21.532 | H83: =Historicals!H61/1000 -> -20.1 | I83: =Historicals!I61/1000 -> -21.54 | J83: =Historicals!J61/1000 -> -19.671 | K83: =-K45*K42 -> -20.078207 | L83: =-L45*L42 -> -19.799914 | M83: =-M45*M42 -> -20.302485 | N83: =-N45*N42 -> -20.013061 | O83: =-O45*O42 -> -19.723636 | P83: =-P45*P42 -> -19.434211 | R83: =SUM(E83:H83) -> -86.388 | S83: =SUM(I83:L83) -> -81.089121 | T83: =SUM(M83:P83) -> -79.473393 | U83: =-U45*U42 -> -77.836299 | V83: =-V45*V42 -> -75.94108
A84: Share repurchases | B84: $m | C84: =Historicals!C62/1000 -> -150.135 | D84: =Historicals!D62/1000 -> -100.019 | E84: =Historicals!E62/1000 -> -93.095 | F84: =Historicals!F62/1000 -> -0.045 | G84: =Historicals!G62/1000 -> -100.069 | H84: =Historicals!H62/1000 -> -160.061 | I84: =Historicals!I62/1000 -> -70.018 | J84: =Historicals!J62/1000 -> -30.37 | K84: =-Inputs!$E$92 -> -40 | L84: =-Inputs!$E$92 -> -40 | M84: =-Inputs!$E$92 -> -40 | N84: =-Inputs!$E$92 -> -40 | O84: =-Inputs!$E$92 -> -40 | P84: =-Inputs!$E$92 -> -40 | R84: =SUM(E84:H84) -> -353.27 | S84: =SUM(I84:L84) -> -180.388 | T84: =SUM(M84:P84) -> -160 | U84: =-4*Inputs!$E$92 -> -160 | V84: =-4*Inputs!$E$92 -> -160
A85: Cash from financing | B85: $m | C85: =Historicals!C63/1000 -> 131.462 | D85: =Historicals!D63/1000 -> -885.775 | E85: =Historicals!E63/1000 -> 150.185 | F85: =Historicals!F63/1000 -> -566.704 | G85: =Historicals!G63/1000 -> -131.156 | H85: =Historicals!H63/1000 -> -2462.625 | I85: =Historicals!I63/1000 -> -959.337 | J85: =Historicals!J63/1000 -> 100.433 | K85: =SUM(K82:K84) -> -60.078207 | L85: =SUM(L82:L84) -> -59.799914 | M85: =SUM(M82:M84) -> -60.302485 | N85: =SUM(N82:N84) -> -60.013061 | O85: =SUM(O82:O84) -> -59.723636 | P85: =SUM(P82:P84) -> -59.434211 | R85: =SUM(E85:H85) -> -3010.3 | S85: =SUM(I85:L85) -> -978.78212 | T85: =SUM(M85:P85) -> -239.47339 | U85: =SUM(U82:U84) -> -237.8363 | V85: =SUM(V82:V84) -> -235.94108
A86: FX effect | B86: $m | C86: =Historicals!C64/1000 -> 11.019 | D86: =Historicals!D64/1000 -> -16.343 | E86: =Historicals!E64/1000 -> 3.299 | F86: =Historicals!F64/1000 -> 9.076 | G86: =Historicals!G64/1000 -> -1.366 | H86: =Historicals!H64/1000 -> 2.484 | I86: =Historicals!I64/1000 -> -7.314 | J86: =Historicals!J64/1000 -> -3.314 | K86: =0 -> 0 | L86: =0 -> 0 | M86: =0 -> 0 | N86: =0 -> 0 | O86: =0 -> 0 | P86: =0 -> 0 | R86: =SUM(E86:H86) -> 13.493 | S86: =SUM(I86:L86) -> -10.628 | T86: =SUM(M86:P86) -> 0 | U86: =0 -> 0 | V86: =0 -> 0
A87: Net change in cash | B87: $m | C87: =C78+C81+C85+C86 -> 406.346 | D87: =D78+D81+D85+D86 -> -666.093 | E87: =E78+E81+E85+E86 -> 356.413 | F87: =F78+F81+F85+F86 -> -340.919 | G87: =G78+G81+G85+G86 -> 70.22 | H87: =H78+H81+H85+H86 -> 1265.176 | I87: =I78+I81+I85+I86 -> -1286.676 | J87: =J78+J81+J85+J86 -> 90.721 | ... P87: =P78+P81+P85+P86 -> -188.89662 | R87: =SUM(E87:H87) -> 1350.89 | S87: =SUM(I87:L87) -> -1520.6557 | T87: =SUM(M87:P87) -> -136.75797 | U87: =U78+U81+U85+U86 -> -154.36522 | V87: =V78+V81+V85+V86 -> -159.22253
A88: Free cash flow (CFO - capex) | B88: $m | C88: =C78+C79 -> 300.424 | D88: =D78+D79 -> 77.039 | E88: =E78+E79 -> 111.561 | F88: =F78+F79 -> 332.371 | G88: =G78+G79 -> -129.119 | H88: =H78+H79 -> 100.43 | I88: =I78+I79 -> -259.813 | J88: =J78+J79 -> 155.434 | ... P88: =P78+P79 -> -129.46241 | R88: =SUM(E88:H88) -> 415.243 | S88: =SUM(I88:L88) -> -309.20159 | T88: =SUM(M88:P88) -> 102.71543 | U88: =U78+U79 -> 83.471083 | V88: =V78+V79 -> 76.718549
A90: Returns (ROIC)
A91: NOPAT (consolidated op. income x (1 - tax)) | B91: $m | R91: =R33*(1-Inputs!$E$29) -> 297.70895 | S91: =S33*(1-Inputs!$E$29) -> 2.9903772 | T91: =T33*(1-Inputs!$E$29) -> 24.473342 | U91: =U33*(1-Inputs!$E$29) -> 1.6653686 | V91: =V33*(1-Inputs!$E$29) -> -2.180183
A92: Invested capital (equity + debt - cash) | B92: $m | C92: =C66+C64-C56 -> 9010.345 | D92: =D66+D64-D56 -> 8566.712 | E92: =E66+E64-E56 -> 8571.62 | F92: =F66+F64-F56 -> 8668.322 | G92: =G66+G64-G56 -> 7189.299 | H92: =H66+H64-H56 -> 3312.218 | I92: =I66+I64-I56 -> 3655.505 | J92: =J66+J64-J56 -> 3729.105 | ... P92: =P66+P64-P56 -> 3916.4458 | R92: =R66+R64-R56 -> 3312.218 | S92: =S66+S64-S56 -> 3905.0959 | T92: =T66+T64-T56 -> 3916.4458 | U92: =U66+U64-U56 -> 3924.2321 | V92: =V66+V64-V56 -> 3934.9254
A93: ROIC (on average invested capital) | B93: % | R93: =R91/AVERAGE(D92,R92) -> 0.050123866 | S93: =S91/AVERAGE(R92,S92) -> 0.00082866764 | T93: =T91/AVERAGE(S92,T92) -> 0.0062579329 | U93: =U91/AVERAGE(T92,U92) -> 0.00042480221 | V93: =V91/AVERAGE(U92,V92) -> -0.00055481341
A94: HDMC NOPAT | B94: $m | R94: =R26*(1-Inputs!$E$29) -> -22.1221 | S94: =S26*(1-Inputs!$E$29) -> 14.540377 | T94: =T26*(1-Inputs!$E$29) -> 24.473342 | U94: =U26*(1-Inputs!$E$29) -> -9.8846314 | V94: =V26*(1-Inputs!$E$29) -> -22.970183
A95: HDMC operating capital (AR + inventory + LT assets - AP) | B95: $m | C95: =C57+C59+C61-C63 -> 1694.481 | D95: =D57+D59+D61-D63 -> 1715.574 | E95: =E57+E59+E61-E63 -> 1541.978 | F95: =F57+F59+F61-F63 -> 1618.901 | G95: =G57+G59+G61-G63 -> 1506.527 | H95: =H57+H59+H61-H63 -> 1634.27 | I95: =I57+I59+I61-I63 -> 1351.335 | J95: =J57+J59+J61-J63 -> 1421.056 | ... P95: =P57+P59+P61-P63 -> 1608.3968 | R95: =R57+R59+R61-R63 -> 1634.27 | S95: =S57+S59+S61-S63 -> 1597.0469 | T95: =T57+T59+T61-T63 -> 1608.3968 | U95: =U57+U59+U61-U63 -> 1616.1831 | V95: =V57+V59+V61-V63 -> 1626.8764
A96: HDMC ROIC | B96: % | R96: =R94/R95 -> -0.01353638 | S96: =S94/S95 -> 0.00910454 | T96: =T94/T95 -> 0.015215985 | U96: =U94/U95 -> -0.0061160344 | V96: =V94/V95 -> -0.014119194
A97: ROE (net income to HOG / avg equity) | B97: % | S97: =S41/AVERAGE(R66,S66) -> 0.019501909 | T97: =T41/AVERAGE(S66,T66) -> 0.027995317 | U97: =U41/AVERAGE(T66,U66) -> 0.020951789 | V97: =V41/AVERAGE(U66,V66) -> 0.020473345
A99: Valuation
A100: FY2027E industrial EBITDA | B100: $m | T100: =T49 -> 138.78356
A101: EV / EBITDA multiple | B101: x | T101: =Inputs!$E$93 -> 7
A102: Industrial EV (multiples) | B102: $m | T102: =MAX(0,T100*T101) -> 971.48492
A103: FY2027E HDFS after-tax income | B103: $m | T103: =T31*(1-Inputs!$E$29) -> 50.05
A104: HDFS equity value (P/E) | B104: $m | T104: =T103*Inputs!$E$94 -> 450.45
A105: LiveWire stake | B105: $m | T105: =Inputs!$E$49 -> 50
A106: HDMC net cash ex-HDFS | B106: $m | T106: =Inputs!$E$48 -> 985.958
A107: Equity value - multiples SOTP | B107: $m | T107: =T102+T104+T105+T106 -> 2457.8929
...

Sheet Bear
A1: Harley-Davidson (HOG) - integrated model: BEAR CASE ($ millions unless noted)
A2: Blue = reported | Black = formula | Red = assumption (see Inputs) | Purple = consensus/market. Shaded columns = forecast.
C4: Q3'24 | D4: Q4'24 | E4: Q1'25 | F4: Q2'25 | G4: Q3'25 | H4: Q4'25 | I4: Q1'26 | J4: Q2'26 | K4: Q3'26E | L4: Q4'26E | M4: Q1'27E | N4: Q2'27E | O4: Q3'27E | P4: Q4'27E | R4: FY2025A | S4: FY2026E | T4: FY2027E | U4: FY2028E | V4: FY2029E
A5: Unit drivers
A6: Retail sales - worldwide | B6: units | C6: =Historicals!C32+Historicals!C33+Historicals!C34+Historicals!C35 -> 36166 | D6: =Historicals!D32+Historicals!D33+Historicals!D34+Historicals!D35 -> 25660 | E6: =Historicals!E32+Historicals!E33+Historicals!E34+Historicals!E35 -> 31010 | F6: =Historicals!F32+Historicals!F33+Historicals!F34+Historicals!F35 -> 42254 | G6: =Historicals!G32+Historicals!G33+Historicals!G34+Historicals!G35 -> 33984 | H6: =Historicals!H32+Historicals!H33+Historicals!H34+Historicals!H35 -> 25287 | I6: =Historicals!I32+Historicals!I33+Historicals!I34+Historicals!I35 -> 33507 | J6: =Historicals!J32+Historicals!J33+Historicals!J34+Historicals!J35 -> 42467 | K6: =G6*(1+Inputs!$D$66) -> 32964.48 | L6: =H6*(1+Inputs!$D$66) -> 24528.39 | M6: =I6*(1+Inputs!$D$67) -> 31831.65 | N6: =J6*(1+Inputs!$D$67) -> 40343.65 | O6: =K6*(1+Inputs!$D$67) -> 31316.256 | P6: =L6*(1+Inputs!$D$67) -> 23301.97 | R6: =SUM(E6:H6) -> 132535 | S6: =SUM(I6:L6) -> 133466.87 | T6: =SUM(M6:P6) -> 126793.53 | U6: =T6*(1+Inputs!$D$68) -> 122989.72 | V6: =U6*(1+Inputs!$D$69) -> 120529.93
A7: of which North America | B7: units | C7: =Historicals!C32 -> 24573 | D7: =Historicals!D32 -> 15127 | E7: =Historicals!E32 -> 20892 | F7: =Historicals!F32 -> 28931 | G7: =Historicals!G32 -> 23462 | H7: =Historicals!H32 -> 15847 | I7: =Historicals!I32 -> 23803 | J7: =Historicals!J32 -> 29751 | R7: =SUM(E7:H7) -> 89132
A8: Retail growth YoY | B8: % | G8: =G6/C6-1 -> -0.060332909 | H8: =H6/D6-1 -> -0.014536243 | I8: =I6/E6-1 -> 0.080522412 | J8: =J6/F6-1 -> 0.0050409429 | K8: =K6/G6-1 -> -0.03 | L8: =L6/H6-1 -> -0.03 | M8: =M6/I6-1 -> -0.05 | N8: =N6/J6-1 -> -0.05 | ... P8: =P6/L6-1 -> -0.05 | S8: =S6/R6-1 -> 0.0070311239 | T8: =T6/S6-1 -> -0.05 | U8: =U6/T6-1 -> -0.03 | V8: =V6/U6-1 -> -0.02
A9: HDMC shipments - worldwide | B9: units | C9: =Historicals!C27 -> 27520 | D9: =Historicals!D27 -> 14010 | E9: =Historicals!E27 -> 38601 | F9: =Historicals!F27 -> 35837 | G9: =Historicals!G27 -> 36524 | H9: =Historicals!H27 -> 13515 | I9: =Historicals!I27 -> 37295 | J9: =Historicals!J27 -> 39209 | K9: =(Inputs!$D$70-I9-J9)*Inputs!$E$38 -> 32097.6 | L9: =Inputs!$D$70-I9-J9-K9 -> 21398.4 | M9: =$T9*Inputs!$E$39 -> 34082.1 | N9: =$T9*Inputs!$E$40 -> 35299.318 | O9: =$T9*Inputs!$E$41 -> 31647.664 | P9: =$T9*Inputs!$E$42 -> 20692.704 | R9: =SUM(E9:H9) -> 124477 | S9: =SUM(I9:L9) -> 130000 | T9: =T6*(1+Inputs!$D$71) -> 121721.79 | U9: =U6*(1+Inputs!$D$72) -> 121759.82 | V9: =V6*(1+Inputs!$D$73) -> 120529.93
A10: Shipment growth YoY | B10: % | G10: =G9/C9-1 -> 0.32718023 | H10: =H9/D9-1 -> -0.035331906 | I10: =I9/E9-1 -> -0.03383332 | J10: =J9/F9-1 -> 0.094092697 | K10: =K9/G9-1 -> -0.12119155 | L10: =L9/H9-1 -> 0.58330744 | M10: =M9/I9-1 -> -0.086148279 | N10: =N9/J9-1 -> -0.099713898 | ... P10: =P9/L9-1 -> -0.032978937 | S10: =S9/R9-1 -> 0.044369643 | T10: =T9/S9-1 -> -0.063678574 | U10: =U9/T9-1 -> 0.0003125 | V10: =V9/U9-1 -> -0.01010101
A11: Implied dealer inventory change (shipments - retail) | B11: units | C11: =C9-C6 -> -8646 | D11: =D9-D6 -> -11650 | E11: =E9-E6 -> 7591 | F11: =F9-F6 -> -6417 | G11: =G9-G6 -> 2540 | H11: =H9-H6 -> -11772 | I11: =I9-I6 -> 3788 | J11: =J9-J6 -> -3258 | ... P11: =P9-P6 -> -2609.267 | R11: =R9-R6 -> -8058 | S11: =S9-S6 -> -3466.87 | T11: =T9-T6 -> -5071.7411 | U11: =U9-U6 -> -1229.8972 | V11: =V9-V6 -> 0
A12: Reported global dealer inventory, YoY | B12: % | G12: =Historicals!G36 -> -0.13 | H12: =Historicals!H36 -> -0.17 | I12: =Historicals!I36 -> -0.22 | J12: =Historicals!J36 -> -0.17
A13: Sport & Lightweight share of shipments | B13: % | C13: =Historicals!C30/Historicals!C27 -> 0.06431686 | D13: =Historicals!D30/Historicals!D27 -> 0.1076374 | E13: =Historicals!E30/Historicals!E27 -> 0.054609984 | F13: =Historicals!F30/Historicals!F27 -> 0.088958339 | G13: =Historicals!G30/Historicals!G27 -> 0.071952689 | H13: =Historicals!H30/Historicals!H27 -> 0.12682205 | I13: =Historicals!I30/Historicals!I27 -> 0.10004022 | J13: =Historicals!J30/Historicals!J27 -> 0.11775358
A14: Touring share of shipments | B14: % | C14: =Historicals!C28/Historicals!C27 -> 0.56297238 | D14: =Historicals!D28/Historicals!D27 -> 0.39707352 | E14: =Historicals!E28/Historicals!E27 -> 0.6134038 | F14: =Historicals!F28/Historicals!F27 -> 0.50450652 | G14: =Historicals!G28/Historicals!G27 -> 0.60330194 | H14: =Historicals!H28/Historicals!H27 -> 0.40392157 | I14: =Historicals!I28/Historicals!I27 -> 0.57702105 | J14: =Historicals!J28/Historicals!J27 -> 0.50093091
A16: Income statement
A17: Motorcycle revenue per unit | B17: $000 | C17: =Historicals!C6/Historicals!C27 -> 22.370203 | D17: =Historicals!D6/Historicals!D27 -> 16.52177 | E17: =Historicals!E6/Historicals!E27 -> 22.379291 | F17: =Historicals!F6/Historicals!F27 -> 21.71083 | G17: =Historicals!G6/Historicals!G27 -> 22.502026 | H17: =Historicals!H6/Historicals!H27 -> 14.34569 | I17: =Historicals!I6/Historicals!I27 -> 22.423757 | J17: =Historicals!J6/Historicals!J27 -> 21.629141 | K17: =Inputs!$E$60*(1+Inputs!$D$74) -> 21.576179 | L17: =Inputs!$E$60*(1+Inputs!$D$74) -> 21.576179 | M17: =$K17*(1+Inputs!$D$75) -> 20.713132 | N17: =$K17*(1+Inputs!$D$75) -> 20.713132 | O17: =$K17*(1+Inputs!$D$75) -> 20.713132 | P17: =$K17*(1+Inputs!$D$75) -> 20.713132 | R17: =R18/R9*1000 -> 21.350611 | S17: =S18/S9*1000 -> 21.83531 | T17: =T18/T9*1000 -> 20.713132 | U17: =T17*(1+Inputs!$D$76) -> 20.298869 | V17: =U17*(1+Inputs!$D$77) -> 20.09588
A18: HDMC - Motorcycles revenue | B18: $m | C18: =Historicals!C6/1000 -> 615.628 | D18: =Historicals!D6/1000 -> 231.47 | E18: =Historicals!E6/1000 -> 863.863 | F18: =Historicals!F6/1000 -> 778.051 | G18: =Historicals!G6/1000 -> 821.864 | H18: =Historicals!H6/1000 -> 193.882 | I18: =Historicals!I6/1000 -> 836.294 | J18: =Historicals!J6/1000 -> 848.057 | K18: =K9*K17/1000 -> 692.54356 | L18: =L9*L17/1000 -> 461.6957 | M18: =M9*M17/1000 -> 705.94702 | N18: =N9*N17/1000 -> 731.15941 | O18: =O9*O17/1000 -> 655.52223 | P18: =P9*P17/1000 -> 428.61069 | R18: =SUM(E18:H18) -> 2657.66 | S18: =SUM(I18:L18) -> 2838.5903 | T18: =SUM(M18:P18) -> 2521.2394 | U18: =U9*U17/1000 -> 2471.5867 | V18: =V9*V17/1000 -> 2422.155
A19: HDMC - Parts & accessories | B19: $m | C19: =(Historicals!C7)/1000 -> 174.301 | D19: =(Historicals!D7)/1000 -> 117.605 | E19: =(Historicals!E7)/1000 -> 143.433 | F19: =(Historicals!F7)/1000 -> 186.874 | G19: =(Historicals!G7)/1000 -> 167.252 | H19: =(Historicals!H7)/1000 -> 116.513 | I19: =(Historicals!I7)/1000 -> 142.243 | J19: =(Historicals!J7)/1000 -> 176.95 | K19: =G19*(1+Inputs!$D$78) -> 158.8894 | L19: =H19*(1+Inputs!$D$78) -> 110.68735 | M19: =I19*(1+Inputs!$D$78) -> 135.13085 | N19: =J19*(1+Inputs!$D$78) -> 168.1025 | O19: =K19*(1+Inputs!$D$78) -> 150.94493 | P19: =L19*(1+Inputs!$D$78) -> 105.15298 | R19: =SUM(E19:H19) -> 614.072 | S19: =SUM(I19:L19) -> 588.76975 | T19: =SUM(M19:P19) -> 559.33126 | U19: =T19*(1+Inputs!$D$78) -> 531.3647 | V19: =U19*(1+Inputs!$D$78) -> 504.79646
A20: HDMC - Apparel, licensing & other | B20: $m | C20: =(Historicals!C8+Historicals!C9+Historicals!C10)/1000 -> 86.476 | D20: =(Historicals!D8+Historicals!D9+Historicals!D10)/1000 -> 71.414 | E20: =(Historicals!E8+Historicals!E9+Historicals!E10)/1000 -> 74.209 | F20: =(Historicals!F8+Historicals!F9+Historicals!F10)/1000 -> 78.724 | G20: =(Historicals!G8+Historicals!G9+Historicals!G10)/1000 -> 84.843 | H20: =(Historicals!H8+Historicals!H9+Historicals!H10)/1000 -> 68.8 | I20: =(Historicals!I8+Historicals!I9+Historicals!I10)/1000 -> 76.934 | J20: =(Historicals!J8+Historicals!J9+Historicals!J10)/1000 -> 79.273 | K20: =G20*(1+Inputs!$D$78) -> 80.60085 | L20: =H20*(1+Inputs!$D$78) -> 65.36 | M20: =I20*(1+Inputs!$D$78) -> 73.0873 | N20: =J20*(1+Inputs!$D$78) -> 75.30935 | O20: =K20*(1+Inputs!$D$78) -> 76.570808 | P20: =L20*(1+Inputs!$D$78) -> 62.092 | R20: =SUM(E20:H20) -> 306.576 | S20: =SUM(I20:L20) -> 302.16785 | T20: =SUM(M20:P20) -> 287.05946 | U20: =T20*(1+Inputs!$D$78) -> 272.70648 | V20: =U20*(1+Inputs!$D$78) -> 259.07116
A21: HDMC revenue | B21: $m | C21: =C18+C19+C20 -> 876.405 | D21: =D18+D19+D20 -> 420.489 | E21: =E18+E19+E20 -> 1081.505 | F21: =F18+F19+F20 -> 1043.649 | G21: =G18+G19+G20 -> 1073.959 | H21: =H18+H19+H20 -> 379.195 | I21: =I18+I19+I20 -> 1055.471 | J21: =J18+J19+J20 -> 1104.28 | ... P21: =P18+P19+P20 -> 595.85567 | R21: =R18+R19+R20 -> 3578.308 | S21: =S18+S19+S20 -> 3729.5279 | T21: =T18+T19+T20 -> 3367.6301 | U21: =U18+U19+U20 -> 3275.6579 | V21: =V18+V19+V20 -> 3186.0226
A22: HDMC revenue growth YoY | B22: % | G22: =G21/C21-1 -> 0.22541405 | H22: =H21/D21-1 -> -0.098204709 | I22: =I21/E21-1 -> -0.024072011 | J22: =J21/F21-1 -> 0.058095203 | K22: =K21/G21-1 -> -0.13215141 | L22: =L21/H21-1 -> 0.68183403 | M22: =M21/I21-1 -> -0.1338794 | N22: =N21/J21-1 -> -0.11746001 | ... P22: =P21/L21-1 -> -0.065680652 | S22: =S21/R21-1 -> 0.042260157 | T22: =T21/S21-1 -> -0.097035816 | U22: =U21/T21-1 -> -0.027310658 | V22: =V21/U21-1 -> -0.027364058
A23: HDMC gross profit | B23: $m | C23: =Historicals!C11/1000 -> 263.813 | D23: =Historicals!D11/1000 -> -3.17 | E23: =Historicals!E11/1000 -> 315.244 | F23: =Historicals!F11/1000 -> 298.705 | G23: =Historicals!G11/1000 -> 283.11 | H23: =Historicals!H11/1000 -> -30.467 | I23: =Historicals!I11/1000 -> 266.989 | J23: =Historicals!J11/1000 -> 304.126 | K23: =(Inputs!$E$57+Inputs!$D$79)*K21-Inputs!$E$58*(1+Inputs!$E$43)^0 -> 214.27444 | L23: =(Inputs!$E$57+Inputs!$D$79)*L21-Inputs!$E$58*(1+Inputs!$E$43)^0 -> 81.128934 | M23: =(Inputs!$E$57+Inputs!$D$80)*M21-Inputs!$E$58*(1+Inputs!$E$43)^1 -> 197.47125 | N23: =(Inputs!$E$57+Inputs!$D$80)*N21-Inputs!$E$58*(1+Inputs!$E$43)^1 -> 224.49866 | O23: =(Inputs!$E$57+Inputs!$D$80)*O21-Inputs!$E$58*(1+Inputs!$E$43)^1 -> 183.54406 | P23: =(Inputs!$E$57+Inputs!$D$80)*P21-Inputs!$E$58*(1+Inputs!$E$43)^1 -> 55.050531 | R23: =SUM(E23:H23) -> 866.592 | S23: =SUM(I23:L23) -> 866.51837 | T23: =SUM(M23:P23) -> 660.5645 | U23: =(Inputs!$E$57+Inputs!$D$80)*U21-4*Inputs!$E$58*(1+Inputs!$E$43)^2 -> 602.48934 | V23: =(Inputs!$E$57+Inputs!$D$80)*V21-4*Inputs!$E$58*(1+Inputs!$E$43)^3 -> 545.1213
A24: HDMC gross margin | B24: % | C24: =C23/C21 -> 0.30101722 | D24: =D23/D21 -> -0.0075388417 | E24: =E23/E21 -> 0.2914864 | F24: =F23/F21 -> 0.28621213 | G24: =G23/G21 -> 0.26361342 | H24: =H23/H21 -> -0.080346524 | I24: =I23/I21 -> 0.25295721 | J24: =J23/J21 -> 0.2754066 | ... P24: =P23/P21 -> 0.092389035 | R24: =R23/R21 -> 0.24217926 | S24: =S23/S21 -> 0.23233997 | T24: =T23/T21 -> 0.19615115 | U24: =U23/U21 -> 0.18392926 | V24: =V23/V21 -> 0.17109775
A25: HDMC operating expense | B25: $m | C25: =Historicals!C12/1000 -> 208.676 | D25: =Historicals!D12/1000 -> 210.472 | E25: =Historicals!E12/1000 -> 198.972 | F25: =Historicals!F12/1000 -> 237.389 | G25: =Historicals!G12/1000 -> 228.991 | H25: =Historicals!H12/1000 -> 229.97 | I25: =Historicals!I12/1000 -> 248.064 | J25: =Historicals!J12/1000 -> 231.788 | K25: =G25*(1+Inputs!$D$81) -> 233.57082 | L25: =H25*(1+Inputs!$D$81) -> 234.5694 | M25: =I25*(1+Inputs!$D$81) -> 253.02528 | N25: =J25*(1+Inputs!$D$81) -> 236.42376 | O25: =K25*(1+Inputs!$D$81) -> 238.24224 | P25: =L25*(1+Inputs!$D$81) -> 239.26079 | R25: =SUM(E25:H25) -> 895.322 | S25: =SUM(I25:L25) -> 947.99222 | T25: =SUM(M25:P25) -> 966.95206 | U25: =T25*(1+Inputs!$D$81) -> 986.29111 | V25: =U25*(1+Inputs!$D$81) -> 1006.0169
A26: HDMC operating income | B26: $m | C26: =C23-C25 -> 55.137 | D26: =D23-D25 -> -213.642 | E26: =E23-E25 -> 116.272 | F26: =F23-F25 -> 61.316 | G26: =G23-G25 -> 54.119 | H26: =H23-H25 -> -260.437 | I26: =I23-I25 -> 18.925 | J26: =J23-J25 -> 72.338 | ... P26: =P23-P25 -> -184.21026 | R26: =R23-R25 -> -28.73 | S26: =S23-S25 -> -81.473846 | T26: =T23-T25 -> -306.38757 | U26: =U23-U25 -> -383.80176 | V26: =V23-V25 -> -460.89563
A27: HDMC operating margin | B27: % | C27: =C26/C21 -> 0.062912694 | D27: =D26/D21 -> -0.50807988 | E27: =E26/E21 -> 0.10750944 | F27: =F26/F21 -> 0.058751553 | G27: =G26/G21 -> 0.050392054 | H27: =H26/H21 -> -0.68681549 | I27: =I26/I21 -> 0.017930384 | J27: =J26/J21 -> 0.065506937 | ... P27: =P26/P21 -> -0.30915248 | R27: =R26/R21 -> -0.0080289343 | S27: =S26/S21 -> -0.021845619 | T27: =T26/T21 -> -0.090980173 | U27: =U26/U21 -> -0.11716784 | V27: =V26/V21 -> -0.14466176
A28: LiveWire revenue | B28: $m | C28: =Historicals!C13/1000 -> 4.808 | D28: =Historicals!D13/1000 -> 10.4 | E28: =Historicals!E13/1000 -> 2.743 | F28: =Historicals!F13/1000 -> 6.011 | G28: =Historicals!G13/1000 -> 5.563 | H28: =Historicals!H13/1000 -> 11.354 | I28: =Historicals!I13/1000 -> 5.116 | J28: =Historicals!J13/1000 -> 9.114 | K28: =G28*(1+Inputs!$D$86) -> 5.563 | L28: =H28*(1+Inputs!$D$86) -> 11.354 | M28: =I28*(1+Inputs!$D$86) -> 5.116 | N28: =J28*(1+Inputs!$D$86) -> 9.114 | O28: =K28*(1+Inputs!$D$86) -> 5.563 | P28: =L28*(1+Inputs!$D$86) -> 11.354 | R28: =SUM(E28:H28) -> 25.671 | S28: =SUM(I28:L28) -> 31.147 | T28: =SUM(M28:P28) -> 31.147 | U28: =T28*(1+Inputs!$D$86) -> 31.147 | V28: =U28*(1+Inputs!$D$86) -> 31.147
A29: LiveWire operating income (loss) | B29: $m | C29: =(Historicals!C14-Historicals!C15)/1000 -> -26.085 | D29: =(Historicals!D14-Historicals!D15)/1000 -> -26.146 | E29: =(Historicals!E14-Historicals!E15)/1000 -> -19.809 | F29: =(Historicals!F14-Historicals!F15)/1000 -> -18.653 | G29: =(Historicals!G14-Historicals!G15)/1000 -> -18.181 | H29: =(Historicals!H14-Historicals!H15)/1000 -> -18.374 | I29: =(Historicals!I14-Historicals!I15)/1000 -> -17.671 | J29: =(Historicals!J14-Historicals!J15)/1000 -> -17.927 | K29: =(Inputs!$D$82-I29-J29)/2 -> -22.201 | L29: =(Inputs!$D$82-I29-J29)/2 -> -22.201 | M29: =Inputs!$D$83/4 -> -20 | N29: =Inputs!$D$83/4 -> -20 | O29: =Inputs!$D$83/4 -> -20 | P29: =Inputs!$D$83/4 -> -20 | R29: =SUM(E29:H29) -> -75.017 | S29: =SUM(I29:L29) -> -80 | T29: =SUM(M29:P29) -> -80 | U29: =Inputs!$D$84 -> -75 | V29: =Inputs!$D$85 -> -70
A30: HDFS revenue | B30: $m | C30: =Historicals!C16/1000 -> 269.482 | D30: =Historicals!D16/1000 -> 256.72 | E30: =Historicals!E16/1000 -> 244.961 | F30: =Historicals!F16/1000 -> 257.438 | G30: =Historicals!G16/1000 -> 261.188 | H30: =Historicals!H16/1000 -> 105.609 | I30: =Historicals!I16/1000 -> 111.944 | J30: =Historicals!J16/1000 -> 117.043 | K30: =AVERAGE($I30:$J30)*(1+Inputs!$D$91)^0.5 -> 113.34278 | L30: =AVERAGE($I30:$J30)*(1+Inputs!$D$91)^0.5 -> 113.34278 | M30: =AVERAGE($I30:$J30)*(1+Inputs!$D$91)^1.5 -> 111.07593 | N30: =AVERAGE($I30:$J30)*(1+Inputs!$D$91)^1.5 -> 111.07593 | O30: =AVERAGE($I30:$J30)*(1+Inputs!$D$91)^1.5 -> 111.07593 | P30: =AVERAGE($I30:$J30)*(1+Inputs!$D$91)^1.5 -> 111.07593 | R30: =SUM(E30:H30) -> 869.196 | S30: =SUM(I30:L30) -> 455.67256 | T30: =SUM(M30:P30) -> 444.30371 | U30: =T30*(1+Inputs!$D$91) -> 435.41763 | V30: =U30*(1+Inputs!$D$91) -> 426.70928
A31: HDFS operating income | B31: $m | C31: =Historicals!C17/1000 -> 76.744 | D31: =Historicals!D17/1000 -> 46.44 | E31: =Historicals!E17/1000 -> 64.036 | F31: =Historicals!F17/1000 -> 69.773 | G31: =Historicals!G17/1000 -> 438.82 | H31: =Historicals!H17/1000 -> -82.247 | I31: =Historicals!I17/1000 -> 22.24 | J31: =Historicals!J17/1000 -> 21.599 | K31: =(Inputs!$D$87-I31-J31)/2 -> 5.5805 | L31: =(Inputs!$D$87-I31-J31)/2 -> 5.5805 | M31: =Inputs!$D$88/4 -> 12.5 | N31: =Inputs!$D$88/4 -> 12.5 | O31: =Inputs!$D$88/4 -> 12.5 | P31: =Inputs!$D$88/4 -> 12.5 | R31: =SUM(E31:H31) -> 490.382 | S31: =SUM(I31:L31) -> 55 | T31: =SUM(M31:P31) -> 50 | U31: =Inputs!$D$89 -> 50 | V31: =Inputs!$D$90 -> 50
A32: Total revenue | B32: $m | C32: =C21+C28+C30 -> 1150.695 | D32: =D21+D28+D30 -> 687.609 | E32: =E21+E28+E30 -> 1329.209 | F32: =F21+F28+F30 -> 1307.098 | G32: =G21+G28+G30 -> 1340.71 | H32: =H21+H28+H30 -> 496.158 | I32: =I21+I28+I30 -> 1172.531 | J32: =J21+J28+J30 -> 1230.437 | ... P32: =P21+P28+P30 -> 718.2856 | R32: =R21+R28+R30 -> 4473.175 | S32: =S21+S28+S30 -> 4216.3474 | T32: =T21+T28+T30 -> 3843.0808 | U32: =U21+U28+U30 -> 3742.2225 | V32: =V21+V28+V30 -> 3643.8789
A33: Consolidated operating income | B33: $m | C33: =C26+C29+C31 -> 105.796 | D33: =D26+D29+D31 -> -193.348 | E33: =E26+E29+E31 -> 160.499 | F33: =F26+F29+F31 -> 112.436 | G33: =G26+G29+G31 -> 474.758 | H33: =H26+H29+H31 -> -361.058 | I33: =I26+I29+I31 -> 23.494 | J33: =J26+J29+J31 -> 76.01 | ... P33: =P26+P29+P31 -> -191.71026 | R33: =R26+R29+R31 -> 386.635 | S33: =S26+S29+S31 -> -106.47385 | T33: =T26+T29+T31 -> -336.38757 | U33: =U26+U29+U31 -> -408.80176 | V33: =V26+V29+V31 -> -480.89563
A34: Other income, net | B34: $m | C34: =Historicals!C18/1000 -> 18.408 | D34: =Historicals!D18/1000 -> 17.445 | E34: =Historicals!E18/1000 -> 16.273 | F34: =Historicals!F18/1000 -> 14.477 | G34: =Historicals!G18/1000 -> 14.706 | H34: =Historicals!H18/1000 -> 15.814 | I34: =Historicals!I18/1000 -> 13.477 | J34: =Historicals!J18/1000 -> 11.047 | K34: =Inputs!$E$30 -> 12 | L34: =Inputs!$E$30 -> 12 | M34: =Inputs!$E$30 -> 12 | N34: =Inputs!$E$30 -> 12 | O34: =Inputs!$E$30 -> 12 | P34: =Inputs!$E$30 -> 12 | R34: =SUM(E34:H34) -> 61.27 | S34: =SUM(I34:L34) -> 48.524 | T34: =SUM(M34:P34) -> 48 | U34: =4*Inputs!$E$30 -> 48 | V34: =4*Inputs!$E$30 -> 48
A35: Investment income | B35: $m | C35: =Historicals!C19/1000 -> 16.45 | D35: =Historicals!D19/1000 -> 13.3 | E35: =Historicals!E19/1000 -> 8.941 | F35: =Historicals!F19/1000 -> 10.95 | G35: =Historicals!G19/1000 -> 12.267 | H35: =Historicals!H19/1000 -> 12.112 | I35: =Historicals!I19/1000 -> 8.696 | J35: =Historicals!J19/1000 -> 11.84 | K35: =Inputs!$E$31 -> 9 | L35: =Inputs!$E$31 -> 9 | M35: =Inputs!$E$31 -> 9 | N35: =Inputs!$E$31 -> 9 | O35: =Inputs!$E$31 -> 9 | P35: =Inputs!$E$31 -> 9 | R35: =SUM(E35:H35) -> 44.27 | S35: =SUM(I35:L35) -> 38.536 | T35: =SUM(M35:P35) -> 36 | U35: =4*Inputs!$E$31 -> 36 | V35: =4*Inputs!$E$31 -> 36
A36: Interest expense | B36: $m | C36: =-Historicals!C20/1000 -> -7.707 | D36: =-Historicals!D20/1000 -> -7.683 | E36: =-Historicals!E20/1000 -> -7.686 | F36: =-Historicals!F20/1000 -> -7.696 | G36: =-Historicals!G20/1000 -> -10.182 | H36: =-Historicals!H20/1000 -> -7.88 | I36: =-Historicals!I20/1000 -> -3.57 | J36: =-Historicals!J20/1000 -> -3.622 | K36: =-Inputs!$E$32 -> -3.6 | L36: =-Inputs!$E$32 -> -3.6 | M36: =-Inputs!$E$32 -> -3.6 | N36: =-Inputs!$E$32 -> -3.6 | O36: =-Inputs!$E$32 -> -3.6 | P36: =-Inputs!$E$32 -> -3.6 | R36: =SUM(E36:H36) -> -33.444 | S36: =SUM(I36:L36) -> -14.392 | T36: =SUM(M36:P36) -> -14.4 | U36: =-4*Inputs!$E$32 -> -14.4 | V36: =-4*Inputs!$E$32 -> -14.4
A37: Pre-tax income | B37: $m | C37: =C33+C34+C35+C36 -> 132.947 | D37: =D33+D34+D35+D36 -> -170.286 | E37: =E33+E34+E35+E36 -> 178.027 | F37: =F33+F34+F35+F36 -> 130.167 | G37: =G33+G34+G35+G36 -> 491.549 | H37: =H33+H34+H35+H36 -> -341.012 | I37: =I33+I34+I35+I36 -> 42.097 | J37: =J33+J34+J35+J36 -> 95.275 | ... P37: =P33+P34+P35+P36 -> -174.31026 | R37: =R33+R34+R35+R36 -> 458.731 | S37: =S33+S34+S35+S36 -> -33.805846 | T37: =T33+T34+T35+T36 -> -266.78757 | U37: =U33+U34+U35+U36 -> -339.20176 | V37: =V33+V34+V35+V36 -> -411.29563
A38: Income tax | B38: $m | C38: =-Historicals!C21/1000 -> -16.98 | D38: =-Historicals!D21/1000 -> 51.857 | E38: =-Historicals!E21/1000 -> -47.23 | F38: =-Historicals!F21/1000 -> -24.422 | G38: =-Historicals!G21/1000 -> -116.384 | H38: =-Historicals!H21/1000 -> 58.459 | I38: =-Historicals!I21/1000 -> -17.974 | J38: =-Historicals!J21/1000 -> -16.294 | K38: =-K37*Inputs!$E$29 -> 4.2588825 | L38: =-L37*Inputs!$E$29 -> 35.112022 | M38: =-M37*Inputs!$E$29 -> 10.500426 | N38: =-N37*Inputs!$E$29 -> 0.46577384 | O38: =-O37*Inputs!$E$29 -> 10.303581 | P38: =-P37*Inputs!$E$29 -> 40.091359 | R38: =SUM(E38:H38) -> -129.577 | S38: =SUM(I38:L38) -> 5.1029047 | T38: =SUM(M38:P38) -> 61.36114 | U38: =-U37*Inputs!$E$29 -> 78.016406 | V38: =-V37*Inputs!$E$29 -> 94.597994
A39: Net income (incl. NCI) | B39: $m | C39: =C37+C38 -> 115.967 | D39: =D37+D38 -> -118.429 | E39: =E37+E38 -> 130.797 | F39: =F37+F38 -> 105.745 | G39: =G37+G38 -> 375.165 | H39: =H37+H38 -> -282.553 | I39: =I37+I38 -> 24.123 | J39: =J37+J38 -> 78.981 | ... P39: =P37+P38 -> -134.2189 | R39: =R37+R38 -> 329.154 | S39: =S37+S38 -> -28.702942 | T39: =T37+T38 -> -205.42643 | U39: =U37+U38 -> -261.18536 | V39: =V37+V38 -> -316.69763
A40: Add: loss attributable to NCI | B40: $m | C40: =Historicals!C22/1000 -> 3.073 | D40: =Historicals!D22/1000 -> 1.538 | E40: =Historicals!E22/1000 -> 2.307 | F40: =Historicals!F22/1000 -> 1.824 | G40: =Historicals!G22/1000 -> 2.201 | H40: =Historicals!H22/1000 -> 3.252 | I40: =Historicals!I22/1000 -> 0.65 | J40: =Historicals!J22/1000 -> 0.824 | K40: =-K29*Inputs!$E$35 -> 1.11005 | L40: =-L29*Inputs!$E$35 -> 1.11005 | M40: =-M29*Inputs!$E$35 -> 1 | N40: =-N29*Inputs!$E$35 -> 1 | O40: =-O29*Inputs!$E$35 -> 1 | P40: =-P29*Inputs!$E$35 -> 1 | R40: =SUM(E40:H40) -> 9.584 | S40: =SUM(I40:L40) -> 3.6941 | T40: =SUM(M40:P40) -> 4 | U40: =-U29*Inputs!$E$35 -> 3.75 | V40: =-V29*Inputs!$E$35 -> 3.5
A41: Net income attributable to HOG | B41: $m | C41: =C39+C40 -> 119.04 | D41: =D39+D40 -> -116.891 | E41: =E39+E40 -> 133.104 | F41: =F39+F40 -> 107.569 | G41: =G39+G40 -> 377.366 | H41: =H39+H40 -> -279.301 | I41: =I39+I40 -> 24.773 | J41: =J39+J40 -> 79.805 | ... P41: =P39+P40 -> -133.2189 | R41: =R39+R40 -> 338.738 | S41: =S39+S40 -> -25.008842 | T41: =T39+T40 -> -201.42643 | U41: =U39+U40 -> -257.43536 | V41: =V39+V40 -> -313.19763
A42: Diluted shares | B42: m | C42: =Historicals!C23/1000 -> 130.963 | D42: =Historicals!D23/1000 -> 126.264 | E42: =Historicals!E23/1000 -> 124.724 | F42: =Historicals!F23/1000 -> 122.203 | G42: =Historicals!G23/1000 -> 121.676 | H42: =Historicals!H23/1000 -> 114.311 | I42: =Historicals!I23/1000 -> 110.768 | J42: =Historicals!J23/1000 -> 108.568 | K42: =J42-Inputs!$D$92/Inputs!$E$5 -> 107.64036 | L42: =K42-Inputs!$D$92/Inputs!$E$5 -> 106.71271 | M42: =L42-Inputs!$D$92/Inputs!$E$5 -> 105.78507 | N42: =M42-Inputs!$D$92/Inputs!$E$5 -> 104.85742 | O42: =N42-Inputs!$D$92/Inputs!$E$5 -> 103.92978 | P42: =O42-Inputs!$D$92/Inputs!$E$5 -> 103.00214 | R42: =AVERAGE(E42:H42) -> 120.7285 | S42: =AVERAGE(I42:L42) -> 108.42227 | T42: =AVERAGE(M42:P42) -> 104.3936 | U42: =T42-4*Inputs!$D$92/Inputs!$E$5 -> 100.68303 | V42: =U42-4*Inputs!$D$92/Inputs!$E$5 -> 96.972453
A43: Diluted EPS | B43: $ | C43: =C41/C42 -> 0.90895902 | D43: =D41/D42 -> -0.92576665 | E43: =E41/E42 -> 1.0671884 | F43: =F41/F42 -> 0.88024844 | G43: =G41/G42 -> 3.1014004 | H43: =H41/H42 -> -2.4433432 | I43: =I41/I42 -> 0.22364762 | J43: =J41/J42 -> 0.73506927 | ... P43: =P41/P42 -> -1.2933605 | R43: =R41/R42 -> 2.8057832 | S43: =S41/S42 -> -0.23066149 | T43: =T41/T42 -> -1.9294901 | U43: =U41/U42 -> -2.5568893 | V43: =V41/V42 -> -3.2297588
A44: Diluted EPS - as reported (check) | B44: $ | C44: =Historicals!C24 -> 0.91 | D44: =Historicals!D24 -> -0.93 | E44: =Historicals!E24 -> 1.07 | F44: =Historicals!F24 -> 0.88 | G44: =Historicals!G24 -> 3.1 | H44: =Historicals!H24 -> -2.44 | I44: =Historicals!I24 -> 0.22 | J44: =Historicals!J24 -> 0.75
A45: Dividends per share | B45: $ | C45: =Historicals!C25 -> 0.1725 | D45: =Historicals!D25 -> 0.1725 | E45: =Historicals!E25 -> 0.18 | F45: =Historicals!F25 -> 0.18 | G45: =Historicals!G25 -> 0.18 | H45: =Historicals!H25 -> 0.18 | I45: =Historicals!I25 -> 0.1875 | J45: =Historicals!J25 -> 0.1875 | K45: =J45 -> 0.1875 | L45: =J45 -> 0.1875 | M45: =$J45*(1+Inputs!$E$45) -> 0.195 | N45: =$J45*(1+Inputs!$E$45) -> 0.195 | O45: =$J45*(1+Inputs!$E$45) -> 0.195 | P45: =$J45*(1+Inputs!$E$45) -> 0.195 | R45: =SUM(E45:H45) -> 0.72 | S45: =SUM(I45:L45) -> 0.75 | T45: =SUM(M45:P45) -> 0.78 | U45: =T45*(1+Inputs!$E$45) -> 0.8112 | V45: =U45*(1+Inputs!$E$45) -> 0.843648
A47: EBITDA & segment profit
A48: D&A | B48: $m | C48: =Historicals!C57/1000 -> 39.19 | D48: =Historicals!D57/1000 -> 41.11 | E48: =Historicals!E57/1000 -> 41.7 | F48: =Historicals!F57/1000 -> 40.43 | G48: =Historicals!G57/1000 -> 44.21 | H48: =Historicals!H57/1000 -> 46.03 | I48: =Historicals!I57/1000 -> 44.14 | J48: =Historicals!J57/1000 -> 42.56 | K48: =Inputs!$E$33 -> 43 | L48: =Inputs!$E$33 -> 43 | M48: =Inputs!$E$33 -> 43 | N48: =Inputs!$E$33 -> 43 | O48: =Inputs!$E$33 -> 43 | P48: =Inputs!$E$33 -> 43 | R48: =SUM(E48:H48) -> 172.37 | S48: =SUM(I48:L48) -> 172.7 | T48: =SUM(M48:P48) -> 172 | U48: =4*Inputs!$E$33 -> 172 | V48: =4*Inputs!$E$33 -> 172
A49: Industrial EBITDA (HDMC + LiveWire + D&A) | B49: $m | C49: =C26+C29+C48 -> 68.242 | D49: =D26+D29+D48 -> -198.678 | E49: =E26+E29+E48 -> 138.163 | F49: =F26+F29+F48 -> 83.093 | G49: =G26+G29+G48 -> 80.148 | H49: =H26+H29+H48 -> -232.781 | I49: =I26+I29+I48 -> 45.394 | J49: =J26+J29+J48 -> 96.971 | ... P49: =P26+P29+P48 -> -161.21026 | R49: =R26+R29+R48 -> 68.623 | S49: =S26+S29+S48 -> 11.226154 | T49: =T26+T29+T48 -> -214.38757 | U49: =U26+U29+U48 -> -286.80176 | V49: =V26+V29+V48 -> -358.89563
A50: Consolidated EBITDA | B50: $m | C50: =C33+C48 -> 144.986 | D50: =D33+D48 -> -152.238 | E50: =E33+E48 -> 202.199 | F50: =F33+F48 -> 152.866 | G50: =G33+G48 -> 518.968 | H50: =H33+H48 -> -315.028 | I50: =I33+I48 -> 67.634 | J50: =J33+J48 -> 118.57 | ... P50: =P33+P48 -> -148.71026 | R50: =R33+R48 -> 559.005 | S50: =S33+S48 -> 66.226154 | T50: =T33+T48 -> -164.38757 | U50: =U33+U48 -> -236.80176 | V50: =V33+V48 -> -308.89563
A51: Consensus EPS | B51: $ | S51: =Inputs!$E$7 -> 0.68
A52: Model EPS vs. consensus | B52: % | S52: =S43/S51-1 -> -1.3392081
A53: Check: FY26 HDMC op. income within guidance $10-50m? | S53: =IF(AND(S26>=Inputs!$E$24,S26<=Inputs!$E$25),"Yes","No") -> No
A55: Balance sheet (period end)
A56: Cash & equivalents (incl. restricted) | B56: $m | C56: =(Historicals!C38+Historicals!C39)/1000 -> 2391.82 | D56: =(Historicals!D38+Historicals!D39)/1000 -> 1725.269 | E56: =(Historicals!E38+Historicals!E39)/1000 -> 2081.307 | F56: =(Historicals!F38+Historicals!F39)/1000 -> 1737.446 | G56: =(Historicals!G38+Historicals!G39)/1000 -> 1826.568 | H56: =(Historicals!H38+Historicals!H39)/1000 -> 3091.744 | I56: =(Historicals!I38+Historicals!I39)/1000 -> 1805.068 | J56: =(Historicals!J38+Historicals!J39)/1000 -> 1895.789 | K56: =J56+K87 -> 1745.7306 | L56: =K56+L87 -> 1510.7416 | M56: =L56+M87 -> 1619.8394 | N56: =M56+N87 -> 1493.8108 | O56: =N56+O87 -> 1356.6241 | P56: =O56+P87 -> 1136.3157 | R56: =H56 -> 3091.744 | S56: =L56 -> 1510.7416 | T56: =P56 -> 1136.3157 | U56: =T56+U87 -> 726.91484 | V56: =U56+V87 -> 261.85175
A57: Accounts receivable | B57: $m | C57: =Historicals!C40/1000 -> 307.701 | D57: =Historicals!D40/1000 -> 234.315 | E57: =Historicals!E40/1000 -> 313.334 | F57: =Historicals!F40/1000 -> 325.756 | G57: =Historicals!G40/1000 -> 305.01 | H57: =Historicals!H40/1000 -> 225.76 | I57: =Historicals!I40/1000 -> 285.786 | J57: =Historicals!J40/1000 -> 301.788 | K57: =G57*($S$21/$R$21) -> 317.89977 | L57: =H57*($S$21/$R$21) -> 235.30065 | M57: =I57*($T$21/$S$21) -> 258.05452 | N57: =J57*($T$21/$S$21) -> 272.50376 | O57: =K57*($T$21/$S$21) -> 287.05211 | P57: =L57*($T$21/$S$21) -> 212.46806 | R57: =H57 -> 225.76 | S57: =L57 -> 235.30065 | T57: =P57 -> 212.46806 | U57: =T57*U21/T21 -> 206.66542 | V57: =U57*V21/U21 -> 201.01022
A58: Finance receivables (total) | B58: $m | C58: =(Historicals!C41+Historicals!C42+Historicals!C45)/1000 -> 7800.387 | D58: =(Historicals!D41+Historicals!D42+Historicals!D45)/1000 -> 7288.294 | E58: =(Historicals!E41+Historicals!E42+Historicals!E45)/1000 -> 7399.607 | F58: =(Historicals!F41+Historicals!F42+Historicals!F45)/1000 -> 7326.222 | G58: =(Historicals!G41+Historicals!G42+Historicals!G45)/1000 -> 5964.434 | H58: =(Historicals!H41+Historicals!H42+Historicals!H45)/1000 -> 1965.224 | I58: =(Historicals!I41+Historicals!I42+Historicals!I45)/1000 -> 2441.403 | J58: =(Historicals!J41+Historicals!J42+Historicals!J45)/1000 -> 2645.18 | K58: =J58*(1+Inputs!$E$44)^0.25 -> 2645.18 | L58: =K58*(1+Inputs!$E$44)^0.25 -> 2645.18 | M58: =L58*(1+Inputs!$E$44)^0.25 -> 2645.18 | N58: =M58*(1+Inputs!$E$44)^0.25 -> 2645.18 | O58: =N58*(1+Inputs!$E$44)^0.25 -> 2645.18 | P58: =O58*(1+Inputs!$E$44)^0.25 -> 2645.18 | R58: =H58 -> 1965.224 | S58: =L58 -> 2645.18 | T58: =P58 -> 2645.18 | U58: =T58*(1+Inputs!$E$44) -> 2645.18 | V58: =U58*(1+Inputs!$E$44) -> 2645.18
A59: Inventories | B59: $m | C59: =Historicals!C43/1000 -> 681.864 | D59: =Historicals!D43/1000 -> 745.793 | E59: =Historicals!E43/1000 -> 712.312 | F59: =Historicals!F43/1000 -> 630.287 | G59: =Historicals!G43/1000 -> 512.186 | H59: =Historicals!H43/1000 -> 730.898 | I59: =Historicals!I43/1000 -> 622.189 | J59: =Historicals!J43/1000 -> 500.935 | K59: =G59*($S$21/$R$21) -> 533.83106 | L59: =H59*($S$21/$R$21) -> 761.78586 | M59: =I59*($T$21/$S$21) -> 561.81438 | N59: =J59*($T$21/$S$21) -> 452.32636 | O59: =K59*($T$21/$S$21) -> 482.03033 | P59: =L59*($T$21/$S$21) -> 687.86535 | R59: =H59 -> 730.898 | S59: =L59 -> 761.78586 | T59: =P59 -> 687.86535 | U59: =T59*(U21-U23)/(T21-T23) -> 679.25211 | V59: =U59*(V21-V23)/(U21-U23) -> 671.05301
A60: Other current assets | B60: $m | C60: =Historicals!C44/1000 -> 208 | D60: =Historicals!D44/1000 -> 259.764 | E60: =Historicals!E44/1000 -> 253.687 | F60: =Historicals!F44/1000 -> 327.26 | G60: =Historicals!G44/1000 -> 297.444 | H60: =Historicals!H44/1000 -> 292.383 | I60: =Historicals!I44/1000 -> 415.301 | J60: =Historicals!J44/1000 -> 250.42 | K60: =J60 -> 250.42 | L60: =K60 -> 250.42 | M60: =L60 -> 250.42 | N60: =M60 -> 250.42 | O60: =N60 -> 250.42 | P60: =O60 -> 250.42 | R60: =H60 -> 292.383 | S60: =L60 -> 250.42 | T60: =P60 -> 250.42 | U60: =T60 -> 250.42 | V60: =U60 -> 250.42
A61: Other long-term assets (incl. PP&E) | B61: $m | C61: =Historicals!C46/1000 -> 1636.887 | D61: =Historicals!D46/1000 -> 1628.144 | E61: =Historicals!E46/1000 -> 1622.134 | F61: =Historicals!F46/1000 -> 1703.474 | G61: =Historicals!G46/1000 -> 1660.742 | H61: =Historicals!H46/1000 -> 1738.806 | I61: =Historicals!I46/1000 -> 1675.914 | J61: =Historicals!J46/1000 -> 1651.753 | K61: =J61-K79-K48 -> 1681.406 | L61: =K61-L79-L48 -> 1711.059 | M61: =L61-M79-M48 -> 1714.309 | N61: =M61-N79-N48 -> 1717.559 | O61: =N61-O79-O48 -> 1720.809 | P61: =O61-P79-P48 -> 1724.059 | R61: =H61 -> 1738.806 | S61: =L61 -> 1711.059 | T61: =P61 -> 1724.059 | U61: =T61-U79-U48 -> 1737.059 | V61: =U61-V79-V48 -> 1750.059
A62: Total assets | B62: $m | C62: =C56+C57+C58+C59+C60+C61 -> 13026.659 | D62: =D56+D57+D58+D59+D60+D61 -> 11881.579 | E62: =E56+E57+E58+E59+E60+E61 -> 12382.381 | F62: =F56+F57+F58+F59+F60+F61 -> 12050.445 | G62: =G56+G57+G58+G59+G60+G61 -> 10566.384 | H62: =H56+H57+H58+H59+H60+H61 -> 8044.815 | I62: =I56+I57+I58+I59+I60+I61 -> 7245.661 | J62: =J56+J57+J58+J59+J60+J61 -> 7245.865 | ... P62: =P56+P57+P58+P59+P60+P61 -> 6656.3081 | R62: =R56+R57+R58+R59+R60+R61 -> 8044.815 | S62: =S56+S57+S58+S59+S60+S61 -> 7114.4871 | T62: =T56+T57+T58+T59+T60+T61 -> 6656.3081 | U62: =U56+U57+U58+U59+U60+U61 -> 6245.4914 | V62: =V56+V57+V58+V59+V60+V61 -> 5779.574
A63: Accounts payable & accrued | B63: $m | C63: =Historicals!C48/1000 -> 931.971 | D63: =Historicals!D48/1000 -> 892.678 | E63: =Historicals!E48/1000 -> 1105.802 | F63: =Historicals!F48/1000 -> 1040.616 | G63: =Historicals!G48/1000 -> 971.411 | H63: =Historicals!H48/1000 -> 1061.194 | I63: =Historicals!I48/1000 -> 1232.554 | J63: =Historicals!J48/1000 -> 1033.42 | K63: =G63*($S$21/$R$21) -> 1012.463 | L63: =H63*($S$21/$R$21) -> 1106.0402 | M63: =I63*($T$21/$S$21) -> 1112.9521 | N63: =J63*($T$21/$S$21) -> 933.14125 | O63: =K63*($T$21/$S$21) -> 914.21781 | P63: =L63*($T$21/$S$21) -> 998.71471 | R63: =H63 -> 1061.194 | S63: =L63 -> 1106.0402 | T63: =P63 -> 998.71471 | U63: =T63*(U21-U23+U25)/(T21-T23+T25) -> 994.75738 | V63: =U63*(V21-V23+V25)/(U21-U23+U25) -> 991.34823
A64: Debt & deposits (mostly HDFS funding) | B64: $m | C64: =(Historicals!C49+Historicals!C50+Historicals!C51+Historicals!C52)/1000 -> 7977.053 | D64: =(Historicals!D49+Historicals!D50+Historicals!D51+Historicals!D52)/1000 -> 7133.481 | E64: =(Historicals!E49+Historicals!E50+Historicals!E51+Historicals!E52)/1000 -> 7479.237 | F64: =(Historicals!F49+Historicals!F50+Historicals!F51+Historicals!F52)/1000 -> 7097.835 | G64: =(Historicals!G49+Historicals!G50+Historicals!G51+Historicals!G52)/1000 -> 5454.488 | H64: =(Historicals!H49+Historicals!H50+Historicals!H51+Historicals!H52)/1000 -> 3247.112 | I64: =(Historicals!I49+Historicals!I50+Historicals!I51+Historicals!I52)/1000 -> 2380.438 | J64: =(Historicals!J49+Historicals!J50+Historicals!J51+Historicals!J52)/1000 -> 2508.875 | K64: =K58*Inputs!$E$61-Inputs!$E$26 -> 2508.875 | L64: =L58*Inputs!$E$61-Inputs!$E$26 -> 2508.875 | M64: =M58*Inputs!$E$61-Inputs!$E$26 -> 2508.875 | N64: =N58*Inputs!$E$61-Inputs!$E$26 -> 2508.875 | O64: =O58*Inputs!$E$61-Inputs!$E$26 -> 2508.875 | P64: =P58*Inputs!$E$61-Inputs!$E$26 -> 2508.875 | R64: =H64 -> 3247.112 | S64: =L64 -> 2508.875 | T64: =P64 -> 2508.875 | U64: =U58*Inputs!$E$61-Inputs!$E$26 -> 2508.875 | V64: =V58*Inputs!$E$61-Inputs!$E$26 -> 2508.875
A65: Other long-term liabilities | B65: $m | C65: =Historicals!C53/1000 -> 692.523 | D65: =Historicals!D53/1000 -> 696.92 | E65: =Historicals!E53/1000 -> 623.652 | F65: =Historicals!F53/1000 -> 604.061 | G65: =Historicals!G53/1000 -> 579.106 | H65: =Historicals!H53/1000 -> 579.659 | I65: =Historicals!I53/1000 -> 552.534 | J65: =Historicals!J53/1000 -> 587.551 | K65: =J65 -> 587.551 | L65: =K65 -> 587.551 | M65: =L65 -> 587.551 | N65: =M65 -> 587.551 | O65: =N65 -> 587.551 | P65: =O65 -> 587.551 | R65: =H65 -> 579.659 | S65: =L65 -> 587.551 | T65: =P65 -> 587.551 | U65: =T65 -> 587.551 | V65: =U65 -> 587.551
A66: Total equity (incl. NCI) | B66: $m | C66: =Historicals!C54/1000 -> 3425.112 | D66: =Historicals!D54/1000 -> 3158.5 | E66: =Historicals!E54/1000 -> 3173.69 | F66: =Historicals!F54/1000 -> 3307.933 | G66: =Historicals!G54/1000 -> 3561.379 | H66: =Historicals!H54/1000 -> 3156.85 | I66: =Historicals!I54/1000 -> 3080.135 | J66: =Historicals!J54/1000 -> 3116.019 | K66: =J66+K39+K73+K83+K84 -> 3065.5784 | L66: =K66+L39+L73+L83+L84 -> 2912.0209 | M66: =L66+M39+M73+M83+M84 -> 2840.2392 | N66: =M66+N39+N73+N83+N84 -> 2802.2326 | O66: =N66+O39+O73+O83+O84 -> 2731.4717 | P66: =O66+P39+P73+P83+P84 -> 2561.1674 | R66: =H66 -> 3156.85 | S66: =L66 -> 2912.0209 | T66: =P66 -> 2561.1674 | U66: =T66+U39+U73+U83+U84 -> 2154.308 | V66: =U66+V39+V73+V83+V84 -> 1691.7997
A67: Total liabilities & equity | B67: $m | C67: =C63+C64+C65+C66 -> 13026.659 | D67: =D63+D64+D65+D66 -> 11881.579 | E67: =E63+E64+E65+E66 -> 12382.381 | F67: =F63+F64+F65+F66 -> 12050.445 | G67: =G63+G64+G65+G66 -> 10566.384 | H67: =H63+H64+H65+H66 -> 8044.815 | I67: =I63+I64+I65+I66 -> 7245.661 | J67: =J63+J64+J65+J66 -> 7245.865 | ... P67: =P63+P64+P65+P66 -> 6656.3081 | R67: =R63+R64+R65+R66 -> 8044.815 | S67: =S63+S64+S65+S66 -> 7114.4871 | T67: =T63+T64+T65+T66 -> 6656.3081 | U67: =U63+U64+U65+U66 -> 6245.4914 | V67: =V63+V64+V65+V66 -> 5779.574
A68: Balance check (assets - L&E) | B68: $m | C68: =ROUND(C62-C67,3) -> 0 | D68: =ROUND(D62-D67,3) -> 0 | E68: =ROUND(E62-E67,3) -> 0 | F68: =ROUND(F62-F67,3) -> 0 | G68: =ROUND(G62-G67,3) -> 0 | H68: =ROUND(H62-H67,3) -> 0 | I68: =ROUND(I62-I67,3) -> 0 | J68: =ROUND(J62-J67,3) -> 0 | ... P68: =ROUND(P62-P67,3) -> 0 | R68: =ROUND(R62-R67,3) -> 0 | S68: =ROUND(S62-S67,3) -> 0 | T68: =ROUND(T62-T67,3) -> 0 | U68: =ROUND(U62-U67,3) -> 0 | V68: =ROUND(V62-V67,3) -> 0
A70: Cash flow statement
A71: Net income (incl. NCI) | B71: $m | C71: =C39 -> 115.967 | D71: =D39 -> -118.429 | E71: =E39 -> 130.797 | F71: =F39 -> 105.745 | G71: =G39 -> 375.165 | H71: =H39 -> -282.553 | I71: =I39 -> 24.123 | J71: =J39 -> 78.981 | ... P71: =P39 -> -134.2189 | R71: =SUM(E71:H71) -> 329.154 | S71: =SUM(I71:L71) -> -28.702942 | T71: =SUM(M71:P71) -> -205.42643 | U71: =U39 -> -261.18536 | V71: =V39 -> -316.69763
A72: D&A | B72: $m | C72: =Historicals!C57/1000 -> 39.19 | D72: =Historicals!D57/1000 -> 41.11 | E72: =Historicals!E57/1000 -> 41.7 | F72: =Historicals!F57/1000 -> 40.43 | G72: =Historicals!G57/1000 -> 44.21 | H72: =Historicals!H57/1000 -> 46.03 | I72: =Historicals!I57/1000 -> 44.14 | J72: =Historicals!J57/1000 -> 42.56 | K72: =K48 -> 43 | L72: =L48 -> 43 | M72: =M48 -> 43 | N72: =N48 -> 43 | O72: =O48 -> 43 | P72: =P48 -> 43 | R72: =SUM(E72:H72) -> 172.37 | S72: =SUM(I72:L72) -> 172.7 | T72: =SUM(M72:P72) -> 172 | U72: =U48 -> 172 | V72: =V48 -> 172
A73: Stock-based compensation | B73: $m | C73: =Historicals!C58/1000 -> 10.83 | D73: =Historicals!D58/1000 -> 9.19 | E73: =Historicals!E58/1000 -> 6.82 | F73: =Historicals!F58/1000 -> 10.59 | G73: =Historicals!G58/1000 -> 8.43 | H73: =Historicals!H58/1000 -> 5.91 | I73: =Historicals!I58/1000 -> 8.54 | J73: =Historicals!J58/1000 -> 9.49 | K73: =Inputs!$E$34 -> 9 | L73: =Inputs!$E$34 -> 9 | M73: =Inputs!$E$34 -> 9 | N73: =Inputs!$E$34 -> 9 | O73: =Inputs!$E$34 -> 9 | P73: =Inputs!$E$34 -> 9 | R73: =SUM(E73:H73) -> 31.75 | S73: =SUM(I73:L73) -> 36.03 | T73: =SUM(M73:P73) -> 36 | U73: =4*Inputs!$E$34 -> 36 | V73: =4*Inputs!$E$34 -> 36
A74: (Increase)/decrease in receivables | B74: $m | K74: =-(K57-J57) -> -16.111771 | L74: =-(L57-K57) -> 82.599117 | M74: =-(M57-L57) -> -22.753869 | N74: =-(N57-M57) -> -14.449233 | O74: =-(O57-N57) -> -14.548352 | P74: =-(P57-O57) -> 74.584045 | R74: =SUM(E74:H74) -> 0 | S74: =SUM(I74:L74) -> 66.487347 | T74: =SUM(M74:P74) -> 22.832591 | U74: =-(U57-T57) -> 5.8026426 | V74: =-(V57-U57) -> 5.6552046
A75: (Increase)/decrease in inventories | B75: $m | K75: =-(K59-J59) -> -32.896061 | L75: =-(L59-K59) -> -227.9548 | M75: =-(M59-L59) -> 199.97148 | N75: =-(N59-M59) -> 109.48802 | O75: =-(O59-N59) -> -29.703965 | P75: =-(P59-O59) -> -205.83502 | R75: =SUM(E75:H75) -> 0 | S75: =SUM(I75:L75) -> -260.85086 | T75: =SUM(M75:P75) -> 73.920513 | U75: =-(U59-T59) -> 8.6132375 | V75: =-(V59-U59) -> 8.1991083
A76: Increase/(decrease) in payables & accrued | B76: $m | K76: =(K63-J63) -> -20.957018 | L76: =(L63-K63) -> 93.577244 | M76: =(M63-L63) -> 6.9118921 | N76: =(N63-M63) -> -179.81087 | O76: =(O63-N63) -> -18.923437 | P76: =(P63-O63) -> 84.4969 | R76: =SUM(E76:H76) -> 0 | S76: =SUM(I76:L76) -> 72.620225 | T76: =SUM(M76:P76) -> -107.32552 | U76: =(U63-T63) -> -3.9573263 | V76: =(V63-U63) -> -3.4091588
A77: Other operating items (historical plug) | B77: $m | C77: =C78-C71-C72-C73 -> 187.026 | D77: =D78-D71-D72-D73 -> 201.307 | E77: =E78-E71-E72-E73 -> -37.783 | F77: =F78-F71-F72-F73 -> 211.193 | G77: =G78-G71-G72-G73 -> -520.394 | H77: =H78-H71-H72-H73 -> 382.632 | I77: =I78-I71-I72-I73 -> -304.824 | J77: =J78-J71-J72-J73 -> 37.305 | K77: =0 -> 0 | L77: =0 -> 0 | M77: =0 -> 0 | N77: =0 -> 0 | O77: =0 -> 0 | P77: =0 -> 0 | R77: =SUM(E77:H77) -> 35.648 | S77: =SUM(I77:L77) -> -267.519 | T77: =SUM(M77:P77) -> 0 | U77: =0 -> 0 | V77: =0 -> 0
A78: Cash from operations | B78: $m | C78: =Historicals!C56/1000 -> 353.013 | D78: =Historicals!D56/1000 -> 133.178 | E78: =Historicals!E56/1000 -> 141.534 | F78: =Historicals!F56/1000 -> 367.958 | G78: =Historicals!G56/1000 -> -92.589 | H78: =Historicals!H56/1000 -> 152.019 | I78: =Historicals!I56/1000 -> -228.021 | J78: =Historicals!J56/1000 -> 168.336 | K78: =SUM(K71:K77) -> -32.222848 | L78: =SUM(L71:L77) -> -117.32739 | M78: =SUM(M71:M77) -> 200.9759 | N78: =SUM(N71:N77) -> -34.331413 | O78: =SUM(O71:O77) -> -45.670351 | P78: =SUM(P71:P77) -> -128.97298 | R78: =SUM(E78:H78) -> 568.922 | S78: =SUM(I78:L78) -> -209.23523 | T78: =SUM(M78:P78) -> -7.9988387 | U78: =SUM(U71:U77) -> -42.726804 | V78: =SUM(V71:V77) -> -98.252479
A79: Capital expenditures | B79: $m | C79: =Historicals!C59/1000 -> -52.589 | D79: =Historicals!D59/1000 -> -56.139 | E79: =Historicals!E59/1000 -> -29.973 | F79: =Historicals!F59/1000 -> -35.587 | G79: =Historicals!G59/1000 -> -36.53 | H79: =Historicals!H59/1000 -> -51.589 | I79: =Historicals!I59/1000 -> -31.792 | J79: =Historicals!J59/1000 -> -12.902 | K79: =-(Inputs!$E$36+I79+J79)/2 -> -72.653 | L79: =-(Inputs!$E$36+I79+J79)/2 -> -72.653 | M79: =-Inputs!$E$37/4 -> -46.25 | N79: =-Inputs!$E$37/4 -> -46.25 | O79: =-Inputs!$E$37/4 -> -46.25 | P79: =-Inputs!$E$37/4 -> -46.25 | R79: =SUM(E79:H79) -> -153.679 | S79: =SUM(I79:L79) -> -190 | T79: =SUM(M79:P79) -> -185 | U79: =-Inputs!$E$37 -> -185 | V79: =-Inputs!$E$37 -> -185
A80: (Increase)/decrease in finance receivables | B80: $m | K80: =-(K58-J58) -> 0 | L80: =-(L58-K58) -> 0 | M80: =-(M58-L58) -> 0 | N80: =-(N58-M58) -> 0 | O80: =-(O58-N58) -> 0 | P80: =-(P58-O58) -> 0 | R80: =SUM(E80:H80) -> 0 | S80: =SUM(I80:L80) -> 0 | T80: =SUM(M80:P80) -> 0 | U80: =-(U58-T58) -> 0 | V80: =-(V58-U58) -> 0
A81: Cash from investing | B81: $m | C81: =Historicals!C60/1000 -> -89.148 | D81: =Historicals!D60/1000 -> 102.847 | E81: =Historicals!E60/1000 -> 61.395 | F81: =Historicals!F60/1000 -> -151.249 | G81: =Historicals!G60/1000 -> 295.331 | H81: =Historicals!H60/1000 -> 3573.298 | I81: =Historicals!I60/1000 -> -92.004 | J81: =Historicals!J60/1000 -> -174.734 | K81: =K79+K80 -> -72.653 | L81: =L79+L80 -> -72.653 | M81: =M79+M80 -> -46.25 | N81: =N79+N80 -> -46.25 | O81: =O79+O80 -> -46.25 | P81: =P79+P80 -> -46.25 | R81: =SUM(E81:H81) -> 3778.775 | S81: =SUM(I81:L81) -> -412.044 | T81: =SUM(M81:P81) -> -185 | U81: =U79+U80 -> -185 | V81: =V79+V80 -> -185
A82: Increase/(decrease) in debt & deposits | B82: $m | K82: =(K64-J64) -> 0 | L82: =(L64-K64) -> 0 | M82: =(M64-L64) -> 0 | N82: =(N64-M64) -> 0 | O82: =(O64-N64) -> 0 | P82: =(P64-O64) -> 0 | R82: =SUM(E82:H82) -> 0 | S82: =SUM(I82:L82) -> 0 | T82: =SUM(M82:P82) -> 0 | U82: =(U64-T64) -> 0 | V82: =(V64-U64) -> 0
A83: Dividends | B83: $m | C83: =Historicals!C61/1000 -> -22.095 | D83: =Historicals!D61/1000 -> -21.77 | E83: =Historicals!E61/1000 -> -22.921 | F83: =Historicals!F61/1000 -> -21.835 | G83: =Historicals!G61/1000 -> -21.532 | H83: =Historicals!H61/1000 -> -20.1 | I83: =Historicals!I61/1000 -> -21.54 | J83: =Historicals!J61/1000 -> -19.671 | K83: =-K45*K42 -> -20.182567 | L83: =-L45*L42 -> -20.008634 | M83: =-M45*M42 -> -20.628088 | N83: =-N45*N42 -> -20.447198 | O83: =-O45*O42 -> -20.266307 | P83: =-P45*P42 -> -20.085417 | R83: =SUM(E83:H83) -> -86.388 | S83: =SUM(I83:L83) -> -81.4022 | T83: =SUM(M83:P83) -> -81.42701 | U83: =-U45*U42 -> -81.674072 | V83: =-V45*V42 -> -81.810616
A84: Share repurchases | B84: $m | C84: =Historicals!C62/1000 -> -150.135 | D84: =Historicals!D62/1000 -> -100.019 | E84: =Historicals!E62/1000 -> -93.095 | F84: =Historicals!F62/1000 -> -0.045 | G84: =Historicals!G62/1000 -> -100.069 | H84: =Historicals!H62/1000 -> -160.061 | I84: =Historicals!I62/1000 -> -70.018 | J84: =Historicals!J62/1000 -> -30.37 | K84: =-Inputs!$D$92 -> -25 | L84: =-Inputs!$D$92 -> -25 | M84: =-Inputs!$D$92 -> -25 | N84: =-Inputs!$D$92 -> -25 | O84: =-Inputs!$D$92 -> -25 | P84: =-Inputs!$D$92 -> -25 | R84: =SUM(E84:H84) -> -353.27 | S84: =SUM(I84:L84) -> -150.388 | T84: =SUM(M84:P84) -> -100 | U84: =-4*Inputs!$D$92 -> -100 | V84: =-4*Inputs!$D$92 -> -100
A85: Cash from financing | B85: $m | C85: =Historicals!C63/1000 -> 131.462 | D85: =Historicals!D63/1000 -> -885.775 | E85: =Historicals!E63/1000 -> 150.185 | F85: =Historicals!F63/1000 -> -566.704 | G85: =Historicals!G63/1000 -> -131.156 | H85: =Historicals!H63/1000 -> -2462.625 | I85: =Historicals!I63/1000 -> -959.337 | J85: =Historicals!J63/1000 -> 100.433 | K85: =SUM(K82:K84) -> -45.182567 | L85: =SUM(L82:L84) -> -45.008634 | M85: =SUM(M82:M84) -> -45.628088 | N85: =SUM(N82:N84) -> -45.447198 | O85: =SUM(O82:O84) -> -45.266307 | P85: =SUM(P82:P84) -> -45.085417 | R85: =SUM(E85:H85) -> -3010.3 | S85: =SUM(I85:L85) -> -949.0952 | T85: =SUM(M85:P85) -> -181.42701 | U85: =SUM(U82:U84) -> -181.67407 | V85: =SUM(V82:V84) -> -181.81062
A86: FX effect | B86: $m | C86: =Historicals!C64/1000 -> 11.019 | D86: =Historicals!D64/1000 -> -16.343 | E86: =Historicals!E64/1000 -> 3.299 | F86: =Historicals!F64/1000 -> 9.076 | G86: =Historicals!G64/1000 -> -1.366 | H86: =Historicals!H64/1000 -> 2.484 | I86: =Historicals!I64/1000 -> -7.314 | J86: =Historicals!J64/1000 -> -3.314 | K86: =0 -> 0 | L86: =0 -> 0 | M86: =0 -> 0 | N86: =0 -> 0 | O86: =0 -> 0 | P86: =0 -> 0 | R86: =SUM(E86:H86) -> 13.493 | S86: =SUM(I86:L86) -> -10.628 | T86: =SUM(M86:P86) -> 0 | U86: =0 -> 0 | V86: =0 -> 0
A87: Net change in cash | B87: $m | C87: =C78+C81+C85+C86 -> 406.346 | D87: =D78+D81+D85+D86 -> -666.093 | E87: =E78+E81+E85+E86 -> 356.413 | F87: =F78+F81+F85+F86 -> -340.919 | G87: =G78+G81+G85+G86 -> 70.22 | H87: =H78+H81+H85+H86 -> 1265.176 | I87: =I78+I81+I85+I86 -> -1286.676 | J87: =J78+J81+J85+J86 -> 90.721 | ... P87: =P78+P81+P85+P86 -> -220.30839 | R87: =SUM(E87:H87) -> 1350.89 | S87: =SUM(I87:L87) -> -1581.0024 | T87: =SUM(M87:P87) -> -374.42585 | U87: =U78+U81+U85+U86 -> -409.40088 | V87: =V78+V81+V85+V86 -> -465.06309
A88: Free cash flow (CFO - capex) | B88: $m | C88: =C78+C79 -> 300.424 | D88: =D78+D79 -> 77.039 | E88: =E78+E79 -> 111.561 | F88: =F78+F79 -> 332.371 | G88: =G78+G79 -> -129.119 | H88: =H78+H79 -> 100.43 | I88: =I78+I79 -> -259.813 | J88: =J78+J79 -> 155.434 | ... P88: =P78+P79 -> -175.22298 | R88: =SUM(E88:H88) -> 415.243 | S88: =SUM(I88:L88) -> -399.23523 | T88: =SUM(M88:P88) -> -192.99884 | U88: =U78+U79 -> -227.7268 | V88: =V78+V79 -> -283.25248
A90: Returns (ROIC)
A91: NOPAT (consolidated op. income x (1 - tax)) | B91: $m | R91: =R33*(1-Inputs!$E$29) -> 297.70895 | S91: =S33*(1-Inputs!$E$29) -> -81.984862 | T91: =T33*(1-Inputs!$E$29) -> -259.01843 | U91: =U33*(1-Inputs!$E$29) -> -314.77736 | V91: =V33*(1-Inputs!$E$29) -> -370.28963
A92: Invested capital (equity + debt - cash) | B92: $m | C92: =C66+C64-C56 -> 9010.345 | D92: =D66+D64-D56 -> 8566.712 | E92: =E66+E64-E56 -> 8571.62 | F92: =F66+F64-F56 -> 8668.322 | G92: =G66+G64-G56 -> 7189.299 | H92: =H66+H64-H56 -> 3312.218 | I92: =I66+I64-I56 -> 3655.505 | J92: =J66+J64-J56 -> 3729.105 | ... P92: =P66+P64-P56 -> 3933.7267 | R92: =R66+R64-R56 -> 3312.218 | S92: =S66+S64-S56 -> 3910.1543 | T92: =T66+T64-T56 -> 3933.7267 | U92: =U66+U64-U56 -> 3936.2682 | V92: =V66+V64-V56 -> 3938.823
A93: ROIC (on average invested capital) | B93: % | R93: =R91/AVERAGE(D92,R92) -> 0.050123866 | S93: =S91/AVERAGE(R92,S92) -> -0.022703028 | T93: =T91/AVERAGE(S92,T92) -> -0.066043436 | U93: =U91/AVERAGE(T92,U92) -> -0.079994298 | V93: =V91/AVERAGE(U92,V92) -> -0.094040723
A94: HDMC NOPAT | B94: $m | R94: =R26*(1-Inputs!$E$29) -> -22.1221 | S94: =S26*(1-Inputs!$E$29) -> -62.734862 | T94: =T26*(1-Inputs!$E$29) -> -235.91843 | U94: =U26*(1-Inputs!$E$29) -> -295.52736 | V94: =V26*(1-Inputs!$E$29) -> -354.88963
A95: HDMC operating capital (AR + inventory + LT assets - AP) | B95: $m | C95: =C57+C59+C61-C63 -> 1694.481 | D95: =D57+D59+D61-D63 -> 1715.574 | E95: =E57+E59+E61-E63 -> 1541.978 | F95: =F57+F59+F61-F63 -> 1618.901 | G95: =G57+G59+G61-G63 -> 1506.527 | H95: =H57+H59+H61-H63 -> 1634.27 | I95: =I57+I59+I61-I63 -> 1351.335 | J95: =J57+J59+J61-J63 -> 1421.056 | ... P95: =P57+P59+P61-P63 -> 1625.6777 | R95: =R57+R59+R61-R63 -> 1634.27 | S95: =S57+S59+S61-S63 -> 1602.1053 | T95: =T57+T59+T61-T63 -> 1625.6777 | U95: =U57+U59+U61-U63 -> 1628.2192 | V95: =V57+V59+V61-V63 -> 1630.774
A96: HDMC ROIC | B96: % | R96: =R94/R95 -> -0.01353638 | S96: =S94/S95 -> -0.039157765 | T96: =T94/T95 -> -0.14512005 | U96: =U94/U95 -> -0.18150343 | V96: =V94/V95 -> -0.21762037
A97: ROE (net income to HOG / avg equity) | B97: % | S97: =S41/AVERAGE(R66,S66) -> -0.0082416787 | T97: =T41/AVERAGE(S66,T66) -> -0.073604786 | U97: =U41/AVERAGE(T66,U66) -> -0.10918745 | V97: =V41/AVERAGE(U66,V66) -> -0.16286472
A99: Valuation
A100: FY2027E industrial EBITDA | B100: $m | T100: =T49 -> -214.38757
A101: EV / EBITDA multiple | B101: x | T101: =Inputs!$D$93 -> 5.5
A102: Industrial EV (multiples) | B102: $m | T102: =MAX(0,T100*T101) -> 0
A103: FY2027E HDFS after-tax income | B103: $m | T103: =T31*(1-Inputs!$E$29) -> 38.5
A104: HDFS equity value (P/E) | B104: $m | T104: =T103*Inputs!$D$94 -> 269.5
A105: LiveWire stake | B105: $m | T105: =Inputs!$E$49 -> 50
A106: HDMC net cash ex-HDFS | B106: $m | T106: =Inputs!$E$48 -> 985.958
A107: Equity value - multiples SOTP | B107: $m | T107: =T102+T104+T105+T106 -> 1305.458
...

Sheet Bull
A1: Harley-Davidson (HOG) - integrated model: BULL CASE ($ millions unless noted)
A2: Blue = reported | Black = formula | Red = assumption (see Inputs) | Purple = consensus/market. Shaded columns = forecast.
C4: Q3'24 | D4: Q4'24 | E4: Q1'25 | F4: Q2'25 | G4: Q3'25 | H4: Q4'25 | I4: Q1'26 | J4: Q2'26 | K4: Q3'26E | L4: Q4'26E | M4: Q1'27E | N4: Q2'27E | O4: Q3'27E | P4: Q4'27E | R4: FY2025A | S4: FY2026E | T4: FY2027E | U4: FY2028E | V4: FY2029E
A5: Unit drivers
A6: Retail sales - worldwide | B6: units | C6: =Historicals!C32+Historicals!C33+Historicals!C34+Historicals!C35 -> 36166 | D6: =Historicals!D32+Historicals!D33+Historicals!D34+Historicals!D35 -> 25660 | E6: =Historicals!E32+Historicals!E33+Historicals!E34+Historicals!E35 -> 31010 | F6: =Historicals!F32+Historicals!F33+Historicals!F34+Historicals!F35 -> 42254 | G6: =Historicals!G32+Historicals!G33+Historicals!G34+Historicals!G35 -> 33984 | H6: =Historicals!H32+Historicals!H33+Historicals!H34+Historicals!H35 -> 25287 | I6: =Historicals!I32+Historicals!I33+Historicals!I34+Historicals!I35 -> 33507 | J6: =Historicals!J32+Historicals!J33+Historicals!J34+Historicals!J35 -> 42467 | K6: =G6*(1+Inputs!$F$66) -> 36702.72 | L6: =H6*(1+Inputs!$F$66) -> 27309.96 | M6: =I6*(1+Inputs!$F$67) -> 34847.28 | N6: =J6*(1+Inputs!$F$67) -> 44165.68 | O6: =K6*(1+Inputs!$F$67) -> 38170.829 | P6: =L6*(1+Inputs!$F$67) -> 28402.358 | R6: =SUM(E6:H6) -> 132535 | S6: =SUM(I6:L6) -> 139986.68 | T6: =SUM(M6:P6) -> 145586.15 | U6: =T6*(1+Inputs!$F$68) -> 149953.73 | V6: =U6*(1+Inputs!$F$69) -> 152952.81
A7: of which North America | B7: units | C7: =Historicals!C32 -> 24573 | D7: =Historicals!D32 -> 15127 | E7: =Historicals!E32 -> 20892 | F7: =Historicals!F32 -> 28931 | G7: =Historicals!G32 -> 23462 | H7: =Historicals!H32 -> 15847 | I7: =Historicals!I32 -> 23803 | J7: =Historicals!J32 -> 29751 | R7: =SUM(E7:H7) -> 89132
A8: Retail growth YoY | B8: % | G8: =G6/C6-1 -> -0.060332909 | H8: =H6/D6-1 -> -0.014536243 | I8: =I6/E6-1 -> 0.080522412 | J8: =J6/F6-1 -> 0.0050409429 | K8: =K6/G6-1 -> 0.08 | L8: =L6/H6-1 -> 0.08 | M8: =M6/I6-1 -> 0.04 | N8: =N6/J6-1 -> 0.04 | ... P8: =P6/L6-1 -> 0.04 | S8: =S6/R6-1 -> 0.056224243 | T8: =T6/S6-1 -> 0.04 | U8: =U6/T6-1 -> 0.03 | V8: =V6/U6-1 -> 0.02
A9: HDMC shipments - worldwide | B9: units | C9: =Historicals!C27 -> 27520 | D9: =Historicals!D27 -> 14010 | E9: =Historicals!E27 -> 38601 | F9: =Historicals!F27 -> 35837 | G9: =Historicals!G27 -> 36524 | H9: =Historicals!H27 -> 13515 | I9: =Historicals!I27 -> 37295 | J9: =Historicals!J27 -> 39209 | K9: =(Inputs!$F$70-I9-J9)*Inputs!$E$38 -> 37497.6 | L9: =Inputs!$F$70-I9-J9-K9 -> 24998.4 | M9: =$T9*Inputs!$E$39 -> 41579.404 | N9: =$T9*Inputs!$E$40 -> 43064.382 | O9: =$T9*Inputs!$E$41 -> 38609.446 | P9: =$T9*Inputs!$E$42 -> 25244.638 | R9: =SUM(E9:H9) -> 124477 | S9: =SUM(I9:L9) -> 139000 | T9: =T6*(1+Inputs!$F$71) -> 148497.87 | U9: =U6*(1+Inputs!$F$72) -> 151453.27 | V9: =V6*(1+Inputs!$F$73) -> 152952.81
A10: Shipment growth YoY | B10: % | G10: =G9/C9-1 -> 0.32718023 | H10: =H9/D9-1 -> -0.035331906 | I10: =I9/E9-1 -> -0.03383332 | J10: =J9/F9-1 -> 0.094092697 | K10: =K9/G9-1 -> 0.026656445 | L10: =L9/H9-1 -> 0.84967814 | M10: =M9/I9-1 -> 0.11487877 | N10: =N9/J9-1 -> 0.098329015 | ... P10: =P9/L9-1 -> 0.0098501474 | S10: =S9/R9-1 -> 0.11667216 | T10: =T9/S9-1 -> 0.068330001 | U10: =U9/T9-1 -> 0.019901961 | V10: =V9/U9-1 -> 0.0099009901
A11: Implied dealer inventory change (shipments - retail) | B11: units | C11: =C9-C6 -> -8646 | D11: =D9-D6 -> -11650 | E11: =E9-E6 -> 7591 | F11: =F9-F6 -> -6417 | G11: =G9-G6 -> 2540 | H11: =H9-H6 -> -11772 | I11: =I9-I6 -> 3788 | J11: =J9-J6 -> -3258 | ... P11: =P9-P6 -> -3157.7205 | R11: =R9-R6 -> -8058 | S11: =S9-S6 -> -986.68 | T11: =T9-T6 -> 2911.7229 | U11: =U9-U6 -> 1499.5373 | V11: =V9-V6 -> 0
A12: Reported global dealer inventory, YoY | B12: % | G12: =Historicals!G36 -> -0.13 | H12: =Historicals!H36 -> -0.17 | I12: =Historicals!I36 -> -0.22 | J12: =Historicals!J36 -> -0.17
A13: Sport & Lightweight share of shipments | B13: % | C13: =Historicals!C30/Historicals!C27 -> 0.06431686 | D13: =Historicals!D30/Historicals!D27 -> 0.1076374 | E13: =Historicals!E30/Historicals!E27 -> 0.054609984 | F13: =Historicals!F30/Historicals!F27 -> 0.088958339 | G13: =Historicals!G30/Historicals!G27 -> 0.071952689 | H13: =Historicals!H30/Historicals!H27 -> 0.12682205 | I13: =Historicals!I30/Historicals!I27 -> 0.10004022 | J13: =Historicals!J30/Historicals!J27 -> 0.11775358
A14: Touring share of shipments | B14: % | C14: =Historicals!C28/Historicals!C27 -> 0.56297238 | D14: =Historicals!D28/Historicals!D27 -> 0.39707352 | E14: =Historicals!E28/Historicals!E27 -> 0.6134038 | F14: =Historicals!F28/Historicals!F27 -> 0.50450652 | G14: =Historicals!G28/Historicals!G27 -> 0.60330194 | H14: =Historicals!H28/Historicals!H27 -> 0.40392157 | I14: =Historicals!I28/Historicals!I27 -> 0.57702105 | J14: =Historicals!J28/Historicals!J27 -> 0.50093091
A16: Income statement
A17: Motorcycle revenue per unit | B17: $000 | C17: =Historicals!C6/Historicals!C27 -> 22.370203 | D17: =Historicals!D6/Historicals!D27 -> 16.52177 | E17: =Historicals!E6/Historicals!E27 -> 22.379291 | F17: =Historicals!F6/Historicals!F27 -> 21.71083 | G17: =Historicals!G6/Historicals!G27 -> 22.502026 | H17: =Historicals!H6/Historicals!H27 -> 14.34569 | I17: =Historicals!I6/Historicals!I27 -> 22.423757 | J17: =Historicals!J6/Historicals!J27 -> 21.629141 | K17: =Inputs!$E$60*(1+Inputs!$F$74) -> 22.236674 | L17: =Inputs!$E$60*(1+Inputs!$F$74) -> 22.236674 | M17: =$K17*(1+Inputs!$F$75) -> 22.236674 | N17: =$K17*(1+Inputs!$F$75) -> 22.236674 | O17: =$K17*(1+Inputs!$F$75) -> 22.236674 | P17: =$K17*(1+Inputs!$F$75) -> 22.236674 | R17: =R18/R9*1000 -> 21.350611 | S17: =S18/S9*1000 -> 22.115498 | T17: =T18/T9*1000 -> 22.236674 | U17: =T17*(1+Inputs!$F$76) -> 22.681408 | V17: =U17*(1+Inputs!$F$77) -> 23.135036
A18: HDMC - Motorcycles revenue | B18: $m | C18: =Historicals!C6/1000 -> 615.628 | D18: =Historicals!D6/1000 -> 231.47 | E18: =Historicals!E6/1000 -> 863.863 | F18: =Historicals!F6/1000 -> 778.051 | G18: =Historicals!G6/1000 -> 821.864 | H18: =Historicals!H6/1000 -> 193.882 | I18: =Historicals!I6/1000 -> 836.294 | J18: =Historicals!J6/1000 -> 848.057 | K18: =K9*K17/1000 -> 833.82191 | L18: =L9*L17/1000 -> 555.88127 | M18: =M9*M17/1000 -> 924.58765 | N18: =N9*N17/1000 -> 957.60863 | O18: =O9*O17/1000 -> 858.54567 | P18: =P9*P17/1000 -> 561.35678 | R18: =SUM(E18:H18) -> 2657.66 | S18: =SUM(I18:L18) -> 3074.0542 | T18: =SUM(M18:P18) -> 3302.0987 | U18: =U9*U17/1000 -> 3435.1733 | V18: =V9*V17/1000 -> 3538.5686
A19: HDMC - Parts & accessories | B19: $m | C19: =(Historicals!C7)/1000 -> 174.301 | D19: =(Historicals!D7)/1000 -> 117.605 | E19: =(Historicals!E7)/1000 -> 143.433 | F19: =(Historicals!F7)/1000 -> 186.874 | G19: =(Historicals!G7)/1000 -> 167.252 | H19: =(Historicals!H7)/1000 -> 116.513 | I19: =(Historicals!I7)/1000 -> 142.243 | J19: =(Historicals!J7)/1000 -> 176.95 | K19: =G19*(1+Inputs!$F$78) -> 172.26956 | L19: =H19*(1+Inputs!$F$78) -> 120.00839 | M19: =I19*(1+Inputs!$F$78) -> 146.51029 | N19: =J19*(1+Inputs!$F$78) -> 182.2585 | O19: =K19*(1+Inputs!$F$78) -> 177.43765 | P19: =L19*(1+Inputs!$F$78) -> 123.60864 | R19: =SUM(E19:H19) -> 614.072 | S19: =SUM(I19:L19) -> 611.47095 | T19: =SUM(M19:P19) -> 629.81508 | U19: =T19*(1+Inputs!$F$78) -> 648.70953 | V19: =U19*(1+Inputs!$F$78) -> 668.17082
A20: HDMC - Apparel, licensing & other | B20: $m | C20: =(Historicals!C8+Historicals!C9+Historicals!C10)/1000 -> 86.476 | D20: =(Historicals!D8+Historicals!D9+Historicals!D10)/1000 -> 71.414 | E20: =(Historicals!E8+Historicals!E9+Historicals!E10)/1000 -> 74.209 | F20: =(Historicals!F8+Historicals!F9+Historicals!F10)/1000 -> 78.724 | G20: =(Historicals!G8+Historicals!G9+Historicals!G10)/1000 -> 84.843 | H20: =(Historicals!H8+Historicals!H9+Historicals!H10)/1000 -> 68.8 | I20: =(Historicals!I8+Historicals!I9+Historicals!I10)/1000 -> 76.934 | J20: =(Historicals!J8+Historicals!J9+Historicals!J10)/1000 -> 79.273 | K20: =G20*(1+Inputs!$F$78) -> 87.38829 | L20: =H20*(1+Inputs!$F$78) -> 70.864 | M20: =I20*(1+Inputs!$F$78) -> 79.24202 | N20: =J20*(1+Inputs!$F$78) -> 81.65119 | O20: =K20*(1+Inputs!$F$78) -> 90.009939 | P20: =L20*(1+Inputs!$F$78) -> 72.98992 | R20: =SUM(E20:H20) -> 306.576 | S20: =SUM(I20:L20) -> 314.45929 | T20: =SUM(M20:P20) -> 323.89307 | U20: =T20*(1+Inputs!$F$78) -> 333.60986 | V20: =U20*(1+Inputs!$F$78) -> 343.61816
A21: HDMC revenue | B21: $m | C21: =C18+C19+C20 -> 876.405 | D21: =D18+D19+D20 -> 420.489 | E21: =E18+E19+E20 -> 1081.505 | F21: =F18+F19+F20 -> 1043.649 | G21: =G18+G19+G20 -> 1073.959 | H21: =H18+H19+H20 -> 379.195 | I21: =I18+I19+I20 -> 1055.471 | J21: =J18+J19+J20 -> 1104.28 | ... P21: =P18+P19+P20 -> 757.95535 | R21: =R18+R19+R20 -> 3578.308 | S21: =S18+S19+S20 -> 3999.9844 | T21: =T18+T19+T20 -> 4255.8069 | U21: =U18+U19+U20 -> 4417.4927 | V21: =V18+V19+V20 -> 4550.3576
A22: HDMC revenue growth YoY | B22: % | G22: =G21/C21-1 -> 0.22541405 | H22: =H21/D21-1 -> -0.098204709 | I22: =I21/E21-1 -> -0.024072011 | J22: =J21/F21-1 -> 0.058095203 | K22: =K21/G21-1 -> 0.018176446 | L22: =L21/H21-1 -> 0.96931305 | M22: =M21/I21-1 -> 0.089883052 | N22: =N21/J21-1 -> 0.10616721 | ... P22: =P21/L21-1 -> 0.015000508 | S22: =S21/R21-1 -> 0.1178424 | T22: =T21/S21-1 -> 0.063955864 | U22: =U21/T21-1 -> 0.037991814 | V22: =V21/U21-1 -> 0.030076993
A23: HDMC gross profit | B23: $m | C23: =Historicals!C11/1000 -> 263.813 | D23: =Historicals!D11/1000 -> -3.17 | E23: =Historicals!E11/1000 -> 315.244 | F23: =Historicals!F11/1000 -> 298.705 | G23: =Historicals!G11/1000 -> 283.11 | H23: =Historicals!H11/1000 -> -30.467 | I23: =Historicals!I11/1000 -> 266.989 | J23: =Historicals!J11/1000 -> 304.126 | K23: =(Inputs!$E$57+Inputs!$F$79)*K21-Inputs!$E$58*(1+Inputs!$E$43)^0 -> 309.18677 | L23: =(Inputs!$E$57+Inputs!$F$79)*L21-Inputs!$E$58*(1+Inputs!$E$43)^0 -> 145.38351 | M23: =(Inputs!$E$57+Inputs!$F$80)*M21-Inputs!$E$58*(1+Inputs!$E$43)^1 -> 337.65277 | N23: =(Inputs!$E$57+Inputs!$F$80)*N21-Inputs!$E$58*(1+Inputs!$E$43)^1 -> 371.63534 | O23: =(Inputs!$E$57+Inputs!$F$80)*O21-Inputs!$E$58*(1+Inputs!$E$43)^1 -> 326.02896 | P23: =(Inputs!$E$57+Inputs!$F$80)*P21-Inputs!$E$58*(1+Inputs!$E$43)^1 -> 150.31719 | R23: =SUM(E23:H23) -> 866.592 | S23: =SUM(I23:L23) -> 1025.6853 | T23: =SUM(M23:P23) -> 1185.6343 | U23: =(Inputs!$E$57+Inputs!$F$80)*U21-4*Inputs!$E$58*(1+Inputs!$E$43)^2 -> 1245.9035 | V23: =(Inputs!$E$57+Inputs!$F$80)*V21-4*Inputs!$E$58*(1+Inputs!$E$43)^3 -> 1292.0743
A24: HDMC gross margin | B24: % | C24: =C23/C21 -> 0.30101722 | D24: =D23/D21 -> -0.0075388417 | E24: =E23/E21 -> 0.2914864 | F24: =F23/F21 -> 0.28621213 | G24: =G23/G21 -> 0.26361342 | H24: =H23/H21 -> -0.080346524 | I24: =I23/I21 -> 0.25295721 | J24: =J23/J21 -> 0.2754066 | ... P24: =P23/P21 -> 0.19831933 | R24: =R23/R21 -> 0.24217926 | S24: =S23/S21 -> 0.25642232 | T24: =T23/T21 -> 0.27859212 | U24: =U23/U21 -> 0.28203861 | V24: =V23/V21 -> 0.28395006
A25: HDMC operating expense | B25: $m | C25: =Historicals!C12/1000 -> 208.676 | D25: =Historicals!D12/1000 -> 210.472 | E25: =Historicals!E12/1000 -> 198.972 | F25: =Historicals!F12/1000 -> 237.389 | G25: =Historicals!G12/1000 -> 228.991 | H25: =Historicals!H12/1000 -> 229.97 | I25: =Historicals!I12/1000 -> 248.064 | J25: =Historicals!J12/1000 -> 231.788 | K25: =G25*(1+Inputs!$F$81) -> 228.991 | L25: =H25*(1+Inputs!$F$81) -> 229.97 | M25: =I25*(1+Inputs!$F$81) -> 248.064 | N25: =J25*(1+Inputs!$F$81) -> 231.788 | O25: =K25*(1+Inputs!$F$81) -> 228.991 | P25: =L25*(1+Inputs!$F$81) -> 229.97 | R25: =SUM(E25:H25) -> 895.322 | S25: =SUM(I25:L25) -> 938.813 | T25: =SUM(M25:P25) -> 938.813 | U25: =T25*(1+Inputs!$F$81) -> 938.813 | V25: =U25*(1+Inputs!$F$81) -> 938.813
A26: HDMC operating income | B26: $m | C26: =C23-C25 -> 55.137 | D26: =D23-D25 -> -213.642 | E26: =E23-E25 -> 116.272 | F26: =F23-F25 -> 61.316 | G26: =G23-G25 -> 54.119 | H26: =H23-H25 -> -260.437 | I26: =I23-I25 -> 18.925 | J26: =J23-J25 -> 72.338 | ... P26: =P23-P25 -> -79.652806 | R26: =R23-R25 -> -28.73 | S26: =S23-S25 -> 86.872282 | T26: =T23-T25 -> 246.82126 | U26: =U23-U25 -> 307.09049 | V26: =V23-V25 -> 353.26131
A27: HDMC operating margin | B27: % | C27: =C26/C21 -> 0.062912694 | D27: =D26/D21 -> -0.50807988 | E27: =E26/E21 -> 0.10750944 | F27: =F26/F21 -> 0.058751553 | G27: =G26/G21 -> 0.050392054 | H27: =H26/H21 -> -0.68681549 | I27: =I26/I21 -> 0.017930384 | J27: =J26/J21 -> 0.065506937 | ... P27: =P26/P21 -> -0.10508905 | R27: =R26/R21 -> -0.0080289343 | S27: =S26/S21 -> 0.021718155 | T27: =T26/T21 -> 0.057996349 | U27: =U26/U21 -> 0.069516921 | V27: =V26/V21 -> 0.077633747
A28: LiveWire revenue | B28: $m | C28: =Historicals!C13/1000 -> 4.808 | D28: =Historicals!D13/1000 -> 10.4 | E28: =Historicals!E13/1000 -> 2.743 | F28: =Historicals!F13/1000 -> 6.011 | G28: =Historicals!G13/1000 -> 5.563 | H28: =Historicals!H13/1000 -> 11.354 | I28: =Historicals!I13/1000 -> 5.116 | J28: =Historicals!J13/1000 -> 9.114 | K28: =G28*(1+Inputs!$F$86) -> 7.7882 | L28: =H28*(1+Inputs!$F$86) -> 15.8956 | M28: =I28*(1+Inputs!$F$86) -> 7.1624 | N28: =J28*(1+Inputs!$F$86) -> 12.7596 | O28: =K28*(1+Inputs!$F$86) -> 10.90348 | P28: =L28*(1+Inputs!$F$86) -> 22.25384 | R28: =SUM(E28:H28) -> 25.671 | S28: =SUM(I28:L28) -> 37.9138 | T28: =SUM(M28:P28) -> 53.07932 | U28: =T28*(1+Inputs!$F$86) -> 74.311048 | V28: =U28*(1+Inputs!$F$86) -> 104.03547
A29: LiveWire operating income (loss) | B29: $m | C29: =(Historicals!C14-Historicals!C15)/1000 -> -26.085 | D29: =(Historicals!D14-Historicals!D15)/1000 -> -26.146 | E29: =(Historicals!E14-Historicals!E15)/1000 -> -19.809 | F29: =(Historicals!F14-Historicals!F15)/1000 -> -18.653 | G29: =(Historicals!G14-Historicals!G15)/1000 -> -18.181 | H29: =(Historicals!H14-Historicals!H15)/1000 -> -18.374 | I29: =(Historicals!I14-Historicals!I15)/1000 -> -17.671 | J29: =(Historicals!J14-Historicals!J15)/1000 -> -17.927 | K29: =(Inputs!$F$82-I29-J29)/2 -> -17.201 | L29: =(Inputs!$F$82-I29-J29)/2 -> -17.201 | M29: =Inputs!$F$83/4 -> -13.75 | N29: =Inputs!$F$83/4 -> -13.75 | O29: =Inputs!$F$83/4 -> -13.75 | P29: =Inputs!$F$83/4 -> -13.75 | R29: =SUM(E29:H29) -> -75.017 | S29: =SUM(I29:L29) -> -70 | T29: =SUM(M29:P29) -> -55 | U29: =Inputs!$F$84 -> -40 | V29: =Inputs!$F$85 -> -30
A30: HDFS revenue | B30: $m | C30: =Historicals!C16/1000 -> 269.482 | D30: =Historicals!D16/1000 -> 256.72 | E30: =Historicals!E16/1000 -> 244.961 | F30: =Historicals!F16/1000 -> 257.438 | G30: =Historicals!G16/1000 -> 261.188 | H30: =Historicals!H16/1000 -> 105.609 | I30: =Historicals!I16/1000 -> 111.944 | J30: =Historicals!J16/1000 -> 117.043 | K30: =AVERAGE($I30:$J30)*(1+Inputs!$F$91)^0.5 -> 117.87827 | L30: =AVERAGE($I30:$J30)*(1+Inputs!$F$91)^0.5 -> 117.87827 | M30: =AVERAGE($I30:$J30)*(1+Inputs!$F$91)^1.5 -> 124.95097 | N30: =AVERAGE($I30:$J30)*(1+Inputs!$F$91)^1.5 -> 124.95097 | O30: =AVERAGE($I30:$J30)*(1+Inputs!$F$91)^1.5 -> 124.95097 | P30: =AVERAGE($I30:$J30)*(1+Inputs!$F$91)^1.5 -> 124.95097 | R30: =SUM(E30:H30) -> 869.196 | S30: =SUM(I30:L30) -> 464.74355 | T30: =SUM(M30:P30) -> 499.80388 | U30: =T30*(1+Inputs!$F$91) -> 529.79211 | V30: =U30*(1+Inputs!$F$91) -> 561.57964
A31: HDFS operating income | B31: $m | C31: =Historicals!C17/1000 -> 76.744 | D31: =Historicals!D17/1000 -> 46.44 | E31: =Historicals!E17/1000 -> 64.036 | F31: =Historicals!F17/1000 -> 69.773 | G31: =Historicals!G17/1000 -> 438.82 | H31: =Historicals!H17/1000 -> -82.247 | I31: =Historicals!I17/1000 -> 22.24 | J31: =Historicals!J17/1000 -> 21.599 | K31: =(Inputs!$F$87-I31-J31)/2 -> 10.5805 | L31: =(Inputs!$F$87-I31-J31)/2 -> 10.5805 | M31: =Inputs!$F$88/4 -> 18.75 | N31: =Inputs!$F$88/4 -> 18.75 | O31: =Inputs!$F$88/4 -> 18.75 | P31: =Inputs!$F$88/4 -> 18.75 | R31: =SUM(E31:H31) -> 490.382 | S31: =SUM(I31:L31) -> 65 | T31: =SUM(M31:P31) -> 75 | U31: =Inputs!$F$89 -> 85 | V31: =Inputs!$F$90 -> 90
A32: Total revenue | B32: $m | C32: =C21+C28+C30 -> 1150.695 | D32: =D21+D28+D30 -> 687.609 | E32: =E21+E28+E30 -> 1329.209 | F32: =F21+F28+F30 -> 1307.098 | G32: =G21+G28+G30 -> 1340.71 | H32: =H21+H28+H30 -> 496.158 | I32: =I21+I28+I30 -> 1172.531 | J32: =J21+J28+J30 -> 1230.437 | ... P32: =P21+P28+P30 -> 905.16016 | R32: =R21+R28+R30 -> 4473.175 | S32: =S21+S28+S30 -> 4502.6418 | T32: =T21+T28+T30 -> 4808.6901 | U32: =U21+U28+U30 -> 5021.5959 | V32: =V21+V28+V30 -> 5215.9727
A33: Consolidated operating income | B33: $m | C33: =C26+C29+C31 -> 105.796 | D33: =D26+D29+D31 -> -193.348 | E33: =E26+E29+E31 -> 160.499 | F33: =F26+F29+F31 -> 112.436 | G33: =G26+G29+G31 -> 474.758 | H33: =H26+H29+H31 -> -361.058 | I33: =I26+I29+I31 -> 23.494 | J33: =J26+J29+J31 -> 76.01 | ... P33: =P26+P29+P31 -> -74.652806 | R33: =R26+R29+R31 -> 386.635 | S33: =S26+S29+S31 -> 81.872282 | T33: =T26+T29+T31 -> 266.82126 | U33: =U26+U29+U31 -> 352.09049 | V33: =V26+V29+V31 -> 413.26131
A34: Other income, net | B34: $m | C34: =Historicals!C18/1000 -> 18.408 | D34: =Historicals!D18/1000 -> 17.445 | E34: =Historicals!E18/1000 -> 16.273 | F34: =Historicals!F18/1000 -> 14.477 | G34: =Historicals!G18/1000 -> 14.706 | H34: =Historicals!H18/1000 -> 15.814 | I34: =Historicals!I18/1000 -> 13.477 | J34: =Historicals!J18/1000 -> 11.047 | K34: =Inputs!$E$30 -> 12 | L34: =Inputs!$E$30 -> 12 | M34: =Inputs!$E$30 -> 12 | N34: =Inputs!$E$30 -> 12 | O34: =Inputs!$E$30 -> 12 | P34: =Inputs!$E$30 -> 12 | R34: =SUM(E34:H34) -> 61.27 | S34: =SUM(I34:L34) -> 48.524 | T34: =SUM(M34:P34) -> 48 | U34: =4*Inputs!$E$30 -> 48 | V34: =4*Inputs!$E$30 -> 48
A35: Investment income | B35: $m | C35: =Historicals!C19/1000 -> 16.45 | D35: =Historicals!D19/1000 -> 13.3 | E35: =Historicals!E19/1000 -> 8.941 | F35: =Historicals!F19/1000 -> 10.95 | G35: =Historicals!G19/1000 -> 12.267 | H35: =Historicals!H19/1000 -> 12.112 | I35: =Historicals!I19/1000 -> 8.696 | J35: =Historicals!J19/1000 -> 11.84 | K35: =Inputs!$E$31 -> 9 | L35: =Inputs!$E$31 -> 9 | M35: =Inputs!$E$31 -> 9 | N35: =Inputs!$E$31 -> 9 | O35: =Inputs!$E$31 -> 9 | P35: =Inputs!$E$31 -> 9 | R35: =SUM(E35:H35) -> 44.27 | S35: =SUM(I35:L35) -> 38.536 | T35: =SUM(M35:P35) -> 36 | U35: =4*Inputs!$E$31 -> 36 | V35: =4*Inputs!$E$31 -> 36
A36: Interest expense | B36: $m | C36: =-Historicals!C20/1000 -> -7.707 | D36: =-Historicals!D20/1000 -> -7.683 | E36: =-Historicals!E20/1000 -> -7.686 | F36: =-Historicals!F20/1000 -> -7.696 | G36: =-Historicals!G20/1000 -> -10.182 | H36: =-Historicals!H20/1000 -> -7.88 | I36: =-Historicals!I20/1000 -> -3.57 | J36: =-Historicals!J20/1000 -> -3.622 | K36: =-Inputs!$E$32 -> -3.6 | L36: =-Inputs!$E$32 -> -3.6 | M36: =-Inputs!$E$32 -> -3.6 | N36: =-Inputs!$E$32 -> -3.6 | O36: =-Inputs!$E$32 -> -3.6 | P36: =-Inputs!$E$32 -> -3.6 | R36: =SUM(E36:H36) -> -33.444 | S36: =SUM(I36:L36) -> -14.392 | T36: =SUM(M36:P36) -> -14.4 | U36: =-4*Inputs!$E$32 -> -14.4 | V36: =-4*Inputs!$E$32 -> -14.4
A37: Pre-tax income | B37: $m | C37: =C33+C34+C35+C36 -> 132.947 | D37: =D33+D34+D35+D36 -> -170.286 | E37: =E33+E34+E35+E36 -> 178.027 | F37: =F33+F34+F35+F36 -> 130.167 | G37: =G33+G34+G35+G36 -> 491.549 | H37: =H33+H34+H35+H36 -> -341.012 | I37: =I33+I34+I35+I36 -> 42.097 | J37: =J33+J34+J35+J36 -> 95.275 | ... P37: =P33+P34+P35+P36 -> -57.252806 | R37: =R33+R34+R35+R36 -> 458.731 | S37: =S33+S34+S35+S36 -> 154.54028 | T37: =T33+T34+T35+T36 -> 336.42126 | U37: =U33+U34+U35+U36 -> 421.69049 | V37: =V33+V34+V35+V36 -> 482.86131
A38: Income tax | B38: $m | C38: =-Historicals!C21/1000 -> -16.98 | D38: =-Historicals!D21/1000 -> 51.857 | E38: =-Historicals!E21/1000 -> -47.23 | F38: =-Historicals!F21/1000 -> -24.422 | G38: =-Historicals!G21/1000 -> -116.384 | H38: =-Historicals!H21/1000 -> 58.459 | I38: =-Historicals!I21/1000 -> -17.974 | J38: =-Historicals!J21/1000 -> -16.294 | K38: =-K37*Inputs!$E$29 -> -20.924313 | L38: =-L37*Inputs!$E$29 -> 16.975608 | M38: =-M37*Inputs!$E$29 -> -25.757416 | N38: =-N37*Inputs!$E$29 -> -37.316889 | O38: =-O37*Inputs!$E$29 -> -27.470731 | P38: =-P37*Inputs!$E$29 -> 13.168145 | R38: =SUM(E38:H38) -> -129.577 | S38: =SUM(I38:L38) -> -38.216705 | T38: =SUM(M38:P38) -> -77.37689 | U38: =-U37*Inputs!$E$29 -> -96.988813 | V38: =-V37*Inputs!$E$29 -> -111.0581
A39: Net income (incl. NCI) | B39: $m | C39: =C37+C38 -> 115.967 | D39: =D37+D38 -> -118.429 | E39: =E37+E38 -> 130.797 | F39: =F37+F38 -> 105.745 | G39: =G37+G38 -> 375.165 | H39: =H37+H38 -> -282.553 | I39: =I37+I38 -> 24.123 | J39: =J37+J38 -> 78.981 | ... P39: =P37+P38 -> -44.08466 | R39: =R37+R38 -> 329.154 | S39: =S37+S38 -> 116.32358 | T39: =T37+T38 -> 259.04437 | U39: =U37+U38 -> 324.70168 | V39: =V37+V38 -> 371.80321
A40: Add: loss attributable to NCI | B40: $m | C40: =Historicals!C22/1000 -> 3.073 | D40: =Historicals!D22/1000 -> 1.538 | E40: =Historicals!E22/1000 -> 2.307 | F40: =Historicals!F22/1000 -> 1.824 | G40: =Historicals!G22/1000 -> 2.201 | H40: =Historicals!H22/1000 -> 3.252 | I40: =Historicals!I22/1000 -> 0.65 | J40: =Historicals!J22/1000 -> 0.824 | K40: =-K29*Inputs!$E$35 -> 0.86005 | L40: =-L29*Inputs!$E$35 -> 0.86005 | M40: =-M29*Inputs!$E$35 -> 0.6875 | N40: =-N29*Inputs!$E$35 -> 0.6875 | O40: =-O29*Inputs!$E$35 -> 0.6875 | P40: =-P29*Inputs!$E$35 -> 0.6875 | R40: =SUM(E40:H40) -> 9.584 | S40: =SUM(I40:L40) -> 3.1941 | T40: =SUM(M40:P40) -> 2.75 | U40: =-U29*Inputs!$E$35 -> 2 | V40: =-V29*Inputs!$E$35 -> 1.5
A41: Net income attributable to HOG | B41: $m | C41: =C39+C40 -> 119.04 | D41: =D39+D40 -> -116.891 | E41: =E39+E40 -> 133.104 | F41: =F39+F40 -> 107.569 | G41: =G39+G40 -> 377.366 | H41: =H39+H40 -> -279.301 | I41: =I39+I40 -> 24.773 | J41: =J39+J40 -> 79.805 | ... P41: =P39+P40 -> -43.39716 | R41: =R39+R40 -> 338.738 | S41: =S39+S40 -> 119.51768 | T41: =T39+T40 -> 261.79437 | U41: =U39+U40 -> 326.70168 | V41: =V39+V40 -> 373.30321
A42: Diluted shares | B42: m | C42: =Historicals!C23/1000 -> 130.963 | D42: =Historicals!D23/1000 -> 126.264 | E42: =Historicals!E23/1000 -> 124.724 | F42: =Historicals!F23/1000 -> 122.203 | G42: =Historicals!G23/1000 -> 121.676 | H42: =Historicals!H23/1000 -> 114.311 | I42: =Historicals!I23/1000 -> 110.768 | J42: =Historicals!J23/1000 -> 108.568 | K42: =J42-Inputs!$F$92/Inputs!$E$5 -> 106.34165 | L42: =K42-Inputs!$F$92/Inputs!$E$5 -> 104.11531 | M42: =L42-Inputs!$F$92/Inputs!$E$5 -> 101.88896 | N42: =M42-Inputs!$F$92/Inputs!$E$5 -> 99.66262 | O42: =N42-Inputs!$F$92/Inputs!$E$5 -> 97.436275 | P42: =O42-Inputs!$F$92/Inputs!$E$5 -> 95.209929 | R42: =AVERAGE(E42:H42) -> 120.7285 | S42: =AVERAGE(I42:L42) -> 107.44824 | T42: =AVERAGE(M42:P42) -> 98.549447 | U42: =T42-4*Inputs!$F$92/Inputs!$E$5 -> 89.644067 | V42: =U42-4*Inputs!$F$92/Inputs!$E$5 -> 80.738686
A43: Diluted EPS | B43: $ | C43: =C41/C42 -> 0.90895902 | D43: =D41/D42 -> -0.92576665 | E43: =E41/E42 -> 1.0671884 | F43: =F41/F42 -> 0.88024844 | G43: =G41/G42 -> 3.1014004 | H43: =H41/H42 -> -2.4433432 | I43: =I41/I42 -> 0.22364762 | J43: =J41/J42 -> 0.73506927 | ... P43: =P41/P42 -> -0.45580498 | R43: =R41/R42 -> 2.8057832 | S43: =S41/S42 -> 1.1123279 | T43: =T41/T42 -> 2.6564773 | U43: =U41/U42 -> 3.6444317 | V43: =V41/V42 -> 4.6235977
A44: Diluted EPS - as reported (check) | B44: $ | C44: =Historicals!C24 -> 0.91 | D44: =Historicals!D24 -> -0.93 | E44: =Historicals!E24 -> 1.07 | F44: =Historicals!F24 -> 0.88 | G44: =Historicals!G24 -> 3.1 | H44: =Historicals!H24 -> -2.44 | I44: =Historicals!I24 -> 0.22 | J44: =Historicals!J24 -> 0.75
A45: Dividends per share | B45: $ | C45: =Historicals!C25 -> 0.1725 | D45: =Historicals!D25 -> 0.1725 | E45: =Historicals!E25 -> 0.18 | F45: =Historicals!F25 -> 0.18 | G45: =Historicals!G25 -> 0.18 | H45: =Historicals!H25 -> 0.18 | I45: =Historicals!I25 -> 0.1875 | J45: =Historicals!J25 -> 0.1875 | K45: =J45 -> 0.1875 | L45: =J45 -> 0.1875 | M45: =$J45*(1+Inputs!$E$45) -> 0.195 | N45: =$J45*(1+Inputs!$E$45) -> 0.195 | O45: =$J45*(1+Inputs!$E$45) -> 0.195 | P45: =$J45*(1+Inputs!$E$45) -> 0.195 | R45: =SUM(E45:H45) -> 0.72 | S45: =SUM(I45:L45) -> 0.75 | T45: =SUM(M45:P45) -> 0.78 | U45: =T45*(1+Inputs!$E$45) -> 0.8112 | V45: =U45*(1+Inputs!$E$45) -> 0.843648
A47: EBITDA & segment profit
A48: D&A | B48: $m | C48: =Historicals!C57/1000 -> 39.19 | D48: =Historicals!D57/1000 -> 41.11 | E48: =Historicals!E57/1000 -> 41.7 | F48: =Historicals!F57/1000 -> 40.43 | G48: =Historicals!G57/1000 -> 44.21 | H48: =Historicals!H57/1000 -> 46.03 | I48: =Historicals!I57/1000 -> 44.14 | J48: =Historicals!J57/1000 -> 42.56 | K48: =Inputs!$E$33 -> 43 | L48: =Inputs!$E$33 -> 43 | M48: =Inputs!$E$33 -> 43 | N48: =Inputs!$E$33 -> 43 | O48: =Inputs!$E$33 -> 43 | P48: =Inputs!$E$33 -> 43 | R48: =SUM(E48:H48) -> 172.37 | S48: =SUM(I48:L48) -> 172.7 | T48: =SUM(M48:P48) -> 172 | U48: =4*Inputs!$E$33 -> 172 | V48: =4*Inputs!$E$33 -> 172
A49: Industrial EBITDA (HDMC + LiveWire + D&A) | B49: $m | C49: =C26+C29+C48 -> 68.242 | D49: =D26+D29+D48 -> -198.678 | E49: =E26+E29+E48 -> 138.163 | F49: =F26+F29+F48 -> 83.093 | G49: =G26+G29+G48 -> 80.148 | H49: =H26+H29+H48 -> -232.781 | I49: =I26+I29+I48 -> 45.394 | J49: =J26+J29+J48 -> 96.971 | ... P49: =P26+P29+P48 -> -50.402806 | R49: =R26+R29+R48 -> 68.623 | S49: =S26+S29+S48 -> 189.57228 | T49: =T26+T29+T48 -> 363.82126 | U49: =U26+U29+U48 -> 439.09049 | V49: =V26+V29+V48 -> 495.26131
A50: Consolidated EBITDA | B50: $m | C50: =C33+C48 -> 144.986 | D50: =D33+D48 -> -152.238 | E50: =E33+E48 -> 202.199 | F50: =F33+F48 -> 152.866 | G50: =G33+G48 -> 518.968 | H50: =H33+H48 -> -315.028 | I50: =I33+I48 -> 67.634 | J50: =J33+J48 -> 118.57 | ... P50: =P33+P48 -> -31.652806 | R50: =R33+R48 -> 559.005 | S50: =S33+S48 -> 254.57228 | T50: =T33+T48 -> 438.82126 | U50: =U33+U48 -> 524.09049 | V50: =V33+V48 -> 585.26131
A51: Consensus EPS | B51: $ | S51: =Inputs!$E$7 -> 0.68
A52: Model EPS vs. consensus | B52: % | S52: =S43/S51-1 -> 0.63577633
A53: Check: FY26 HDMC op. income within guidance $10-50m? | S53: =IF(AND(S26>=Inputs!$E$24,S26<=Inputs!$E$25),"Yes","No") -> No
A55: Balance sheet (period end)
A56: Cash & equivalents (incl. restricted) | B56: $m | C56: =(Historicals!C38+Historicals!C39)/1000 -> 2391.82 | D56: =(Historicals!D38+Historicals!D39)/1000 -> 1725.269 | E56: =(Historicals!E38+Historicals!E39)/1000 -> 2081.307 | F56: =(Historicals!F38+Historicals!F39)/1000 -> 1737.446 | G56: =(Historicals!G38+Historicals!G39)/1000 -> 1826.568 | H56: =(Historicals!H38+Historicals!H39)/1000 -> 3091.744 | I56: =(Historicals!I38+Historicals!I39)/1000 -> 1805.068 | J56: =(Historicals!J38+Historicals!J39)/1000 -> 1895.789 | K56: =J56+K87 -> 1806.939 | L56: =K56+L87 -> 1594.3997 | M56: =L56+M87 -> 1834.9956 | N56: =M56+N87 -> 1786.3556 | O56: =N56+O87 -> 1743.0346 | P56: =O56+P87 -> 1567.049 | R56: =H56 -> 3091.744 | S56: =L56 -> 1594.3997 | T56: =P56 -> 1567.049 | U56: =T56+U87 -> 1595.0437 | V56: =U56+V87 -> 1676.096
A57: Accounts receivable | B57: $m | C57: =Historicals!C40/1000 -> 307.701 | D57: =Historicals!D40/1000 -> 234.315 | E57: =Historicals!E40/1000 -> 313.334 | F57: =Historicals!F40/1000 -> 325.756 | G57: =Historicals!G40/1000 -> 305.01 | H57: =Historicals!H40/1000 -> 225.76 | I57: =Historicals!I40/1000 -> 285.786 | J57: =Historicals!J40/1000 -> 301.788 | K57: =G57*($S$21/$R$21) -> 340.95311 | L57: =H57*($S$21/$R$21) -> 252.3641 | M57: =I57*($T$21/$S$21) -> 304.06369 | N57: =J57*($T$21/$S$21) -> 321.08911 | O57: =K57*($T$21/$S$21) -> 362.75906 | P57: =L57*($T$21/$S$21) -> 268.50427 | R57: =H57 -> 225.76 | S57: =L57 -> 252.3641 | T57: =P57 -> 268.50427 | U57: =T57*U21/T21 -> 278.70523 | V57: =U57*V21/U21 -> 287.08784
A58: Finance receivables (total) | B58: $m | C58: =(Historicals!C41+Historicals!C42+Historicals!C45)/1000 -> 7800.387 | D58: =(Historicals!D41+Historicals!D42+Historicals!D45)/1000 -> 7288.294 | E58: =(Historicals!E41+Historicals!E42+Historicals!E45)/1000 -> 7399.607 | F58: =(Historicals!F41+Historicals!F42+Historicals!F45)/1000 -> 7326.222 | G58: =(Historicals!G41+Historicals!G42+Historicals!G45)/1000 -> 5964.434 | H58: =(Historicals!H41+Historicals!H42+Historicals!H45)/1000 -> 1965.224 | I58: =(Historicals!I41+Historicals!I42+Historicals!I45)/1000 -> 2441.403 | J58: =(Historicals!J41+Historicals!J42+Historicals!J45)/1000 -> 2645.18 | K58: =J58*(1+Inputs!$E$44)^0.25 -> 2645.18 | L58: =K58*(1+Inputs!$E$44)^0.25 -> 2645.18 | M58: =L58*(1+Inputs!$E$44)^0.25 -> 2645.18 | N58: =M58*(1+Inputs!$E$44)^0.25 -> 2645.18 | O58: =N58*(1+Inputs!$E$44)^0.25 -> 2645.18 | P58: =O58*(1+Inputs!$E$44)^0.25 -> 2645.18 | R58: =H58 -> 1965.224 | S58: =L58 -> 2645.18 | T58: =P58 -> 2645.18 | U58: =T58*(1+Inputs!$E$44) -> 2645.18 | V58: =U58*(1+Inputs!$E$44) -> 2645.18
A59: Inventories | B59: $m | C59: =Historicals!C43/1000 -> 681.864 | D59: =Historicals!D43/1000 -> 745.793 | E59: =Historicals!E43/1000 -> 712.312 | F59: =Historicals!F43/1000 -> 630.287 | G59: =Historicals!G43/1000 -> 512.186 | H59: =Historicals!H43/1000 -> 730.898 | I59: =Historicals!I43/1000 -> 622.189 | J59: =Historicals!J43/1000 -> 500.935 | K59: =G59*($S$21/$R$21) -> 572.54323 | L59: =H59*($S$21/$R$21) -> 817.02878 | M59: =I59*($T$21/$S$21) -> 661.98164 | N59: =J59*($T$21/$S$21) -> 532.97273 | O59: =K59*($T$21/$S$21) -> 609.16073 | P59: =L59*($T$21/$S$21) -> 869.28256 | R59: =H59 -> 730.898 | S59: =L59 -> 817.02878 | T59: =P59 -> 869.28256 | U59: =T59*(U21-U23)/(T21-T23) -> 897.99745 | V59: =U59*(V21-V23)/(U21-U23) -> 922.54384
A60: Other current assets | B60: $m | C60: =Historicals!C44/1000 -> 208 | D60: =Historicals!D44/1000 -> 259.764 | E60: =Historicals!E44/1000 -> 253.687 | F60: =Historicals!F44/1000 -> 327.26 | G60: =Historicals!G44/1000 -> 297.444 | H60: =Historicals!H44/1000 -> 292.383 | I60: =Historicals!I44/1000 -> 415.301 | J60: =Historicals!J44/1000 -> 250.42 | K60: =J60 -> 250.42 | L60: =K60 -> 250.42 | M60: =L60 -> 250.42 | N60: =M60 -> 250.42 | O60: =N60 -> 250.42 | P60: =O60 -> 250.42 | R60: =H60 -> 292.383 | S60: =L60 -> 250.42 | T60: =P60 -> 250.42 | U60: =T60 -> 250.42 | V60: =U60 -> 250.42
A61: Other long-term assets (incl. PP&E) | B61: $m | C61: =Historicals!C46/1000 -> 1636.887 | D61: =Historicals!D46/1000 -> 1628.144 | E61: =Historicals!E46/1000 -> 1622.134 | F61: =Historicals!F46/1000 -> 1703.474 | G61: =Historicals!G46/1000 -> 1660.742 | H61: =Historicals!H46/1000 -> 1738.806 | I61: =Historicals!I46/1000 -> 1675.914 | J61: =Historicals!J46/1000 -> 1651.753 | K61: =J61-K79-K48 -> 1681.406 | L61: =K61-L79-L48 -> 1711.059 | M61: =L61-M79-M48 -> 1714.309 | N61: =M61-N79-N48 -> 1717.559 | O61: =N61-O79-O48 -> 1720.809 | P61: =O61-P79-P48 -> 1724.059 | R61: =H61 -> 1738.806 | S61: =L61 -> 1711.059 | T61: =P61 -> 1724.059 | U61: =T61-U79-U48 -> 1737.059 | V61: =U61-V79-V48 -> 1750.059
A62: Total assets | B62: $m | C62: =C56+C57+C58+C59+C60+C61 -> 13026.659 | D62: =D56+D57+D58+D59+D60+D61 -> 11881.579 | E62: =E56+E57+E58+E59+E60+E61 -> 12382.381 | F62: =F56+F57+F58+F59+F60+F61 -> 12050.445 | G62: =G56+G57+G58+G59+G60+G61 -> 10566.384 | H62: =H56+H57+H58+H59+H60+H61 -> 8044.815 | I62: =I56+I57+I58+I59+I60+I61 -> 7245.661 | J62: =J56+J57+J58+J59+J60+J61 -> 7245.865 | ... P62: =P56+P57+P58+P59+P60+P61 -> 7324.4948 | R62: =R56+R57+R58+R59+R60+R61 -> 8044.815 | S62: =S56+S57+S58+S59+S60+S61 -> 7270.4515 | T62: =T56+T57+T58+T59+T60+T61 -> 7324.4948 | U62: =U56+U57+U58+U59+U60+U61 -> 7404.4054 | V62: =V56+V57+V58+V59+V60+V61 -> 7531.3867
A63: Accounts payable & accrued | B63: $m | C63: =Historicals!C48/1000 -> 931.971 | D63: =Historicals!D48/1000 -> 892.678 | E63: =Historicals!E48/1000 -> 1105.802 | F63: =Historicals!F48/1000 -> 1040.616 | G63: =Historicals!G48/1000 -> 971.411 | H63: =Historicals!H48/1000 -> 1061.194 | I63: =Historicals!I48/1000 -> 1232.554 | J63: =Historicals!J48/1000 -> 1033.42 | K63: =G63*($S$21/$R$21) -> 1085.8844 | L63: =H63*($S$21/$R$21) -> 1186.2477 | M63: =I63*($T$21/$S$21) -> 1311.3831 | N63: =J63*($T$21/$S$21) -> 1099.5133 | O63: =K63*($T$21/$S$21) -> 1155.3331 | P63: =L63*($T$21/$S$21) -> 1262.1151 | R63: =H63 -> 1061.194 | S63: =L63 -> 1186.2477 | T63: =P63 -> 1262.1151 | U63: =T63*(U21-U23+U25)/(T21-T23+T25) -> 1294.0433 | V63: =U63*(V21-V23+V25)/(U21-U23+U25) -> 1321.3364
A64: Debt & deposits (mostly HDFS funding) | B64: $m | C64: =(Historicals!C49+Historicals!C50+Historicals!C51+Historicals!C52)/1000 -> 7977.053 | D64: =(Historicals!D49+Historicals!D50+Historicals!D51+Historicals!D52)/1000 -> 7133.481 | E64: =(Historicals!E49+Historicals!E50+Historicals!E51+Historicals!E52)/1000 -> 7479.237 | F64: =(Historicals!F49+Historicals!F50+Historicals!F51+Historicals!F52)/1000 -> 7097.835 | G64: =(Historicals!G49+Historicals!G50+Historicals!G51+Historicals!G52)/1000 -> 5454.488 | H64: =(Historicals!H49+Historicals!H50+Historicals!H51+Historicals!H52)/1000 -> 3247.112 | I64: =(Historicals!I49+Historicals!I50+Historicals!I51+Historicals!I52)/1000 -> 2380.438 | J64: =(Historicals!J49+Historicals!J50+Historicals!J51+Historicals!J52)/1000 -> 2508.875 | K64: =K58*Inputs!$E$61-Inputs!$E$26 -> 2508.875 | L64: =L58*Inputs!$E$61-Inputs!$E$26 -> 2508.875 | M64: =M58*Inputs!$E$61-Inputs!$E$26 -> 2508.875 | N64: =N58*Inputs!$E$61-Inputs!$E$26 -> 2508.875 | O64: =O58*Inputs!$E$61-Inputs!$E$26 -> 2508.875 | P64: =P58*Inputs!$E$61-Inputs!$E$26 -> 2508.875 | R64: =H64 -> 3247.112 | S64: =L64 -> 2508.875 | T64: =P64 -> 2508.875 | U64: =U58*Inputs!$E$61-Inputs!$E$26 -> 2508.875 | V64: =V58*Inputs!$E$61-Inputs!$E$26 -> 2508.875
A65: Other long-term liabilities | B65: $m | C65: =Historicals!C53/1000 -> 692.523 | D65: =Historicals!D53/1000 -> 696.92 | E65: =Historicals!E53/1000 -> 623.652 | F65: =Historicals!F53/1000 -> 604.061 | G65: =Historicals!G53/1000 -> 579.106 | H65: =Historicals!H53/1000 -> 579.659 | I65: =Historicals!I53/1000 -> 552.534 | J65: =Historicals!J53/1000 -> 587.551 | K65: =J65 -> 587.551 | L65: =K65 -> 587.551 | M65: =L65 -> 587.551 | N65: =M65 -> 587.551 | O65: =N65 -> 587.551 | P65: =O65 -> 587.551 | R65: =H65 -> 579.659 | S65: =L65 -> 587.551 | T65: =P65 -> 587.551 | U65: =T65 -> 587.551 | V65: =U65 -> 587.551
A66: Total equity (incl. NCI) | B66: $m | C66: =Historicals!C54/1000 -> 3425.112 | D66: =Historicals!D54/1000 -> 3158.5 | E66: =Historicals!E54/1000 -> 3173.69 | F66: =Historicals!F54/1000 -> 3307.933 | G66: =Historicals!G54/1000 -> 3561.379 | H66: =Historicals!H54/1000 -> 3156.85 | I66: =Historicals!I54/1000 -> 3080.135 | J66: =Historicals!J54/1000 -> 3116.019 | K66: =J66+K39+K73+K83+K84 -> 3115.1309 | L66: =K66+L39+L73+L83+L84 -> 2987.7779 | M66: =L66+M39+M73+M83+M84 -> 3003.1409 | N66: =M66+N39+N73+N83+N84 -> 3057.6371 | O66: =N66+O39+O73+O83+O84 -> 3079.6043 | P66: =O66+P39+P73+P83+P84 -> 2965.9537 | R66: =H66 -> 3156.85 | S66: =L66 -> 2987.7779 | T66: =P66 -> 2965.9537 | U66: =T66+U39+U73+U83+U84 -> 3013.9361 | V66: =U66+V39+V73+V83+V84 -> 3113.6243
A67: Total liabilities & equity | B67: $m | C67: =C63+C64+C65+C66 -> 13026.659 | D67: =D63+D64+D65+D66 -> 11881.579 | E67: =E63+E64+E65+E66 -> 12382.381 | F67: =F63+F64+F65+F66 -> 12050.445 | G67: =G63+G64+G65+G66 -> 10566.384 | H67: =H63+H64+H65+H66 -> 8044.815 | I67: =I63+I64+I65+I66 -> 7245.661 | J67: =J63+J64+J65+J66 -> 7245.865 | ... P67: =P63+P64+P65+P66 -> 7324.4948 | R67: =R63+R64+R65+R66 -> 8044.815 | S67: =S63+S64+S65+S66 -> 7270.4515 | T67: =T63+T64+T65+T66 -> 7324.4948 | U67: =U63+U64+U65+U66 -> 7404.4054 | V67: =V63+V64+V65+V66 -> 7531.3867
A68: Balance check (assets - L&E) | B68: $m | C68: =ROUND(C62-C67,3) -> 0 | D68: =ROUND(D62-D67,3) -> 0 | E68: =ROUND(E62-E67,3) -> 0 | F68: =ROUND(F62-F67,3) -> 0 | G68: =ROUND(G62-G67,3) -> 0 | H68: =ROUND(H62-H67,3) -> 0 | I68: =ROUND(I62-I67,3) -> 0 | J68: =ROUND(J62-J67,3) -> 0 | ... P68: =ROUND(P62-P67,3) -> 0 | R68: =ROUND(R62-R67,3) -> 0 | S68: =ROUND(S62-S67,3) -> 0 | T68: =ROUND(T62-T67,3) -> 0 | U68: =ROUND(U62-U67,3) -> 0 | V68: =ROUND(V62-V67,3) -> 0
A70: Cash flow statement
A71: Net income (incl. NCI) | B71: $m | C71: =C39 -> 115.967 | D71: =D39 -> -118.429 | E71: =E39 -> 130.797 | F71: =F39 -> 105.745 | G71: =G39 -> 375.165 | H71: =H39 -> -282.553 | I71: =I39 -> 24.123 | J71: =J39 -> 78.981 | ... P71: =P39 -> -44.08466 | R71: =SUM(E71:H71) -> 329.154 | S71: =SUM(I71:L71) -> 116.32358 | T71: =SUM(M71:P71) -> 259.04437 | U71: =U39 -> 324.70168 | V71: =V39 -> 371.80321
A72: D&A | B72: $m | C72: =Historicals!C57/1000 -> 39.19 | D72: =Historicals!D57/1000 -> 41.11 | E72: =Historicals!E57/1000 -> 41.7 | F72: =Historicals!F57/1000 -> 40.43 | G72: =Historicals!G57/1000 -> 44.21 | H72: =Historicals!H57/1000 -> 46.03 | I72: =Historicals!I57/1000 -> 44.14 | J72: =Historicals!J57/1000 -> 42.56 | K72: =K48 -> 43 | L72: =L48 -> 43 | M72: =M48 -> 43 | N72: =N48 -> 43 | O72: =O48 -> 43 | P72: =P48 -> 43 | R72: =SUM(E72:H72) -> 172.37 | S72: =SUM(I72:L72) -> 172.7 | T72: =SUM(M72:P72) -> 172 | U72: =U48 -> 172 | V72: =V48 -> 172
A73: Stock-based compensation | B73: $m | C73: =Historicals!C58/1000 -> 10.83 | D73: =Historicals!D58/1000 -> 9.19 | E73: =Historicals!E58/1000 -> 6.82 | F73: =Historicals!F58/1000 -> 10.59 | G73: =Historicals!G58/1000 -> 8.43 | H73: =Historicals!H58/1000 -> 5.91 | I73: =Historicals!I58/1000 -> 8.54 | J73: =Historicals!J58/1000 -> 9.49 | K73: =Inputs!$E$34 -> 9 | L73: =Inputs!$E$34 -> 9 | M73: =Inputs!$E$34 -> 9 | N73: =Inputs!$E$34 -> 9 | O73: =Inputs!$E$34 -> 9 | P73: =Inputs!$E$34 -> 9 | R73: =SUM(E73:H73) -> 31.75 | S73: =SUM(I73:L73) -> 36.03 | T73: =SUM(M73:P73) -> 36 | U73: =4*Inputs!$E$34 -> 36 | V73: =4*Inputs!$E$34 -> 36
A74: (Increase)/decrease in receivables | B74: $m | K74: =-(K57-J57) -> -39.165112 | L74: =-(L57-K57) -> 88.589011 | M74: =-(M57-L57) -> -51.699589 | N74: =-(N57-M57) -> -17.025422 | O74: =-(O57-N57) -> -41.66995 | P74: =-(P57-O57) -> 94.254797 | R74: =SUM(E74:H74) -> 0 | S74: =SUM(I74:L74) -> 49.423899 | T74: =SUM(M74:P74) -> -16.140164 | U74: =-(U57-T57) -> -10.200964 | V74: =-(V57-U57) -> -8.3826152
A75: (Increase)/decrease in inventories | B75: $m | K75: =-(K59-J59) -> -71.60823 | L75: =-(L59-K59) -> -244.48555 | M75: =-(M59-L59) -> 155.04714 | N75: =-(N59-M59) -> 129.0089 | O75: =-(O59-N59) -> -76.187996 | P75: =-(P59-O59) -> -260.12183 | R75: =SUM(E75:H75) -> 0 | S75: =SUM(I75:L75) -> -316.09378 | T75: =SUM(M75:P75) -> -52.253781 | U75: =-(U59-T59) -> -28.714892 | V75: =-(V59-U59) -> -24.546389
A76: Increase/(decrease) in payables & accrued | B76: $m | K76: =(K63-J63) -> 52.464408 | L76: =(L63-K63) -> 100.36324 | M76: =(M63-L63) -> 125.1354 | N76: =(N63-M63) -> -211.86979 | O76: =(O63-N63) -> 55.819815 | P76: =(P63-O63) -> 106.78206 | R76: =SUM(E76:H76) -> 0 | S76: =SUM(I76:L76) -> 152.82765 | T76: =SUM(M76:P76) -> 75.867494 | U76: =(U63-T63) -> 31.928131 | V76: =(V63-U63) -> 27.293166
A77: Other operating items (historical plug) | B77: $m | C77: =C78-C71-C72-C73 -> 187.026 | D77: =D78-D71-D72-D73 -> 201.307 | E77: =E78-E71-E72-E73 -> -37.783 | F77: =F78-F71-F72-F73 -> 211.193 | G77: =G78-G71-G72-G73 -> -520.394 | H77: =H78-H71-H72-H73 -> 382.632 | I77: =I78-I71-I72-I73 -> -304.824 | J77: =J78-J71-J72-J73 -> 37.305 | K77: =0 -> 0 | L77: =0 -> 0 | M77: =0 -> 0 | N77: =0 -> 0 | O77: =0 -> 0 | P77: =0 -> 0 | R77: =SUM(E77:H77) -> 35.648 | S77: =SUM(I77:L77) -> -267.519 | T77: =SUM(M77:P77) -> 0 | U77: =0 -> 0 | V77: =0 -> 0
A78: Cash from operations | B78: $m | C78: =Historicals!C56/1000 -> 353.013 | D78: =Historicals!D56/1000 -> 133.178 | E78: =Historicals!E56/1000 -> 141.534 | F78: =Historicals!F56/1000 -> 367.958 | G78: =Historicals!G56/1000 -> -92.589 | H78: =Historicals!H56/1000 -> 152.019 | I78: =Historicals!I56/1000 -> -228.021 | J78: =Historicals!J56/1000 -> 168.336 | K78: =SUM(K71:K77) -> 63.742028 | L78: =SUM(L71:L77) -> -60.364678 | M78: =SUM(M71:M77) -> 366.71431 | N78: =SUM(N71:N77) -> 77.044149 | O78: =SUM(O71:O77) -> 81.929097 | P78: =SUM(P71:P77) -> -51.169633 | R78: =SUM(E78:H78) -> 568.922 | S78: =SUM(I78:L78) -> -56.307649 | T78: =SUM(M78:P78) -> 474.51792 | U78: =SUM(U71:U77) -> 525.71395 | V78: =SUM(V71:V77) -> 574.16737
A79: Capital expenditures | B79: $m | C79: =Historicals!C59/1000 -> -52.589 | D79: =Historicals!D59/1000 -> -56.139 | E79: =Historicals!E59/1000 -> -29.973 | F79: =Historicals!F59/1000 -> -35.587 | G79: =Historicals!G59/1000 -> -36.53 | H79: =Historicals!H59/1000 -> -51.589 | I79: =Historicals!I59/1000 -> -31.792 | J79: =Historicals!J59/1000 -> -12.902 | K79: =-(Inputs!$E$36+I79+J79)/2 -> -72.653 | L79: =-(Inputs!$E$36+I79+J79)/2 -> -72.653 | M79: =-Inputs!$E$37/4 -> -46.25 | N79: =-Inputs!$E$37/4 -> -46.25 | O79: =-Inputs!$E$37/4 -> -46.25 | P79: =-Inputs!$E$37/4 -> -46.25 | R79: =SUM(E79:H79) -> -153.679 | S79: =SUM(I79:L79) -> -190 | T79: =SUM(M79:P79) -> -185 | U79: =-Inputs!$E$37 -> -185 | V79: =-Inputs!$E$37 -> -185
A80: (Increase)/decrease in finance receivables | B80: $m | K80: =-(K58-J58) -> 0 | L80: =-(L58-K58) -> 0 | M80: =-(M58-L58) -> 0 | N80: =-(N58-M58) -> 0 | O80: =-(O58-N58) -> 0 | P80: =-(P58-O58) -> 0 | R80: =SUM(E80:H80) -> 0 | S80: =SUM(I80:L80) -> 0 | T80: =SUM(M80:P80) -> 0 | U80: =-(U58-T58) -> 0 | V80: =-(V58-U58) -> 0
A81: Cash from investing | B81: $m | C81: =Historicals!C60/1000 -> -89.148 | D81: =Historicals!D60/1000 -> 102.847 | E81: =Historicals!E60/1000 -> 61.395 | F81: =Historicals!F60/1000 -> -151.249 | G81: =Historicals!G60/1000 -> 295.331 | H81: =Historicals!H60/1000 -> 3573.298 | I81: =Historicals!I60/1000 -> -92.004 | J81: =Historicals!J60/1000 -> -174.734 | K81: =K79+K80 -> -72.653 | L81: =L79+L80 -> -72.653 | M81: =M79+M80 -> -46.25 | N81: =N79+N80 -> -46.25 | O81: =O79+O80 -> -46.25 | P81: =P79+P80 -> -46.25 | R81: =SUM(E81:H81) -> 3778.775 | S81: =SUM(I81:L81) -> -412.044 | T81: =SUM(M81:P81) -> -185 | U81: =U79+U80 -> -185 | V81: =V79+V80 -> -185
A82: Increase/(decrease) in debt & deposits | B82: $m | K82: =(K64-J64) -> 0 | L82: =(L64-K64) -> 0 | M82: =(M64-L64) -> 0 | N82: =(N64-M64) -> 0 | O82: =(O64-N64) -> 0 | P82: =(P64-O64) -> 0 | R82: =SUM(E82:H82) -> 0 | S82: =SUM(I82:L82) -> 0 | T82: =SUM(M82:P82) -> 0 | U82: =(U64-T64) -> 0 | V82: =(V64-U64) -> 0
A83: Dividends | B83: $m | C83: =Historicals!C61/1000 -> -22.095 | D83: =Historicals!D61/1000 -> -21.77 | E83: =Historicals!E61/1000 -> -22.921 | F83: =Historicals!F61/1000 -> -21.835 | G83: =Historicals!G61/1000 -> -21.532 | H83: =Historicals!H61/1000 -> -20.1 | I83: =Historicals!I61/1000 -> -21.54 | J83: =Historicals!J61/1000 -> -19.671 | K83: =-K45*K42 -> -19.93906 | L83: =-L45*L42 -> -19.521621 | M83: =-M45*M42 -> -19.868348 | N83: =-N45*N42 -> -19.434211 | O83: =-O45*O42 -> -19.000074 | P83: =-P45*P42 -> -18.565936 | R83: =SUM(E83:H83) -> -86.388 | S83: =SUM(I83:L83) -> -80.671681 | T83: =SUM(M83:P83) -> -76.868569 | U83: =-U45*U42 -> -72.719267 | V83: =-V45*V42 -> -68.115031
A84: Share repurchases | B84: $m | C84: =Historicals!C62/1000 -> -150.135 | D84: =Historicals!D62/1000 -> -100.019 | E84: =Historicals!E62/1000 -> -93.095 | F84: =Historicals!F62/1000 -> -0.045 | G84: =Historicals!G62/1000 -> -100.069 | H84: =Historicals!H62/1000 -> -160.061 | I84: =Historicals!I62/1000 -> -70.018 | J84: =Historicals!J62/1000 -> -30.37 | K84: =-Inputs!$F$92 -> -60 | L84: =-Inputs!$F$92 -> -60 | M84: =-Inputs!$F$92 -> -60 | N84: =-Inputs!$F$92 -> -60 | O84: =-Inputs!$F$92 -> -60 | P84: =-Inputs!$F$92 -> -60 | R84: =SUM(E84:H84) -> -353.27 | S84: =SUM(I84:L84) -> -220.388 | T84: =SUM(M84:P84) -> -240 | U84: =-4*Inputs!$F$92 -> -240 | V84: =-4*Inputs!$F$92 -> -240
A85: Cash from financing | B85: $m | C85: =Historicals!C63/1000 -> 131.462 | D85: =Historicals!D63/1000 -> -885.775 | E85: =Historicals!E63/1000 -> 150.185 | F85: =Historicals!F63/1000 -> -566.704 | G85: =Historicals!G63/1000 -> -131.156 | H85: =Historicals!H63/1000 -> -2462.625 | I85: =Historicals!I63/1000 -> -959.337 | J85: =Historicals!J63/1000 -> 100.433 | K85: =SUM(K82:K84) -> -79.93906 | L85: =SUM(L82:L84) -> -79.521621 | M85: =SUM(M82:M84) -> -79.868348 | N85: =SUM(N82:N84) -> -79.434211 | O85: =SUM(O82:O84) -> -79.000074 | P85: =SUM(P82:P84) -> -78.565936 | R85: =SUM(E85:H85) -> -3010.3 | S85: =SUM(I85:L85) -> -1018.3647 | T85: =SUM(M85:P85) -> -316.86857 | U85: =SUM(U82:U84) -> -312.71927 | V85: =SUM(V82:V84) -> -308.11503
A86: FX effect | B86: $m | C86: =Historicals!C64/1000 -> 11.019 | D86: =Historicals!D64/1000 -> -16.343 | E86: =Historicals!E64/1000 -> 3.299 | F86: =Historicals!F64/1000 -> 9.076 | G86: =Historicals!G64/1000 -> -1.366 | H86: =Historicals!H64/1000 -> 2.484 | I86: =Historicals!I64/1000 -> -7.314 | J86: =Historicals!J64/1000 -> -3.314 | K86: =0 -> 0 | L86: =0 -> 0 | M86: =0 -> 0 | N86: =0 -> 0 | O86: =0 -> 0 | P86: =0 -> 0 | R86: =SUM(E86:H86) -> 13.493 | S86: =SUM(I86:L86) -> -10.628 | T86: =SUM(M86:P86) -> 0 | U86: =0 -> 0 | V86: =0 -> 0
A87: Net change in cash | B87: $m | C87: =C78+C81+C85+C86 -> 406.346 | D87: =D78+D81+D85+D86 -> -666.093 | E87: =E78+E81+E85+E86 -> 356.413 | F87: =F78+F81+F85+F86 -> -340.919 | G87: =G78+G81+G85+G86 -> 70.22 | H87: =H78+H81+H85+H86 -> 1265.176 | I87: =I78+I81+I85+I86 -> -1286.676 | J87: =J78+J81+J85+J86 -> 90.721 | ... P87: =P78+P81+P85+P86 -> -175.98557 | R87: =SUM(E87:H87) -> 1350.89 | S87: =SUM(I87:L87) -> -1497.3443 | T87: =SUM(M87:P87) -> -27.350649 | U87: =U78+U81+U85+U86 -> 27.994687 | V87: =V78+V81+V85+V86 -> 81.052339
A88: Free cash flow (CFO - capex) | B88: $m | C88: =C78+C79 -> 300.424 | D88: =D78+D79 -> 77.039 | E88: =E78+E79 -> 111.561 | F88: =F78+F79 -> 332.371 | G88: =G78+G79 -> -129.119 | H88: =H78+H79 -> 100.43 | I88: =I78+I79 -> -259.813 | J88: =J78+J79 -> 155.434 | ... P88: =P78+P79 -> -97.419633 | R88: =SUM(E88:H88) -> 415.243 | S88: =SUM(I88:L88) -> -246.30765 | T88: =SUM(M88:P88) -> 289.51792 | U88: =U78+U79 -> 340.71395 | V88: =V78+V79 -> 389.16737
A90: Returns (ROIC)
A91: NOPAT (consolidated op. income x (1 - tax)) | B91: $m | R91: =R33*(1-Inputs!$E$29) -> 297.70895 | S91: =S33*(1-Inputs!$E$29) -> 63.041657 | T91: =T33*(1-Inputs!$E$29) -> 205.45237 | U91: =U33*(1-Inputs!$E$29) -> 271.10968 | V91: =V33*(1-Inputs!$E$29) -> 318.21121
A92: Invested capital (equity + debt - cash) | B92: $m | C92: =C66+C64-C56 -> 9010.345 | D92: =D66+D64-D56 -> 8566.712 | E92: =E66+E64-E56 -> 8571.62 | F92: =F66+F64-F56 -> 8668.322 | G92: =G66+G64-G56 -> 7189.299 | H92: =H66+H64-H56 -> 3312.218 | I92: =I66+I64-I56 -> 3655.505 | J92: =J66+J64-J56 -> 3729.105 | ... P92: =P66+P64-P56 -> 3907.7797 | R92: =R66+R64-R56 -> 3312.218 | S92: =S66+S64-S56 -> 3902.2532 | T92: =T66+T64-T56 -> 3907.7797 | U92: =U66+U64-U56 -> 3927.7674 | V92: =V66+V64-V56 -> 3946.4032
A93: ROIC (on average invested capital) | B93: % | R93: =R91/AVERAGE(D92,R92) -> 0.050123866 | S93: =S91/AVERAGE(R92,S92) -> 0.017476446 | T93: =T91/AVERAGE(S92,T92) -> 0.052612421 | U93: =U91/AVERAGE(T92,U92) -> 0.069199936 | V93: =V91/AVERAGE(U92,V92) -> 0.080824057
A94: HDMC NOPAT | B94: $m | R94: =R26*(1-Inputs!$E$29) -> -22.1221 | S94: =S26*(1-Inputs!$E$29) -> 66.891657 | T94: =T26*(1-Inputs!$E$29) -> 190.05237 | U94: =U26*(1-Inputs!$E$29) -> 236.45968 | V94: =V26*(1-Inputs!$E$29) -> 272.01121
A95: HDMC operating capital (AR + inventory + LT assets - AP) | B95: $m | C95: =C57+C59+C61-C63 -> 1694.481 | D95: =D57+D59+D61-D63 -> 1715.574 | E95: =E57+E59+E61-E63 -> 1541.978 | F95: =F57+F59+F61-F63 -> 1618.901 | G95: =G57+G59+G61-G63 -> 1506.527 | H95: =H57+H59+H61-H63 -> 1634.27 | I95: =I57+I59+I61-I63 -> 1351.335 | J95: =J57+J59+J61-J63 -> 1421.056 | ... P95: =P57+P59+P61-P63 -> 1599.7307 | R95: =R57+R59+R61-R63 -> 1634.27 | S95: =S57+S59+S61-S63 -> 1594.2042 | T95: =T57+T59+T61-T63 -> 1599.7307 | U95: =U57+U59+U61-U63 -> 1619.7184 | V95: =V57+V59+V61-V63 -> 1638.3542
A96: HDMC ROIC | B96: % | R96: =R94/R95 -> -0.01353638 | S96: =S94/S95 -> 0.041959277 | T96: =T94/T95 -> 0.11880273 | U96: =U94/U95 -> 0.14598814 | V96: =V94/V95 -> 0.1660271
A97: ROE (net income to HOG / avg equity) | B97: % | S97: =S41/AVERAGE(R66,S66) -> 0.038901518 | T97: =T41/AVERAGE(S66,T66) -> 0.087942954 | U97: =U41/AVERAGE(T66,U66) -> 0.10926679 | V97: =V41/AVERAGE(U66,V66) -> 0.12184399
A99: Valuation
A100: FY2027E industrial EBITDA | B100: $m | T100: =T49 -> 363.82126
A101: EV / EBITDA multiple | B101: x | T101: =Inputs!$F$93 -> 8
A102: Industrial EV (multiples) | B102: $m | T102: =MAX(0,T100*T101) -> 2910.5701
A103: FY2027E HDFS after-tax income | B103: $m | T103: =T31*(1-Inputs!$E$29) -> 57.75
A104: HDFS equity value (P/E) | B104: $m | T104: =T103*Inputs!$F$94 -> 635.25
A105: LiveWire stake | B105: $m | T105: =Inputs!$E$49 -> 50
A106: HDMC net cash ex-HDFS | B106: $m | T106: =Inputs!$E$48 -> 985.958
A107: Equity value - multiples SOTP | B107: $m | T107: =T102+T104+T105+T106 -> 4581.7781
...

Sheet Exhibits
A1: Exhibit data for the memo (linked to Base model)
A3: Exhibit 1: Shipments vs. retail, YoY growth, and HDMC gross margin
B4: Q3'24 | C4: Q4'24 | D4: Q1'25 | E4: Q2'25 | F4: Q3'25 | G4: Q4'25 | H4: Q1'26 | I4: Q2'26
A5: Shipments YoY | B5: =Base!C10 -> 0 | C5: =Base!D10 -> 0 | D5: =Base!E10 -> 0 | E5: =Base!F10 -> 0 | F5: =Base!G10 -> 0.32718023 | G5: =Base!H10 -> -0.035331906 | H5: =Base!I10 -> -0.03383332 | I5: =Base!J10 -> 0.094092697
A6: Retail YoY (worldwide) | B6: =Base!C8 -> 0 | C6: =Base!D8 -> 0 | D6: =Base!E8 -> 0 | E6: =Base!F8 -> 0 | F6: =Base!G8 -> -0.060332909 | G6: =Base!H8 -> -0.014536243 | H6: =Base!I8 -> 0.080522412 | I6: =Base!J8 -> 0.0050409429
A7: Shipments - retail (units) | B7: =Base!C11 -> -8646 | C7: =Base!D11 -> -11650 | D7: =Base!E11 -> 7591 | E7: =Base!F11 -> -6417 | F7: =Base!G11 -> 2540 | G7: =Base!H11 -> -11772 | H7: =Base!I11 -> 3788 | I7: =Base!J11 -> -3258
A8: Reported dealer inventory YoY | B8: =Base!C12 -> 0 | C8: =Base!D12 -> 0 | D8: =Base!E12 -> 0 | E8: =Base!F12 -> 0 | F8: =Base!G12 -> -0.13 | G8: =Base!H12 -> -0.17 | H8: =Base!I12 -> -0.22 | I8: =Base!J12 -> -0.17
A9: HDMC gross margin | B9: =Base!C24 -> 0.30101722 | C9: =Base!D24 -> -0.0075388417 | D9: =Base!E24 -> 0.2914864 | E9: =Base!F24 -> 0.28621213 | F9: =Base!G24 -> 0.26361342 | G9: =Base!H24 -> -0.080346524 | H9: =Base!I24 -> 0.25295721 | I9: =Base!J24 -> 0.2754066
A10: Sport & Lightweight share of shipments | B10: =Base!C13 -> 0.06431686 | C10: =Base!D13 -> 0.1076374 | D10: =Base!E13 -> 0.054609984 | E10: =Base!F13 -> 0.088958339 | F10: =Base!G13 -> 0.071952689 | G10: =Base!H13 -> 0.12682205 | H10: =Base!I13 -> 0.10004022 | I10: =Base!J13 -> 0.11775358
A11: HDMC revenue ($m) | B11: =Base!C21 -> 876.405 | C11: =Base!D21 -> 420.489 | D11: =Base!E21 -> 1081.505 | E11: =Base!F21 -> 1043.649 | F11: =Base!G21 -> 1073.959 | G11: =Base!H21 -> 379.195 | H11: =Base!I21 -> 1055.471 | I11: =Base!J21 -> 1104.28
A12: HDMC gross profit ($m) | B12: =Base!C23 -> 263.813 | C12: =Base!D23 -> -3.17 | D12: =Base!E23 -> 315.244 | E12: =Base!F23 -> 298.705 | F12: =Base!G23 -> 283.11 | G12: =Base!H23 -> -30.467 | H12: =Base!I23 -> 266.989 | I12: =Base!J23 -> 304.126
A14: Exhibit 2: Operating leverage - HDMC gross profit vs. revenue (scatter), fitted line from Inputs
A15: Fitted contribution margin | B15: =Inputs!$E$57 -> 0.46742844
A16: Fitted fixed cost per quarter ($m) | B16: =Inputs!$E$58 -> 207.40416
A17: R-squared | B17: =Inputs!$E$59 -> 0.98718031
